Workbook

Sheet Guide
B2: CITY GOVERNMENT OF ORMOC
B3: Institutional Assessment Tool (IAT) for the CDRRMO and Emergency Operations Center
B4: Scoring workbook - companion to the IAT Standards, Policy & Methodology document. Version 1.1 (October 2026), draft for validation with CDRRMO Ormoc. v1.1 adds RA 12287 IRR (signed 14 Sep 2026) requirements and selected UNDRR Scorecard indicators.
B6: HOW TO USE
B7: 1. Fill in the Profile sheet (assessment date, team, informants).
B8: 2. In A_CDRRMO and B_EOC, score each indicator in the yellow 'Score' column using the 0-4 rubric below, or NA if it truly does not apply to Ormoc.
B9: 3. Record the evidence actually seen (document title/date, site observation) in 'Evidence Observed'. No evidence = score of 2 or lower.
B10: 4. Write the gap and recommended action. Priority and compliance status calculate automatically.
B11: 5. Review the Dashboard (domain maturity, mandatory compliance, priority gaps), then complete the Action_Plan sheet for High-priority items.
B12: 6. Validate scores with CDRRMO management in the validation workshop before finalizing. Change only yellow cells; grey/white cells are formulas or reference text.
B14: SCORING RUBRIC (per indicator)
B15: Score | C15: Maturity level | D15: What it looks like | E15: Minimum evidence required
B16: 0 | C16: Absent | D16: Not in place; no plan to establish. | E16: None
B17: 1 | C17: Initial / Ad hoc | D17: Done informally, depends on individuals; not documented. | E17: Verbal account (KII/FGD) only
B18: 2 | C18: Developing | D18: Exists but incomplete, outdated, unapproved or not consistently applied. | E18: Draft or partial document, or observation of partial practice
B19: 3 | C19: Compliant / Established | D19: Meets the legal/policy standard; documented, approved, applied. | E19: Approved document AND proof of use (records, logs, reports)
B20: 4 | C20: Advanced / Institutionalized | D20: Exceeds standard; tested, reviewed and improved regularly; a model for others. | E20: Level 3 evidence PLUS test/exercise/AAR showing review and improvement
B21: NA | C21: Not applicable | D21: Indicator does not apply to Ormoc's context. Excluded from computation. | E21: Written justification in Remarks
B23: AUTOMATIC CALCULATIONS
B24: Domain Maturity Index (0-4) | C24: Weighted average of scored indicators: sum(score x weight) / sum(weight). NA and blanks excluded.
B25: Maturity band | C25: <0.5 Absent | 0.5-1.49 Initial | 1.5-2.49 Developing | 2.5-3.49 Compliant | >=3.5 Advanced
B26: Mandatory Compliance Rate | C26: Share of scored Mandatory (M) indicators rated 3 or 4. Target: 100%.
B27: Gap Priority Score | C27: (4 - score) x weight x 1.5 if Mandatory (x1.0 if Good Practice). High >= 9; Medium 4-8.9; Low < 4.
B28: Weight | C28: 3 = critical to life-safety or legal compliance; 2 = important to effectiveness; 1 = supportive/good practice.
B30: CELL LEGEND
B31: Yellow | C31: Input - assessor fills in
B32: Grey | C32: Formula - do not edit
B34: EXAMPLE OF A COMPLETED ROW (illustrative only)
B35: Indicator | C35: Score | D35: Evidence Observed | E35: Gap / Remarks | F35: Recommended Action
B36: A2.6 24/7 operations capability with documented shift roster | C36: 2 | D36: Roster for Jul-Sep 2026 seen; night shift covered by 1 staff only; logbook gaps on 3 dates. | E36: Night shift below minimum; no handover form. | F36: Adopt 3-shift roster with min. 2 duty officers/shift; introduce handover form (MOO Ch.4).
B39: WHAT CHANGED IN VERSION 1.1
B40: Totals | C40: 125 indicators in Parts A and B (82 CDRRMO, 43 EOC); 79 Mandatory, 46 Good Practice. Up from 108 (73 M / 35 GP).
B41: RA 12287 IRR | C41: 6 new Mandatory indicators (A1.8, A2.9, A6.7, A8.8, A8.9, A10.8) and 6 revised (A1.6, A2.8, A4.6, A6.2, A8.6, B1.2). A4.6 now follows IRR Rule V: AA is charged to up to 10% of the 70% LDRRMF, not to the QRF.
B42: UNDRR Scorecard | C42: 11 new Good Practice indicators adapted from the Detailed Level Scorecard (A2.10, A4.9, A5.7, A5.8, A5.9, A7.8, A7.9, A9.5, A10.9, B5.7, B6.6); A7.6 and A10.2 widened. The DRSC reference sits in the Standard column.
B43: Part C | C43: New C_Interface sheet: 15 indicators owned by other offices (planning, engineering, utilities, environment, health, education, agriculture). Same rubric; separate index on the Dashboard; not counted in the IMI or the Mandatory Compliance Rate.
B44: Crosswalk | C44: The Crosswalk sheet shows how every Scorecard criterion and every IRR provision is treated: New, Modified, Covered, Interface or Deferred to the city-wide Scorecard workshop.

Sheet Dashboard
B2: INSTITUTIONAL ASSESSMENT DASHBOARD - CDRRMO & EOC, CITY OF ORMOC
B3: All values compute from the A_CDRRMO and B_EOC sheets. Maturity Index scale 0-4.
B5: Code | C5: Domain | D5: Indicators | E5: Scored | F5: Maturity Index (0-4) | G5: Maturity Band | H5: Mandatory Compliance | I5: High-priority gaps | J5: Index %
B6: A1 | C6: Legal Mandate & DRRM Governance | D6: =COUNTIF(A_CDRRMO!$B$5:$B$96,B6) -> 8 | E6: =SUMIF(A_CDRRMO!$B$5:$B$96,B6,A_CDRRMO!$S$5:$S$96) -> 8 | F6: =IF(SUMIF(A_CDRRMO!$B$5:$B$96,B6,A_CDRRMO!$R$5:$R$96)=0,"",SUMIF(A_CDRRMO!$B$5:$B$96,B6,A_CDRRMO!$Q$5:$Q$96)/SUMIF(A_CDRRMO!$B$5:$B$96,B6,A_CDRRMO!$R$5:$R$96)*4) -> 2.5882353 | G6: =IF(F6="","",IF(F6<0.5,"Absent",IF(F6<1.5,"Initial",IF(F6<2.5,"Developing",IF(F6<3.5,"Compliant","Advanced"))))) -> Compliant | H6: =IF(SUMIF(A_CDRRMO!$B$5:$B$96,B6,A_CDRRMO!$T$5:$T$96)=0,"",SUMIF(A_CDRRMO!$B$5:$B$96,B6,A_CDRRMO!$U$5:$U$96)/SUMIF(A_CDRRMO!$B$5:$B$96,B6,A_CDRRMO!$T$5:$T$96)) -> 0.5 | I6: =COUNTIFS(A_CDRRMO!$B$5:$B$96,B6,A_CDRRMO!$N$5:$N$96,"High") -> 2 | J6: =IF(F6="",0,F6/4) -> 0.64705882
B7: A2 | C7: Organization, Staffing & Human Resources | D7: =COUNTIF(A_CDRRMO!$B$5:$B$96,B7) -> 10 | E7: =SUMIF(A_CDRRMO!$B$5:$B$96,B7,A_CDRRMO!$S$5:$S$96) -> 10 | F7: =IF(SUMIF(A_CDRRMO!$B$5:$B$96,B7,A_CDRRMO!$R$5:$R$96)=0,"",SUMIF(A_CDRRMO!$B$5:$B$96,B7,A_CDRRMO!$Q$5:$Q$96)/SUMIF(A_CDRRMO!$B$5:$B$96,B7,A_CDRRMO!$R$5:$R$96)*4) -> 1.7727273 | G7: =IF(F7="","",IF(F7<0.5,"Absent",IF(F7<1.5,"Initial",IF(F7<2.5,"Developing",IF(F7<3.5,"Compliant","Advanced"))))) -> Developing | H7: =IF(SUMIF(A_CDRRMO!$B$5:$B$96,B7,A_CDRRMO!$T$5:$T$96)=0,"",SUMIF(A_CDRRMO!$B$5:$B$96,B7,A_CDRRMO!$U$5:$U$96)/SUMIF(A_CDRRMO!$B$5:$B$96,B7,A_CDRRMO!$T$5:$T$96)) -> 0.14285714 | I7: =COUNTIFS(A_CDRRMO!$B$5:$B$96,B7,A_CDRRMO!$N$5:$N$96,"High") -> 5 | J7: =IF(F7="",0,F7/4) -> 0.44318182
B8: A3 | C8: DRRM & Contingency Planning | D8: =COUNTIF(A_CDRRMO!$B$5:$B$96,B8) -> 7 | E8: =SUMIF(A_CDRRMO!$B$5:$B$96,B8,A_CDRRMO!$S$5:$S$96) -> 7 | F8: =IF(SUMIF(A_CDRRMO!$B$5:$B$96,B8,A_CDRRMO!$R$5:$R$96)=0,"",SUMIF(A_CDRRMO!$B$5:$B$96,B8,A_CDRRMO!$Q$5:$Q$96)/SUMIF(A_CDRRMO!$B$5:$B$96,B8,A_CDRRMO!$R$5:$R$96)*4) -> 3.1666667 | G8: =IF(F8="","",IF(F8<0.5,"Absent",IF(F8<1.5,"Initial",IF(F8<2.5,"Developing",IF(F8<3.5,"Compliant","Advanced"))))) -> Compliant | H8: =IF(SUMIF(A_CDRRMO!$B$5:$B$96,B8,A_CDRRMO!$T$5:$T$96)=0,"",SUMIF(A_CDRRMO!$B$5:$B$96,B8,A_CDRRMO!$U$5:$U$96)/SUMIF(A_CDRRMO!$B$5:$B$96,B8,A_CDRRMO!$T$5:$T$96)) -> 0.66666667 | I8: =COUNTIFS(A_CDRRMO!$B$5:$B$96,B8,A_CDRRMO!$N$5:$N$96,"High") -> 1 | J8: =IF(F8="",0,F8/4) -> 0.79166667
B9: A4 | C9: DRRM Financing & Fund Management | D9: =COUNTIF(A_CDRRMO!$B$5:$B$96,B9) -> 9 | E9: =SUMIF(A_CDRRMO!$B$5:$B$96,B9,A_CDRRMO!$S$5:$S$96) -> 8 | F9: =IF(SUMIF(A_CDRRMO!$B$5:$B$96,B9,A_CDRRMO!$R$5:$R$96)=0,"",SUMIF(A_CDRRMO!$B$5:$B$96,B9,A_CDRRMO!$Q$5:$Q$96)/SUMIF(A_CDRRMO!$B$5:$B$96,B9,A_CDRRMO!$R$5:$R$96)*4) -> 3.1176471 | G9: =IF(F9="","",IF(F9<0.5,"Absent",IF(F9<1.5,"Initial",IF(F9<2.5,"Developing",IF(F9<3.5,"Compliant","Advanced"))))) -> Compliant | H9: =IF(SUMIF(A_CDRRMO!$B$5:$B$96,B9,A_CDRRMO!$T$5:$T$96)=0,"",SUMIF(A_CDRRMO!$B$5:$B$96,B9,A_CDRRMO!$U$5:$U$96)/SUMIF(A_CDRRMO!$B$5:$B$96,B9,A_CDRRMO!$T$5:$T$96)) -> 0.83333333 | I9: =COUNTIFS(A_CDRRMO!$B$5:$B$96,B9,A_CDRRMO!$N$5:$N$96,"High") -> 1 | J9: =IF(F9="",0,F9/4) -> 0.77941176
B10: A5 | C10: Risk Assessment, Data & Knowledge Management | D10: =COUNTIF(A_CDRRMO!$B$5:$B$96,B10) -> 9 | E10: =SUMIF(A_CDRRMO!$B$5:$B$96,B10,A_CDRRMO!$S$5:$S$96) -> 9 | F10: =IF(SUMIF(A_CDRRMO!$B$5:$B$96,B10,A_CDRRMO!$R$5:$R$96)=0,"",SUMIF(A_CDRRMO!$B$5:$B$96,B10,A_CDRRMO!$Q$5:$Q$96)/SUMIF(A_CDRRMO!$B$5:$B$96,B10,A_CDRRMO!$R$5:$R$96)*4) -> 2.0555556 | G10: =IF(F10="","",IF(F10<0.5,"Absent",IF(F10<1.5,"Initial",IF(F10<2.5,"Developing",IF(F10<3.5,"Compliant","Advanced"))))) -> Developing | H10: =IF(SUMIF(A_CDRRMO!$B$5:$B$96,B10,A_CDRRMO!$T$5:$T$96)=0,"",SUMIF(A_CDRRMO!$B$5:$B$96,B10,A_CDRRMO!$U$5:$U$96)/SUMIF(A_CDRRMO!$B$5:$B$96,B10,A_CDRRMO!$T$5:$T$96)) -> 0.75 | I10: =COUNTIFS(A_CDRRMO!$B$5:$B$96,B10,A_CDRRMO!$N$5:$N$96,"High") -> 0 | J10: =IF(F10="",0,F10/4) -> 0.51388889
B11: A6 | C11: Early Warning & Risk Communication | D11: =COUNTIF(A_CDRRMO!$B$5:$B$96,B11) -> 7 | E11: =SUMIF(A_CDRRMO!$B$5:$B$96,B11,A_CDRRMO!$S$5:$S$96) -> 7 | F11: =IF(SUMIF(A_CDRRMO!$B$5:$B$96,B11,A_CDRRMO!$R$5:$R$96)=0,"",SUMIF(A_CDRRMO!$B$5:$B$96,B11,A_CDRRMO!$Q$5:$Q$96)/SUMIF(A_CDRRMO!$B$5:$B$96,B11,A_CDRRMO!$R$5:$R$96)*4) -> 2.2666667 | G11: =IF(F11="","",IF(F11<0.5,"Absent",IF(F11<1.5,"Initial",IF(F11<2.5,"Developing",IF(F11<3.5,"Compliant","Advanced"))))) -> Developing | H11: =IF(SUMIF(A_CDRRMO!$B$5:$B$96,B11,A_CDRRMO!$T$5:$T$96)=0,"",SUMIF(A_CDRRMO!$B$5:$B$96,B11,A_CDRRMO!$U$5:$U$96)/SUMIF(A_CDRRMO!$B$5:$B$96,B11,A_CDRRMO!$T$5:$T$96)) -> 0.25 | I11: =COUNTIFS(A_CDRRMO!$B$5:$B$96,B11,A_CDRRMO!$N$5:$N$96,"High") -> 3 | J11: =IF(F11="",0,F11/4) -> 0.56666667
B12: A7 | C12: Preparedness & Community Capacity | D12: =COUNTIF(A_CDRRMO!$B$5:$B$96,B12) -> 9 | E12: =SUMIF(A_CDRRMO!$B$5:$B$96,B12,A_CDRRMO!$S$5:$S$96) -> 8 | F12: =IF(SUMIF(A_CDRRMO!$B$5:$B$96,B12,A_CDRRMO!$R$5:$R$96)=0,"",SUMIF(A_CDRRMO!$B$5:$B$96,B12,A_CDRRMO!$Q$5:$Q$96)/SUMIF(A_CDRRMO!$B$5:$B$96,B12,A_CDRRMO!$R$5:$R$96)*4) -> 2.9333333 | G12: =IF(F12="","",IF(F12<0.5,"Absent",IF(F12<1.5,"Initial",IF(F12<2.5,"Developing",IF(F12<3.5,"Compliant","Advanced"))))) -> Compliant | H12: =IF(SUMIF(A_CDRRMO!$B$5:$B$96,B12,A_CDRRMO!$T$5:$T$96)=0,"",SUMIF(A_CDRRMO!$B$5:$B$96,B12,A_CDRRMO!$U$5:$U$96)/SUMIF(A_CDRRMO!$B$5:$B$96,B12,A_CDRRMO!$T$5:$T$96)) -> 0.8 | I12: =COUNTIFS(A_CDRRMO!$B$5:$B$96,B12,A_CDRRMO!$N$5:$N$96,"High") -> 1 | J12: =IF(F12="",0,F12/4) -> 0.73333333
B13: A8 | C13: Response Capability | D13: =COUNTIF(A_CDRRMO!$B$5:$B$96,B13) -> 9 | E13: =SUMIF(A_CDRRMO!$B$5:$B$96,B13,A_CDRRMO!$S$5:$S$96) -> 9 | F13: =IF(SUMIF(A_CDRRMO!$B$5:$B$96,B13,A_CDRRMO!$R$5:$R$96)=0,"",SUMIF(A_CDRRMO!$B$5:$B$96,B13,A_CDRRMO!$Q$5:$Q$96)/SUMIF(A_CDRRMO!$B$5:$B$96,B13,A_CDRRMO!$R$5:$R$96)*4) -> 1.6818182 | G13: =IF(F13="","",IF(F13<0.5,"Absent",IF(F13<1.5,"Initial",IF(F13<2.5,"Developing",IF(F13<3.5,"Compliant","Advanced"))))) -> Developing | H13: =IF(SUMIF(A_CDRRMO!$B$5:$B$96,B13,A_CDRRMO!$T$5:$T$96)=0,"",SUMIF(A_CDRRMO!$B$5:$B$96,B13,A_CDRRMO!$U$5:$U$96)/SUMIF(A_CDRRMO!$B$5:$B$96,B13,A_CDRRMO!$T$5:$T$96)) -> 0.375 | I13: =COUNTIFS(A_CDRRMO!$B$5:$B$96,B13,A_CDRRMO!$N$5:$N$96,"High") -> 5 | J13: =IF(F13="",0,F13/4) -> 0.42045455
B14: A9 | C14: Rehabilitation & Recovery | D14: =COUNTIF(A_CDRRMO!$B$5:$B$96,B14) -> 5 | E14: =SUMIF(A_CDRRMO!$B$5:$B$96,B14,A_CDRRMO!$S$5:$S$96) -> 5 | F14: =IF(SUMIF(A_CDRRMO!$B$5:$B$96,B14,A_CDRRMO!$R$5:$R$96)=0,"",SUMIF(A_CDRRMO!$B$5:$B$96,B14,A_CDRRMO!$Q$5:$Q$96)/SUMIF(A_CDRRMO!$B$5:$B$96,B14,A_CDRRMO!$R$5:$R$96)*4) -> 1.875 | G14: =IF(F14="","",IF(F14<0.5,"Absent",IF(F14<1.5,"Initial",IF(F14<2.5,"Developing",IF(F14<3.5,"Compliant","Advanced"))))) -> Developing | H14: =IF(SUMIF(A_CDRRMO!$B$5:$B$96,B14,A_CDRRMO!$T$5:$T$96)=0,"",SUMIF(A_CDRRMO!$B$5:$B$96,B14,A_CDRRMO!$U$5:$U$96)/SUMIF(A_CDRRMO!$B$5:$B$96,B14,A_CDRRMO!$T$5:$T$96)) -> 1 | I14: =COUNTIFS(A_CDRRMO!$B$5:$B$96,B14,A_CDRRMO!$N$5:$N$96,"High") -> 0 | J14: =IF(F14="",0,F14/4) -> 0.46875
B15: A10 | C15: Partnerships, M&E & Accountability | D15: =COUNTIF(A_CDRRMO!$B$5:$B$96,B15) -> 9 | E15: =SUMIF(A_CDRRMO!$B$5:$B$96,B15,A_CDRRMO!$S$5:$S$96) -> 9 | F15: =IF(SUMIF(A_CDRRMO!$B$5:$B$96,B15,A_CDRRMO!$R$5:$R$96)=0,"",SUMIF(A_CDRRMO!$B$5:$B$96,B15,A_CDRRMO!$Q$5:$Q$96)/SUMIF(A_CDRRMO!$B$5:$B$96,B15,A_CDRRMO!$R$5:$R$96)*4) -> 2.5 | G15: =IF(F15="","",IF(F15<0.5,"Absent",IF(F15<1.5,"Initial",IF(F15<2.5,"Developing",IF(F15<3.5,"Compliant","Advanced"))))) -> Compliant | H15: =IF(SUMIF(A_CDRRMO!$B$5:$B$96,B15,A_CDRRMO!$T$5:$T$96)=0,"",SUMIF(A_CDRRMO!$B$5:$B$96,B15,A_CDRRMO!$U$5:$U$96)/SUMIF(A_CDRRMO!$B$5:$B$96,B15,A_CDRRMO!$T$5:$T$96)) -> 0.5 | I15: =COUNTIFS(A_CDRRMO!$B$5:$B$96,B15,A_CDRRMO!$N$5:$N$96,"High") -> 1 | J15: =IF(F15="",0,F15/4) -> 0.625
B16: B1 | C16: EOC Legal Basis & Concept of Operations | D16: =COUNTIF(B_EOC!$B$5:$B$54,B16) -> 5 | E16: =SUMIF(B_EOC!$B$5:$B$54,B16,B_EOC!$S$5:$S$54) -> 5 | F16: =IF(SUMIF(B_EOC!$B$5:$B$54,B16,B_EOC!$R$5:$R$54)=0,"",SUMIF(B_EOC!$B$5:$B$54,B16,B_EOC!$Q$5:$Q$54)/SUMIF(B_EOC!$B$5:$B$54,B16,B_EOC!$R$5:$R$54)*4) -> 1.8461538 | G16: =IF(F16="","",IF(F16<0.5,"Absent",IF(F16<1.5,"Initial",IF(F16<2.5,"Developing",IF(F16<3.5,"Compliant","Advanced"))))) -> Developing | H16: =IF(SUMIF(B_EOC!$B$5:$B$54,B16,B_EOC!$T$5:$T$54)=0,"",SUMIF(B_EOC!$B$5:$B$54,B16,B_EOC!$U$5:$U$54)/SUMIF(B_EOC!$B$5:$B$54,B16,B_EOC!$T$5:$T$54)) -> 0 | I16: =COUNTIFS(B_EOC!$B$5:$B$54,B16,B_EOC!$N$5:$N$54,"High") -> 4 | J16: =IF(F16="",0,F16/4) -> 0.46153846
B17: B2 | C17: EOC Facility, Site & Resilience | D17: =COUNTIF(B_EOC!$B$5:$B$54,B17) -> 7 | E17: =SUMIF(B_EOC!$B$5:$B$54,B17,B_EOC!$S$5:$S$54) -> 0 | F17: =IF(SUMIF(B_EOC!$B$5:$B$54,B17,B_EOC!$R$5:$R$54)=0,"",SUMIF(B_EOC!$B$5:$B$54,B17,B_EOC!$Q$5:$Q$54)/SUMIF(B_EOC!$B$5:$B$54,B17,B_EOC!$R$5:$R$54)*4) | G17: =IF(F17="","",IF(F17<0.5,"Absent",IF(F17<1.5,"Initial",IF(F17<2.5,"Developing",IF(F17<3.5,"Compliant","Advanced"))))) | H17: =IF(SUMIF(B_EOC!$B$5:$B$54,B17,B_EOC!$T$5:$T$54)=0,"",SUMIF(B_EOC!$B$5:$B$54,B17,B_EOC!$U$5:$U$54)/SUMIF(B_EOC!$B$5:$B$54,B17,B_EOC!$T$5:$T$54)) | I17: =COUNTIFS(B_EOC!$B$5:$B$54,B17,B_EOC!$N$5:$N$54,"High") -> 0 | J17: =IF(F17="",0,F17/4) -> 0
B18: B3 | C18: EOC Communications & ICT | D18: =COUNTIF(B_EOC!$B$5:$B$54,B18) -> 6 | E18: =SUMIF(B_EOC!$B$5:$B$54,B18,B_EOC!$S$5:$S$54) -> 2 | F18: =IF(SUMIF(B_EOC!$B$5:$B$54,B18,B_EOC!$R$5:$R$54)=0,"",SUMIF(B_EOC!$B$5:$B$54,B18,B_EOC!$Q$5:$Q$54)/SUMIF(B_EOC!$B$5:$B$54,B18,B_EOC!$R$5:$R$54)*4) -> 2 | G18: =IF(F18="","",IF(F18<0.5,"Absent",IF(F18<1.5,"Initial",IF(F18<2.5,"Developing",IF(F18<3.5,"Compliant","Advanced"))))) -> Developing | H18: =IF(SUMIF(B_EOC!$B$5:$B$54,B18,B_EOC!$T$5:$T$54)=0,"",SUMIF(B_EOC!$B$5:$B$54,B18,B_EOC!$U$5:$U$54)/SUMIF(B_EOC!$B$5:$B$54,B18,B_EOC!$T$5:$T$54)) -> 0 | I18: =COUNTIFS(B_EOC!$B$5:$B$54,B18,B_EOC!$N$5:$N$54,"High") -> 1 | J18: =IF(F18="",0,F18/4) -> 0.5
B19: B4 | C19: EOC Organization & Staffing | D19: =COUNTIF(B_EOC!$B$5:$B$54,B19) -> 6 | E19: =SUMIF(B_EOC!$B$5:$B$54,B19,B_EOC!$S$5:$S$54) -> 5 | F19: =IF(SUMIF(B_EOC!$B$5:$B$54,B19,B_EOC!$R$5:$R$54)=0,"",SUMIF(B_EOC!$B$5:$B$54,B19,B_EOC!$Q$5:$Q$54)/SUMIF(B_EOC!$B$5:$B$54,B19,B_EOC!$R$5:$R$54)*4) -> 1.4 | G19: =IF(F19="","",IF(F19<0.5,"Absent",IF(F19<1.5,"Initial",IF(F19<2.5,"Developing",IF(F19<3.5,"Compliant","Advanced"))))) -> Initial | H19: =IF(SUMIF(B_EOC!$B$5:$B$54,B19,B_EOC!$T$5:$T$54)=0,"",SUMIF(B_EOC!$B$5:$B$54,B19,B_EOC!$U$5:$U$54)/SUMIF(B_EOC!$B$5:$B$54,B19,B_EOC!$T$5:$T$54)) -> 0 | I19: =COUNTIFS(B_EOC!$B$5:$B$54,B19,B_EOC!$N$5:$N$54,"High") -> 1 | J19: =IF(F19="",0,F19/4) -> 0.35
B20: B5 | C20: Information Management & Reporting | D20: =COUNTIF(B_EOC!$B$5:$B$54,B20) -> 7 | E20: =SUMIF(B_EOC!$B$5:$B$54,B20,B_EOC!$S$5:$S$54) -> 5 | F20: =IF(SUMIF(B_EOC!$B$5:$B$54,B20,B_EOC!$R$5:$R$54)=0,"",SUMIF(B_EOC!$B$5:$B$54,B20,B_EOC!$Q$5:$Q$54)/SUMIF(B_EOC!$B$5:$B$54,B20,B_EOC!$R$5:$R$54)*4) -> 1.4545455 | G20: =IF(F20="","",IF(F20<0.5,"Absent",IF(F20<1.5,"Initial",IF(F20<2.5,"Developing",IF(F20<3.5,"Compliant","Advanced"))))) -> Initial | H20: =IF(SUMIF(B_EOC!$B$5:$B$54,B20,B_EOC!$T$5:$T$54)=0,"",SUMIF(B_EOC!$B$5:$B$54,B20,B_EOC!$U$5:$U$54)/SUMIF(B_EOC!$B$5:$B$54,B20,B_EOC!$T$5:$T$54)) -> 0 | I20: =COUNTIFS(B_EOC!$B$5:$B$54,B20,B_EOC!$N$5:$N$54,"High") -> 2 | J20: =IF(F20="",0,F20/4) -> 0.36363636
B21: B6 | C21: Coordination & Resource Management | D21: =COUNTIF(B_EOC!$B$5:$B$54,B21) -> 6 | E21: =SUMIF(B_EOC!$B$5:$B$54,B21,B_EOC!$S$5:$S$54) -> 5 | F21: =IF(SUMIF(B_EOC!$B$5:$B$54,B21,B_EOC!$R$5:$R$54)=0,"",SUMIF(B_EOC!$B$5:$B$54,B21,B_EOC!$Q$5:$Q$54)/SUMIF(B_EOC!$B$5:$B$54,B21,B_EOC!$R$5:$R$54)*4) -> 1.2727273 | G21: =IF(F21="","",IF(F21<0.5,"Absent",IF(F21<1.5,"Initial",IF(F21<2.5,"Developing",IF(F21<3.5,"Compliant","Advanced"))))) -> Initial | H21: =IF(SUMIF(B_EOC!$B$5:$B$54,B21,B_EOC!$T$5:$T$54)=0,"",SUMIF(B_EOC!$B$5:$B$54,B21,B_EOC!$U$5:$U$54)/SUMIF(B_EOC!$B$5:$B$54,B21,B_EOC!$T$5:$T$54)) -> 0 | I21: =COUNTIFS(B_EOC!$B$5:$B$54,B21,B_EOC!$N$5:$N$54,"High") -> 2 | J21: =IF(F21="",0,F21/4) -> 0.31818182
B22: B7 | C22: EOC SOPs, Training, Exercises & Continuity | D22: =COUNTIF(B_EOC!$B$5:$B$54,B22) -> 6 | E22: =SUMIF(B_EOC!$B$5:$B$54,B22,B_EOC!$S$5:$S$54) -> 6 | F22: =IF(SUMIF(B_EOC!$B$5:$B$54,B22,B_EOC!$R$5:$R$54)=0,"",SUMIF(B_EOC!$B$5:$B$54,B22,B_EOC!$Q$5:$Q$54)/SUMIF(B_EOC!$B$5:$B$54,B22,B_EOC!$R$5:$R$54)*4) -> 2.0833333 | G22: =IF(F22="","",IF(F22<0.5,"Absent",IF(F22<1.5,"Initial",IF(F22<2.5,"Developing",IF(F22<3.5,"Compliant","Advanced"))))) -> Developing | H22: =IF(SUMIF(B_EOC!$B$5:$B$54,B22,B_EOC!$T$5:$T$54)=0,"",SUMIF(B_EOC!$B$5:$B$54,B22,B_EOC!$U$5:$U$54)/SUMIF(B_EOC!$B$5:$B$54,B22,B_EOC!$T$5:$T$54)) -> 0.25 | I22: =COUNTIFS(B_EOC!$B$5:$B$54,B22,B_EOC!$N$5:$N$54,"High") -> 1 | J22: =IF(F22="",0,F22/4) -> 0.52083333
C24: PART A - CDRRMO OVERALL | D24: =COUNTA(A_CDRRMO!$B$5:$B$96) -> 82 | E24: =SUM(A_CDRRMO!$S$5:$S$96) -> 80 | F24: =IF((SUM(A_CDRRMO!$R$5:$R$96))=0,"",(SUM(A_CDRRMO!$Q$5:$Q$96))/(SUM(A_CDRRMO!$R$5:$R$96))*4) -> 2.3795181 | G24: =IF(F24="","",IF(F24<0.5,"Absent",IF(F24<1.5,"Initial",IF(F24<2.5,"Developing",IF(F24<3.5,"Compliant","Advanced"))))) -> Developing | H24: =IF((SUM(A_CDRRMO!$T$5:$T$96))=0,"",(SUM(A_CDRRMO!$U$5:$U$96))/(SUM(A_CDRRMO!$T$5:$T$96))) -> 0.52941176 | I24: =COUNTIF(A_CDRRMO!$N$5:$N$96,"High") -> 19 | J24: =IF(F24="",0,F24/4) -> 0.59487952
C25: PART B - EOC OVERALL | D25: =COUNTA(B_EOC!$B$5:$B$54) -> 43 | E25: =SUM(B_EOC!$S$5:$S$54) -> 28 | F25: =IF((SUM(B_EOC!$R$5:$R$54))=0,"",(SUM(B_EOC!$Q$5:$Q$54))/(SUM(B_EOC!$R$5:$R$54))*4) -> 1.6612903 | G25: =IF(F25="","",IF(F25<0.5,"Absent",IF(F25<1.5,"Initial",IF(F25<2.5,"Developing",IF(F25<3.5,"Compliant","Advanced"))))) -> Developing | H25: =IF((SUM(B_EOC!$T$5:$T$54))=0,"",(SUM(B_EOC!$U$5:$U$54))/(SUM(B_EOC!$T$5:$T$54))) -> 0.05 | I25: =COUNTIF(B_EOC!$N$5:$N$54,"High") -> 11 | J25: =IF(F25="",0,F25/4) -> 0.41532258
C26: INSTITUTIONAL MATURITY INDEX (A+B) | D26: =COUNTA(A_CDRRMO!$B$5:$B$96)+COUNTA(B_EOC!$B$5:$B$54) -> 125 | E26: =SUM(A_CDRRMO!$S$5:$S$96)+SUM(B_EOC!$S$5:$S$54) -> 108 | F26: =IF((SUM(A_CDRRMO!$R$5:$R$96)+SUM(B_EOC!$R$5:$R$54))=0,"",(SUM(A_CDRRMO!$Q$5:$Q$96)+SUM(B_EOC!$Q$5:$Q$54))/(SUM(A_CDRRMO!$R$5:$R$96)+SUM(B_EOC!$R$5:$R$54))*4) -> 2.1842105 | G26: =IF(F26="","",IF(F26<0.5,"Absent",IF(F26<1.5,"Initial",IF(F26<2.5,"Developing",IF(F26<3.5,"Compliant","Advanced"))))) -> Developing | H26: =IF((SUM(A_CDRRMO!$T$5:$T$96)+SUM(B_EOC!$T$5:$T$54))=0,"",(SUM(A_CDRRMO!$U$5:$U$96)+SUM(B_EOC!$U$5:$U$54))/(SUM(A_CDRRMO!$T$5:$T$96)+SUM(B_EOC!$T$5:$T$54))) -> 0.3943662 | I26: =COUNTIF(A_CDRRMO!$N$5:$N$96,"High")+COUNTIF(B_EOC!$N$5:$N$54,"High") -> 30 | J26: =IF(F26="",0,F26/4) -> 0.54605263
C27: PART C - INTERFACE INDEX (separate; not in IMI) | D27: =COUNTA(C_Interface!$B$5:$B$24) -> 15 | E27: =SUM(C_Interface!$S$5:$S$24) -> 7 | F27: =IF(SUM(C_Interface!$R$5:$R$24)=0,"",SUM(C_Interface!$Q$5:$Q$24)/SUM(C_Interface!$R$5:$R$24)*4) -> 1.2857143 | G27: =IF(F27="","",IF(F27<0.5,"Absent",IF(F27<1.5,"Initial",IF(F27<2.5,"Developing",IF(F27<3.5,"Compliant","Advanced"))))) -> Initial | H27: n/a | I27: =COUNTIF(C_Interface!$N$5:$N$24,"High") -> 1 | J27: =IF(F27="",0,F27/4) -> 0.32142857
B28: Notes: 'Indicators' counts all indicators in the domain; 'Scored' excludes NA and blank. Mandatory Compliance = share of scored Mandatory indicators rated 3-4. A domain is considered compliant only when Mandatory Compliance is 100%. Part C (interface) is scored with the same rubric but reported separately because the items are owned by other offices.

Sheet Profile
B2: ASSESSMENT PROFILE
B4: LGU | C4: City of Ormoc
B5: Province / Region | C5: Leyte / Region VIII (Eastern Visayas)
B6: Income class / LGU type | C6: 1st-class independent component city (ICC)
B7: Number of barangays | C7: 85 (PSA PSGC since 4Q 2022; City Ord. No. 052 s.2021, plebiscite 8 Oct 2022). The DRRM 10-Year Plan still shows 110.
B8: Office assessed | C8: City DRRM Office and City Emergency Operations Center
B9: CDRRMO Head | C9: Ciriaco Tolibao
B10: Assessment period (from - to) | C10: October 2026 (field scoring by the CDRRMO team; desk review completed 30 Oct 2026)
B11: Lead assessor | C11: Alvin M. Silva, Development of MOP on EOC and DRRM Consultant
B12: Assessment team members | C12: CDRRMO Planning, Operations and Admin section staff (names to be entered by the City)
B13: Key informants interviewed (names/positions) | C13: Positions only, per RA 10173: CDRRMO section staff (FGDs). CPDO KII pending (A5.5, A5.6). Names kept in the lead assessor's field notes, not in this workbook.
B14: FGD groups conducted | C14: 3 FGDs: CDRRMO Planning Section, Operations Section, Admin Section
B15: Sites inspected | C15: None yet. Pending: EOC/OpCen facility, warehouse, sampled evacuation centers (Part B OBS/TST)
... B18: Validated by (name/position) | C18: Pending
B20: Pre-filled values come from the consultancy scope; confirm or correct them with CDRRMO.

Sheet A_CDRRMO
A1: PART A - CDRRMO INSTITUTIONAL CAPACITY ASSESSMENT
A2: Score in yellow cells only. Type: M = Mandatory (legal/policy compliance), GP = Good practice. Methods: DR document review, KII interview, FGD focus group, OBS observation, TST test/demonstration.
A4: ID | B4: Domain | C4: Indicator | D4: Standard / Policy Reference | E4: Type (M/GP) | F4: Means of Verification | G4: Method | H4: Weight | I4: Score (0-4/NA) | J4: Evidence Observed | K4: Gap / Remarks | L4: Recommended Action | M4: Gap Priority Score | N4: Priority | O4: Compliance Status | P4: Feeds Manual Chapter | Q4: w*score | R4: w*4 | S4: Scored | T4: M scored | U4: M compliant
A5: A1 LEGAL MANDATE & DRRM GOVERNANCE - CDRRMC/CDRRMO legal basis, council functionality, policy instruments
A6: A1.1 | B6: A1 | C6: City ordinance/EO creating the CDRRMO as a regular office (not ad hoc), with defined functions mirroring RA 10121 Sec. 12(c) | D6: RA 10121 Sec. 12; IRR Rule 6; JMC 2014-1 | E6: M | F6: Ordinance/EO; Sangguniang Panlungsod records | G6: DR | H6: 3 | I6: 2 | J6: F: EO covers both the CDRRMO and BDRRMOs and follows minimum requirements; amended, but no ordinance on BDRRMOs. DR: 10-Yr Plan lists hiring of 4+4+2 CDRRMO plantilla positions, so the office is not yet staffed as a full department. | K6: No ordinance establishing the CDRRMO as a regular department with JMC 2014-1 divisions; the EO is the only basis. (Field FGD notes formerly typed here were moved to A2.4, A2.6, A2.10 and B6.1.) | L6: Draft an ordinance creating the CDRRMO as a regular department with Admin & Training, Research & Planning and Operations & Warning divisions and their functions (RA 10121 Sec. 12(c); JMC 2014-1). Attach the organogram and staffing pattern from MOO Ch.2. | M6: =IF(ISNUMBER(I6),(4-I6)*H6*IF(E6="M",1.5,1),"") -> 9 | N6: =IF(M6="","",IF(M6>=9,"High",IF(M6>=4,"Medium","Low"))) -> High | O6: =IF(NOT(ISNUMBER(I6)),IF(I6="NA","N/A","Not scored"),IF(E6="M",IF(I6>=3,"Compliant","Non-compliant"),IF(I6>=3,"Meets GP","Below GP"))) -> Non-compliant | P6: MOO Ch.1 Legal & Institutional Framework | Q6: =IF(ISNUMBER(I6),I6*H6,0) -> 6 | R6: =IF(ISNUMBER(I6),4*H6,0) -> 12 | S6: =IF(ISNUMBER(I6),1,0) -> 1 | T6: =IF(AND(E6="M",ISNUMBER(I6)),1,0) -> 1 | U6: =IF(AND(E6="M",ISNUMBER(I6)),IF(I6>=3,1,0),0) -> 0
A7: A1.2 | B7: A1 | C7: CDRRMC constituted with complete membership per RA 10121 Sec. 11 (incl. CSO and private sector reps) | D7: RA 10121 Sec. 11 | E7: M | F7: EO on CDRRMC composition; list of members | G7: DR | H7: 2 | I7: 2 | J7: F: CDRRMC EO needs updating to cover the mandated representations; minimum of 4 CSO seats not yet met. | K7: Composition incomplete against RA 10121 Sec. 11 (incl. CSO and private-sector seats). (Operations FGD notes formerly here were moved to B6.1 and B7.1.) | L7: Issue an updated EO on CDRRMC composition listing every RA 10121 Sec. 11 seat by office, with at least 4 accredited CSOs and a private-sector seat (e.g., EDC). Record the roster as an MOO Ch.1 annex and review it yearly. | M7: =IF(ISNUMBER(I7),(4-I7)*H7*IF(E7="M",1.5,1),"") -> 6 | N7: =IF(M7="","",IF(M7>=9,"High",IF(M7>=4,"Medium","Low"))) -> Medium | O7: =IF(NOT(ISNUMBER(I7)),IF(I7="NA","N/A","Not scored"),IF(E7="M",IF(I7>=3,"Compliant","Non-compliant"),IF(I7>=3,"Meets GP","Below GP"))) -> Non-compliant | P7: MOO Ch.1 | Q7: =IF(ISNUMBER(I7),I7*H7,0) -> 4 | R7: =IF(ISNUMBER(I7),4*H7,0) -> 8 | S7: =IF(ISNUMBER(I7),1,0) -> 1 | T7: =IF(AND(E7="M",ISNUMBER(I7)),1,0) -> 1 | U7: =IF(AND(E7="M",ISNUMBER(I7)),IF(I7>=3,1,0),0) -> 0
A8: A1.3 | B8: A1 | C8: CDRRMC meets at least quarterly (and as needed); minutes and resolutions on file | D8: RA 10121 Sec. 11; GKS/SGLG functionality criteria | E8: M | F8: Minutes, attendance, resolutions (last 4 quarters) | G8: DR, KII | H8: 2 | I8: 4 | J8: F: scored 4 (quarterly meetings, minutes and resolutions on file). DR: CDRRMC Res. No. 1 s.2023 approved the 10-Yr Plan. | K8: Validate with the last 4 quarters of minutes and attendance. (Admin FGD notes formerly here were moved to A2.4, A2.6 and A2.10.) | L8: Keep the quarterly schedule; add a standing agenda item on RA 12287 readiness and the action plan from this assessment. Use the minutes template in MOO Ch.1. | M8: =IF(ISNUMBER(I8),(4-I8)*H8*IF(E8="M",1.5,1),"") -> 0 | N8: =IF(M8="","",IF(M8>=9,"High",IF(M8>=4,"Medium","Low"))) -> Low | O8: =IF(NOT(ISNUMBER(I8)),IF(I8="NA","N/A","Not scored"),IF(E8="M",IF(I8>=3,"Compliant","Non-compliant"),IF(I8>=3,"Meets GP","Below GP"))) -> Compliant | P8: MOO Ch.1 | Q8: =IF(ISNUMBER(I8),I8*H8,0) -> 8 | R8: =IF(ISNUMBER(I8),4*H8,0) -> 8 | S8: =IF(ISNUMBER(I8),1,0) -> 1 | T8: =IF(AND(E8="M",ISNUMBER(I8)),1,0) -> 1 | U8: =IF(AND(E8="M",ISNUMBER(I8)),IF(I8>=3,1,0),0) -> 1
A9: A1.4 | B9: A1 | C9: CDRRMO serves as CDRRMC secretariat with documented secretariat procedures | D9: RA 10121 Sec. 12(c)(17) | E9: M | F9: Secretariat SOP; agenda/minutes templates | G9: DR, KII | H9: 1 | I9: 4 | J9: F: scored 4; CDRRMO serves as secretariat. | K9: Validate: secretariat SOP and agenda/minutes templates to be sighted in the workshop. | L9: Write the secretariat procedure (notice, agenda, quorum, minutes, resolutions, tracking) into MOO Ch.2. | M9: =IF(ISNUMBER(I9),(4-I9)*H9*IF(E9="M",1.5,1),"") -> 0 | N9: =IF(M9="","",IF(M9>=9,"High",IF(M9>=4,"Medium","Low"))) -> Low | O9: =IF(NOT(ISNUMBER(I9)),IF(I9="NA","N/A","Not scored"),IF(E9="M",IF(I9>=3,"Compliant","Non-compliant"),IF(I9>=3,"Meets GP","Below GP"))) -> Compliant | P9: MOO Ch.2 Office Organization | Q9: =IF(ISNUMBER(I9),I9*H9,0) -> 4 | R9: =IF(ISNUMBER(I9),4*H9,0) -> 4 | S9: =IF(ISNUMBER(I9),1,0) -> 1 | T9: =IF(AND(E9="M",ISNUMBER(I9)),1,0) -> 1 | U9: =IF(AND(E9="M",ISNUMBER(I9)),IF(I9>=3,1,0),0) -> 1
A10: A1.5 | B10: A1 | C10: Local DRRM-related ordinances in force (e.g., pre-emptive/forced evacuation, no-build zones, hazard-based zoning) | D10: RA 10121 Sec. 12(c)(19); RA 7160; CLUP/ZO | E10: GP | F10: Ordinances; ZO; enforcement records | G10: DR | H10: 2 | I10: 3 | J10: F: pre-emptive/forced evacuation ordinance in force but needs amendment; granular class suspension needed. DR: CLUP/ZO 2017-2027 in force with Water Code river easements, a 5-m easement on the Marina Fault trace and no-build zones, but no flood, landslide or storm-surge overlay zone (its overlays are heritage, critical habitat, eco-tourism, KBA, TOD and urban corridor). 10-Yr Plan cites an approved Shelter Plan. | K10: Evacuation ordinance lacks procedural steps (who orders, triggers, enforcement); class-suspension rules not barangay-specific; ZO has no hazard overlay zones. | L10: Amend the evacuation ordinance to add procedural statements: triggers tied to the warning-action matrix (A6.2), authority to order, assistance to PWD/elderly, livestock and pets (RA 12287 IRR Rule IV), and enforcement. Add granular (barangay/school-level) class and work suspension. In the CLUP/ZO update, add flood, landslide, storm-surge, liquefaction and tsunami overlay zones (CDRA MDA 1). | M10: =IF(ISNUMBER(I10),(4-I10)*H10*IF(E10="M",1.5,1),"") -> 2 | N10: =IF(M10="","",IF(M10>=9,"High",IF(M10>=4,"Medium","Low"))) -> Low | O10: =IF(NOT(ISNUMBER(I10)),IF(I10="NA","N/A","Not scored"),IF(E10="M",IF(I10>=3,"Compliant","Non-compliant"),IF(I10>=3,"Meets GP","Below GP"))) -> Meets GP | P10: MOO Ch.1 | Q10: =IF(ISNUMBER(I10),I10*H10,0) -> 6 | R10: =IF(ISNUMBER(I10),4*H10,0) -> 8 | S10: =IF(ISNUMBER(I10),1,0) -> 1 | T10: =IF(AND(E10="M",ISNUMBER(I10)),1,0) -> 0 | U10: =IF(AND(E10="M",ISNUMBER(I10)),IF(I10>=3,1,0),0) -> 0
A11: A1.6 | B11: A1 | C11: Protocol for declaring a State of Calamity, incl. CDRRMC recommendation steps and post-declaration measures (State of Imminent Disaster now assessed separately under A1.8) | D11: RA 10121 Sec. 16 | E11: M | F11: Protocol/SOP; past CDRRMC resolutions | G11: DR, KII | H11: 3 | I11: 3 | J11: F: scored 4, 'innate in the policy'; confusion noted on national declarations (e.g., San Juanico Bridge closure). DR: 10-Yr Plan records a State of Calamity declaration (Res. No. 354) for TS Urduja 2017. | K11: Assessor adjustment 4 -> 3: past use is shown, but no stand-alone written protocol and no test/AAR showing improvement were cited, which a 4 requires. v1.1 limits this item to State of Calamity; the State of Imminent Disaster is now A1.8. | L11: Write a State of Calamity protocol in MOO Ch.1: criteria (NDRRMC Memo on SoC criteria), RDANA/PDNA basis, CDRRMC recommendation, SP resolution template, post-declaration measures (price freeze, QRF use, reporting). Add a note on how to read national/regional declarations that affect Ormoc. | M11: =IF(ISNUMBER(I11),(4-I11)*H11*IF(E11="M",1.5,1),"") -> 4.5 | N11: =IF(M11="","",IF(M11>=9,"High",IF(M11>=4,"Medium","Low"))) -> Medium | O11: =IF(NOT(ISNUMBER(I11)),IF(I11="NA","N/A","Not scored"),IF(E11="M",IF(I11>=3,"Compliant","Non-compliant"),IF(I11>=3,"Meets GP","Below GP"))) -> Compliant | P11: MOO Ch.1 | Q11: =IF(ISNUMBER(I11),I11*H11,0) -> 9 | R11: =IF(ISNUMBER(I11),4*H11,0) -> 12 | S11: =IF(ISNUMBER(I11),1,0) -> 1 | T11: =IF(AND(E11="M",ISNUMBER(I11)),1,0) -> 1 | U11: =IF(AND(E11="M",ISNUMBER(I11)),IF(I11>=3,1,0),0) -> 1
A12: A1.7 | B12: A1 | C12: DRRM is represented in City Development Council and Local Finance Committee deliberations | D12: RA 7160; JMC 2013-1 | E12: GP | F12: Minutes; LDC/LFC membership | G12: DR, KII | H12: 1 | I12: 4 | J12: F: scored 4; DRRM represented in CDC and LFC. | K12: Validate with CDC/LFC minutes. | L12: Keep representation; use the LFC seat to secure the AA line (A4.6) and the EOC budget (B7.5) in the FY2028 budget call. | M12: =IF(ISNUMBER(I12),(4-I12)*H12*IF(E12="M",1.5,1),"") -> 0 | N12: =IF(M12="","",IF(M12>=9,"High",IF(M12>=4,"Medium","Low"))) -> Low | O12: =IF(NOT(ISNUMBER(I12)),IF(I12="NA","N/A","Not scored"),IF(E12="M",IF(I12>=3,"Compliant","Non-compliant"),IF(I12>=3,"Meets GP","Below GP"))) -> Meets GP | P12: MOO Ch.1 | Q12: =IF(ISNUMBER(I12),I12*H12,0) -> 4 | R12: =IF(ISNUMBER(I12),4*H12,0) -> 4 | S12: =IF(ISNUMBER(I12),1,0) -> 1 | T12: =IF(AND(E12="M",ISNUMBER(I12)),1,0) -> 0 | U12: =IF(AND(E12="M",ISNUMBER(I12)),IF(I12>=3,1,0),0) -> 0
A13: A1.8 | B13: A1 | C13: State of Imminent Disaster procedure: CDRRMC coordinates with RDRRMC VIII when the pre-disaster risk assessment shows reasonable certainty of severe impact; request format to RDRRMC (24-hour reply); Mayor's EO template; adoption rule when the Region (or Province, applicability to an ICC to be confirmed) is declared; lifting grounds and authority | D13: RA 12287; RA 12287 IRR (2026) Rule II Sec. 6; Rule III Secs. 2-4 | E13: M | F13: SOP; EO template; CDRRMC resolution and RDRRMC request templates | G13: DR, KII | H13: 3 | I13: 1 | J13: DR: RA 12287 IRR signed 14 Sep 2026; F (A4.6): AA arrangements 'not in place yet at local level, IRR for cascading'. No local SID SOP, EO template or RDRRMC request template found. | K13: Mandatory new requirement not yet in place: request to RDRRMC VIII (24-h reply), Mayor's EO, adoption rule, lifting grounds. | L13: Draft the State of Imminent Disaster procedure (IRR Rule II Sec. 6; Rule III Secs. 2-4): PDRA trigger, CDRRMC resolution, request to RDRRMC VIII, Mayor's EO template, adoption rule, lifting and the 45-day report (A10.8). Confirm with OCD VIII whether a Provincial declaration applies to an ICC. Walk it through in a tabletop to reach score 3. | M13: =IF(ISNUMBER(I13),(4-I13)*H13*IF(E13="M",1.5,1),"") -> 13.5 | N13: =IF(M13="","",IF(M13>=9,"High",IF(M13>=4,"Medium","Low"))) -> High | O13: =IF(NOT(ISNUMBER(I13)),IF(I13="NA","N/A","Not scored"),IF(E13="M",IF(I13>=3,"Compliant","Non-compliant"),IF(I13>=3,"Meets GP","Below GP"))) -> Non-compliant | P13: MOO Ch.1 / EOC Ch.2 | Q13: =IF(ISNUMBER(I13),I13*H13,0) -> 3 | R13: =IF(ISNUMBER(I13),4*H13,0) -> 12 | S13: =IF(ISNUMBER(I13),1,0) -> 1 | T13: =IF(AND(E13="M",ISNUMBER(I13)),1,0) -> 1 | U13: =IF(AND(E13="M",ISNUMBER(I13)),IF(I13>=3,1,0),0) -> 0
A14: A2 ORGANIZATION, STAFFING & HUMAN RESOURCES - JMC 2014-1 structure, plantilla, 24/7 capacity, competencies
A15: A2.1 | B15: A2 | C15: Organizational structure follows JMC 2014-1: Head + Administration & Training, Research & Planning, and Operations & Warning divisions | D15: NDRRMC-DILG-DBM-CSC JMC 2014-1 | E15: M | F15: Approved organogram; plantilla | G15: DR | H15: 3 | I15: 2 | J15: F: scored 2. DR: 10-Yr Plan SWOC says required CDRRMO positions exist but are not filled; FGDs show Planning, Operations and Admin sections exist. | K15: Divisions exist as sections, but not as an approved JMC 2014-1 structure; normal-operations tasks and response tasks are mixed (Planning FGD). | L15: Adopt the JMC 2014-1 organogram (Head + 3 divisions) with separate normal-operations and response (EOC) roles, through the ordinance in A1.1 and MOO Ch.2. | M15: =IF(ISNUMBER(I15),(4-I15)*H15*IF(E15="M",1.5,1),"") -> 9 | N15: =IF(M15="","",IF(M15>=9,"High",IF(M15>=4,"Medium","Low"))) -> High | O15: =IF(NOT(ISNUMBER(I15)),IF(I15="NA","N/A","Not scored"),IF(E15="M",IF(I15>=3,"Compliant","Non-compliant"),IF(I15>=3,"Meets GP","Below GP"))) -> Non-compliant | P15: MOO Ch.2 Office Organization | Q15: =IF(ISNUMBER(I15),I15*H15,0) -> 6 | R15: =IF(ISNUMBER(I15),4*H15,0) -> 12 | S15: =IF(ISNUMBER(I15),1,0) -> 1 | T15: =IF(AND(E15="M",ISNUMBER(I15)),1,0) -> 1 | U15: =IF(AND(E15="M",ISNUMBER(I15)),IF(I15>=3,1,0),0) -> 0
A16: A2.2 | B16: A2 | C16: CDRRMO Head is a permanent plantilla position filled by a qualified appointee | D16: RA 10121 Sec. 12(b); JMC 2014-1 | E16: M | F16: Appointment; PDS vs CSC QS | G16: DR | H16: 3 | I16: 4 | J16: F: scored 4; permanent Head appointed. DR: 10-Yr Plan names the CDRRMO Head (Ciriaco Tolibao). | K16: Validate appointment papers vs CSC QS. | L16: Maintain; document succession (OIC order of precedence) in MOO Ch.2. | M16: =IF(ISNUMBER(I16),(4-I16)*H16*IF(E16="M",1.5,1),"") -> 0 | N16: =IF(M16="","",IF(M16>=9,"High",IF(M16>=4,"Medium","Low"))) -> Low | O16: =IF(NOT(ISNUMBER(I16)),IF(I16="NA","N/A","Not scored"),IF(E16="M",IF(I16>=3,"Compliant","Non-compliant"),IF(I16>=3,"Meets GP","Below GP"))) -> Compliant | P16: MOO Ch.2 | Q16: =IF(ISNUMBER(I16),I16*H16,0) -> 12 | R16: =IF(ISNUMBER(I16),4*H16,0) -> 12 | S16: =IF(ISNUMBER(I16),1,0) -> 1 | T16: =IF(AND(E16="M",ISNUMBER(I16)),1,0) -> 1 | U16: =IF(AND(E16="M",ISNUMBER(I16)),IF(I16>=3,1,0),0) -> 1
A17: A2.3 | B17: A2 | C17: Minimum plantilla positions per JMC 2014-1 created and filled (ratio of filled/required) | D17: JMC 2014-1; CSC QS | E17: M | F17: Plantilla of Personnel; vacancy list | G17: DR | H17: 3 | I17: 2 | J17: F: scored 4. DR: 10-Yr Plan SWOC says required positions are not filled and its PPAs include hiring 4+4+2 plantilla items plus a maintenance engineer and property custodian. | K17: Assessor adjustment 4 -> 2 under the conflicting-evidence rule (take the lower). Restore if the current Plantilla of Personnel shows all JMC 2014-1 minimum positions filled. | L17: Get the Plantilla of Personnel and vacancy list; compute filled/required. Request creation and funding of the 10 planned items in the FY2028 budget, prioritising Operations & Warning (24/7 OpCen) and Research & Planning (GIS). | M17: =IF(ISNUMBER(I17),(4-I17)*H17*IF(E17="M",1.5,1),"") -> 9 | N17: =IF(M17="","",IF(M17>=9,"High",IF(M17>=4,"Medium","Low"))) -> High | O17: =IF(NOT(ISNUMBER(I17)),IF(I17="NA","N/A","Not scored"),IF(E17="M",IF(I17>=3,"Compliant","Non-compliant"),IF(I17>=3,"Meets GP","Below GP"))) -> Non-compliant | P17: MOO Ch.2 | Q17: =IF(ISNUMBER(I17),I17*H17,0) -> 6 | R17: =IF(ISNUMBER(I17),4*H17,0) -> 12 | S17: =IF(ISNUMBER(I17),1,0) -> 1 | T17: =IF(AND(E17="M",ISNUMBER(I17)),1,0) -> 1 | U17: =IF(AND(E17="M",ISNUMBER(I17)),IF(I17>=3,1,0),0) -> 0
A18: A2.4 | B18: A2 | C18: Job descriptions/position descriptions defined for every position, aligned to RA 10121 functions | D18: CSC rules; JMC 2014-1 | E18: M | F18: JDs/PDFs; IPCR/OPCR | G18: DR | H18: 2 | I18: 2 | J18: F: scored 2. Admin FGD: 'clearer job description per staff'; no monitoring tool for individual performance. | K18: JDs not defined per position; Admin functions bypassed in some activities. | L18: Write position descriptions for every CDRRMO and EOC role (MOO annex), aligned to RA 10121 functions; link them to IPCR/OPCR targets. | M18: =IF(ISNUMBER(I18),(4-I18)*H18*IF(E18="M",1.5,1),"") -> 6 | N18: =IF(M18="","",IF(M18>=9,"High",IF(M18>=4,"Medium","Low"))) -> Medium | O18: =IF(NOT(ISNUMBER(I18)),IF(I18="NA","N/A","Not scored"),IF(E18="M",IF(I18>=3,"Compliant","Non-compliant"),IF(I18>=3,"Meets GP","Below GP"))) -> Non-compliant | P18: MOO Ch.2 / Annex JDs | Q18: =IF(ISNUMBER(I18),I18*H18,0) -> 4 | R18: =IF(ISNUMBER(I18),4*H18,0) -> 8 | S18: =IF(ISNUMBER(I18),1,0) -> 1 | T18: =IF(AND(E18="M",ISNUMBER(I18)),1,0) -> 1 | U18: =IF(AND(E18="M",ISNUMBER(I18)),IF(I18>=3,1,0),0) -> 0
A19: A2.5 | B19: A2 | C19: 24/7 operations capability with documented shift roster (Operations Center/Duty officers) | D19: RA 10121 Sec. 12(c)(16); EOC guidelines | E19: M | F19: Duty roster (last 3 months); logbook | G19: DR, OBS | H19: 3 | I19: 1 | J19: F: attached SOP covers EOC activation only, not an SP-approved OpCen SOP for normal operations. DR: 10-Yr Plan says the Operations Center runs 24/7 with trained personnel, but operations need a manual/SOP; 'Operations Center SOP/Manual' is a 2023-24 PPA. | K19: 24/7 operation exists in practice but no approved normal-operations (White) SOP and roster. | L19: Write the OpCen normal-operations SOP (shifts, handover, monitoring, logbook, reporting times 6AM/6PM per RDRRMC8 Res. 12-006) as EOC Manual Ch.4/Ch.5, using the RDRRMOC SOPG 2022 forms (turn-over document, swapping form, duty composition by alert level); have it approved and keep 3 months of rosters as proof of use. | M19: =IF(ISNUMBER(I19),(4-I19)*H19*IF(E19="M",1.5,1),"") -> 13.5 | N19: =IF(M19="","",IF(M19>=9,"High",IF(M19>=4,"Medium","Low"))) -> High | O19: =IF(NOT(ISNUMBER(I19)),IF(I19="NA","N/A","Not scored"),IF(E19="M",IF(I19>=3,"Compliant","Non-compliant"),IF(I19>=3,"Meets GP","Below GP"))) -> Non-compliant | P19: MOO Ch.4 Operations / EOC Ch.4 | Q19: =IF(ISNUMBER(I19),I19*H19,0) -> 3 | R19: =IF(ISNUMBER(I19),4*H19,0) -> 12 | S19: =IF(ISNUMBER(I19),1,0) -> 1 | T19: =IF(AND(E19="M",ISNUMBER(I19)),1,0) -> 1 | U19: =IF(AND(E19="M",ISNUMBER(I19)),IF(I19>=3,1,0),0) -> 0
A20: A2.6 | B20: A2 | C20: Training needs analysis done and competency-based training plan for staff (ICS, BLS/SFA, WASAR, CSSR, MOSAR, EOC, PDNA, GIS) | D20: RA 10121 Sec. 14; OCD/DRRM Training Institute curricula | E20: GP | F20: TNA; training plan; certificates | G20: DR, KII | H20: 2 | I20: 1 | J20: F: scored 1. Planning FGD: no training needs assessment plan; Admin FGD: TNA proposals not routed to Planning. DR: 10-Yr Plan lists ICS all levels, EOC Management, MDM, CCCM, RDANA and PDNA training. | K20: No TNA or competency-based training plan. | L20: Run a TNA for all CDRRMO/EOC staff against the competency list (ICS, BLS/SFA, WASAR, CSSR, EOC, PDNA, GIS); produce a 3-year training plan with OCD VIII courses in MOO Ch.6. | M20: =IF(ISNUMBER(I20),(4-I20)*H20*IF(E20="M",1.5,1),"") -> 6 | N20: =IF(M20="","",IF(M20>=9,"High",IF(M20>=4,"Medium","Low"))) -> Medium | O20: =IF(NOT(ISNUMBER(I20)),IF(I20="NA","N/A","Not scored"),IF(E20="M",IF(I20>=3,"Compliant","Non-compliant"),IF(I20>=3,"Meets GP","Below GP"))) -> Below GP | P20: MOO Ch.6 Capacity Development | Q20: =IF(ISNUMBER(I20),I20*H20,0) -> 2 | R20: =IF(ISNUMBER(I20),4*H20,0) -> 8 | S20: =IF(ISNUMBER(I20),1,0) -> 1 | T20: =IF(AND(E20="M",ISNUMBER(I20)),1,0) -> 0 | U20: =IF(AND(E20="M",ISNUMBER(I20)),IF(I20>=3,1,0),0) -> 0
A21: A2.7 | B21: A2 | C21: Personnel welfare and safety: insurance, hazard pay, PPE, psychosocial support for responders | D21: RA 10121 Sec. 12; RA 11036 (MHPSS); CSC rules | E21: M | F21: Insurance policy; PPE inventory; MHPSS program | G21: DR, KII | H21: 2 | I21: 1 | J21: F: scored 1. DR: 10-Yr Plan lists responder care and insurance for ACDVs as planned PPAs. | K21: No insurance, hazard pay, PPE or MHPSS programme documented for responders. | L21: Adopt a responder welfare policy: group accident insurance (staff and accredited volunteers), PPE issue list, rest cycles, MHPSS referral with CHO (RA 11036). Memo 131 also requires EOC personnel welfare. | M21: =IF(ISNUMBER(I21),(4-I21)*H21*IF(E21="M",1.5,1),"") -> 9 | N21: =IF(M21="","",IF(M21>=9,"High",IF(M21>=4,"Medium","Low"))) -> High | O21: =IF(NOT(ISNUMBER(I21)),IF(I21="NA","N/A","Not scored"),IF(E21="M",IF(I21>=3,"Compliant","Non-compliant"),IF(I21>=3,"Meets GP","Below GP"))) -> Non-compliant | P21: MOO Ch.2 / Ch.4 | Q21: =IF(ISNUMBER(I21),I21*H21,0) -> 2 | R21: =IF(ISNUMBER(I21),4*H21,0) -> 8 | S21: =IF(ISNUMBER(I21),1,0) -> 1 | T21: =IF(AND(E21="M",ISNUMBER(I21)),1,0) -> 1 | U21: =IF(AND(E21="M",ISNUMBER(I21)),IF(I21>=3,1,0),0) -> 0
A22: A2.8 | B22: A2 | C22: Volunteer/auxiliary responder management system (accreditation, registry, deployment, insurance), incl. mobilization of ACDVs for anticipatory action | D22: RA 10121 Sec. 13; NDRRMC volunteer guidelines; RA 12287 IRR (2026) Rule IV Sec. 5 | E22: GP | F22: Volunteer registry; MOAs; accreditation | G22: DR, KII | H22: 1 | I22: 3 | J22: F: scored 3. DR: 10-Yr Plan SWOC says the volunteer roster is not institutionalised; ACDV roster/accreditation is a planned PPA. | K22: Validate: registry and accreditation records. ACDV mobilisation for AA (IRR Rule IV Sec. 5) not yet covered. | L22: Formalise the ACDV registry with accreditation, insurance and deployment rules, and add AA tasks for ACDVs. | M22: =IF(ISNUMBER(I22),(4-I22)*H22*IF(E22="M",1.5,1),"") -> 1 | N22: =IF(M22="","",IF(M22>=9,"High",IF(M22>=4,"Medium","Low"))) -> Low | O22: =IF(NOT(ISNUMBER(I22)),IF(I22="NA","N/A","Not scored"),IF(E22="M",IF(I22>=3,"Compliant","Non-compliant"),IF(I22>=3,"Meets GP","Below GP"))) -> Meets GP | P22: MOO Ch.6 | Q22: =IF(ISNUMBER(I22),I22*H22,0) -> 3 | R22: =IF(ISNUMBER(I22),4*H22,0) -> 4 | S22: =IF(ISNUMBER(I22),1,0) -> 1 | T22: =IF(AND(E22="M",ISNUMBER(I22)),1,0) -> 0 | U22: =IF(AND(E22="M",ISNUMBER(I22)),IF(I22>=3,1,0),0) -> 0
A23: A2.9 | B23: A2 | C23: Anticipatory action focal person designated in the CDRRMO, with AA training for staff, BDRRMCs, ACDVs and partner CSOs (incl. community-based early warning and early action) | D23: RA 12287 IRR (2026) Rule IV Sec. 1; Rule VII | E23: M | F23: Designation memo; training records | G23: DR | H23: 2 | I23: 0 | J23: DR: no AA focal-person designation found in the documents reviewed; F (A4.6): AA not yet in place locally. | K23: New mandatory item (IRR Rule IV Sec. 1; Rule VII). | L23: Designate an AA focal person by office order and enrol them, BDRRMC officers, ACDVs and partner CSOs in AA training when OCD VIII cascades the IRR. | M23: =IF(ISNUMBER(I23),(4-I23)*H23*IF(E23="M",1.5,1),"") -> 12 | N23: =IF(M23="","",IF(M23>=9,"High",IF(M23>=4,"Medium","Low"))) -> High | O23: =IF(NOT(ISNUMBER(I23)),IF(I23="NA","N/A","Not scored"),IF(E23="M",IF(I23>=3,"Compliant","Non-compliant"),IF(I23>=3,"Meets GP","Below GP"))) -> Non-compliant | P23: MOO Ch.2 / Ch.6 | Q23: =IF(ISNUMBER(I23),I23*H23,0) -> 0 | R23: =IF(ISNUMBER(I23),4*H23,0) -> 8 | S23: =IF(ISNUMBER(I23),1,0) -> 1 | T23: =IF(AND(E23="M",ISNUMBER(I23)),1,0) -> 1 | U23: =IF(AND(E23="M",ISNUMBER(I23)),IF(I23>=3,1,0),0) -> 0
A24: A2.10 | B24: A2 | C24: Inventory of DRRM-relevant skills across the CDRRMO, partner offices and barangays (SAR, engineering, logistics, GIS, PDNA, MHPSS) updated within the last 12 months | D24: UNDRR DRSC 6.1.1 | E24: GP | F24: Skills inventory with date | G24: DR | H24: 1 | I24: 1 | J24: F (Admin FGD, formerly under A1.3): lack of a database on personnel. DR: 10-Yr Plan volunteer roster not institutionalised. | K24: No skills inventory across CDRRMO, partner offices and barangays. | L24: Build a skills inventory (SAR, engineering, logistics, GIS, PDNA, MHPSS) covering CDRRMO, CDRRMC offices and BDRRMCs; update it every 12 months (UNDRR DRSC 6.1.1). | M24: =IF(ISNUMBER(I24),(4-I24)*H24*IF(E24="M",1.5,1),"") -> 3 | N24: =IF(M24="","",IF(M24>=9,"High",IF(M24>=4,"Medium","Low"))) -> Low | O24: =IF(NOT(ISNUMBER(I24)),IF(I24="NA","N/A","Not scored"),IF(E24="M",IF(I24>=3,"Compliant","Non-compliant"),IF(I24>=3,"Meets GP","Below GP"))) -> Below GP | P24: MOO Ch.6 | Q24: =IF(ISNUMBER(I24),I24*H24,0) -> 1 | R24: =IF(ISNUMBER(I24),4*H24,0) -> 4 | S24: =IF(ISNUMBER(I24),1,0) -> 1 | T24: =IF(AND(E24="M",ISNUMBER(I24)),1,0) -> 0 | U24: =IF(AND(E24="M",ISNUMBER(I24)),IF(I24>=3,1,0),0) -> 0
A25: A3 DRRM & CONTINGENCY PLANNING - LDRRMP, CPs, PSCP, mainstreaming in CDP/CLUP/LCCAP
A26: A3.1 | B26: A3 | C26: Local DRRM Plan (LDRRMP) current, approved by Sanggunian, aligned with NDRRMP 2020-2030 and Sendai Framework | D26: RA 10121 Sec. 12(c)(6); NDRRMP 2020-2030 | E26: M | F26: LDRRMP; SP resolution | G26: DR | H26: 3 | I26: 4 | J26: F: scored 4. DR: 10-Yr Plan adopted by SP Res. 2023-112, prepared with the NDRRMC 2022 LDRRMP guidebook. | K26: Validate the alignment table to NDRRMP 2020-2030 and Sendai. Barangay count in the plan (110) predates the 2022 merger; use 85. | L26: Maintain; in the next update correct the barangay count to 85 and add RA 12287 anticipatory action PPAs. | M26: =IF(ISNUMBER(I26),(4-I26)*H26*IF(E26="M",1.5,1),"") -> 0 | N26: =IF(M26="","",IF(M26>=9,"High",IF(M26>=4,"Medium","Low"))) -> Low | O26: =IF(NOT(ISNUMBER(I26)),IF(I26="NA","N/A","Not scored"),IF(E26="M",IF(I26>=3,"Compliant","Non-compliant"),IF(I26>=3,"Meets GP","Below GP"))) -> Compliant | P26: MOO Ch.3 Planning | Q26: =IF(ISNUMBER(I26),I26*H26,0) -> 12 | R26: =IF(ISNUMBER(I26),4*H26,0) -> 12 | S26: =IF(ISNUMBER(I26),1,0) -> 1 | T26: =IF(AND(E26="M",ISNUMBER(I26)),1,0) -> 1 | U26: =IF(AND(E26="M",ISNUMBER(I26)),IF(I26>=3,1,0),0) -> 1
A27: A3.2 | B27: A3 | C27: DRR-CCA mainstreamed in CDP, CLUP, ELA and LCCAP (hazard data used in land use and investment decisions) | D27: RA 10121 Sec. 2; RA 9729 as amended by RA 10174; HLURB/DHSUD CLUP guidelines | E27: M | F27: CDP, CLUP, LCCAP; LDIP/AIP tagging | G27: DR | H27: 2 | I27: 2 | J27: F: plans mainstreaming and provisions need review. DR: CLUP 2017-2027 has a DRRM-CCA sectoral chapter and fault/river easements, but no hazard overlay zones; it still uses 110 barangays and predates the CDRA. CDRA Final Report (TWG under EO 2023-0025) Ch.6 sets 8 Major Decision Areas to feed the CLUP, ZO, CDP, LCCAP, LDRRMP and LDRRMFIP. | K27: Assessor adjustment 3 -> 2 (conflicting evidence, take the lower): CDRA results are not yet carried into zoning overlays, a project screening step (C1.2) or the CDP/AIP. Restore to 3 when the updated CLUP/ZO is approved with CDRA overlays. | L27: Use the CLUP/ZO update to adopt CDRA hazard overlays and the MDA 1-8 interventions; tag CDP/AIP and LCCAP projects to CDRA risk-register entries; review mainstreaming in CDP, CLUP, ELA and LCCAP (see C1.1-C1.4). | M27: =IF(ISNUMBER(I27),(4-I27)*H27*IF(E27="M",1.5,1),"") -> 3 | N27: =IF(M27="","",IF(M27>=9,"High",IF(M27>=4,"Medium","Low"))) -> Low | O27: =IF(NOT(ISNUMBER(I27)),IF(I27="NA","N/A","Not scored"),IF(E27="M",IF(I27>=3,"Compliant","Non-compliant"),IF(I27>=3,"Meets GP","Below GP"))) -> Compliant | P27: MOO Ch.3 | Q27: =IF(ISNUMBER(I27),I27*H27,0) -> 6 | R27: =IF(ISNUMBER(I27),4*H27,0) -> 8 | S27: =IF(ISNUMBER(I27),1,0) -> 1 | T27: =IF(AND(E27="M",ISNUMBER(I27)),1,0) -> 1 | U27: =IF(AND(E27="M",ISNUMBER(I27)),IF(I27>=3,1,0),0) -> 1
A28: A3.3 | B28: A3 | C28: Hazard-specific Contingency Plans for priority hazards (flood/flash flood, landslide, earthquake/tsunami, tropical cyclone, industrial/geothermal), updated and tested | D28: NDRRMC CP guidelines; OCD CP Manual | E28: M | F28: CPs; simulation reports | G28: DR | H28: 3 | I28: 3 | J28: F: CPs updated but tested only for earthquake and flooding. DR: 10-Yr Plan says CPs exist but need updating; new CPs are planned. CDRA MDA 7 calls for hazard-specific CPs for flood, landslide, storm surge, earthquake and tsunami. | K28: No CPs for other top hazards (landslide, tsunami, tropical cyclone, geothermal/industrial); untested CPs. | L28: Prepare CPs for the remaining priority hazards and test each by tabletop; add AA annexes (A8.8) and pre-disaster recovery annex (A9.5). | M28: =IF(ISNUMBER(I28),(4-I28)*H28*IF(E28="M",1.5,1),"") -> 4.5 | N28: =IF(M28="","",IF(M28>=9,"High",IF(M28>=4,"Medium","Low"))) -> Medium | O28: =IF(NOT(ISNUMBER(I28)),IF(I28="NA","N/A","Not scored"),IF(E28="M",IF(I28>=3,"Compliant","Non-compliant"),IF(I28>=3,"Meets GP","Below GP"))) -> Compliant | P28: MOO Ch.3 / EOC Ch.3 | Q28: =IF(ISNUMBER(I28),I28*H28,0) -> 9 | R28: =IF(ISNUMBER(I28),4*H28,0) -> 12 | S28: =IF(ISNUMBER(I28),1,0) -> 1 | T28: =IF(AND(E28="M",ISNUMBER(I28)),1,0) -> 1 | U28: =IF(AND(E28="M",ISNUMBER(I28)),IF(I28>=3,1,0),0) -> 1
A29: A3.4 | B29: A3 | C29: Public Service Continuity Plan (PSCP) prepared covering CDRRMO and essential city services | D29: NDRRMC/OCD PSCP Guidebook | E29: M | F29: PSCP; BIA; essential functions list | G29: DR | H29: 2 | I29: 2 | J29: F: scored 2. DR: PSCP formulation is a 2023 PPA in 10-Yr Plan; NDRRMC/OCD PSCP Guidebook available. | K29: PSCP not completed; no BIA or essential-functions list sighted. | L29: Complete the PSCP using the PSCP Guidebook: essential functions, BIA, alternate site (links to B2.7), orders of succession, vital records. Exercise it once. | M29: =IF(ISNUMBER(I29),(4-I29)*H29*IF(E29="M",1.5,1),"") -> 6 | N29: =IF(M29="","",IF(M29>=9,"High",IF(M29>=4,"Medium","Low"))) -> Medium | O29: =IF(NOT(ISNUMBER(I29)),IF(I29="NA","N/A","Not scored"),IF(E29="M",IF(I29>=3,"Compliant","Non-compliant"),IF(I29>=3,"Meets GP","Below GP"))) -> Non-compliant | P29: MOO Ch.3 / EOC Ch.7 | Q29: =IF(ISNUMBER(I29),I29*H29,0) -> 4 | R29: =IF(ISNUMBER(I29),4*H29,0) -> 8 | S29: =IF(ISNUMBER(I29),1,0) -> 1 | T29: =IF(AND(E29="M",ISNUMBER(I29)),1,0) -> 1 | U29: =IF(AND(E29="M",ISNUMBER(I29)),IF(I29>=3,1,0),0) -> 0
A30: A3.5 | B30: A3 | C30: Annual LDRRMF Investment Plan (LDRRMFIP) prepared, approved and consistent with LDRRMP | D30: JMC 2013-1 | E30: M | F30: LDRRMFIP; CDRRMC resolution | G30: DR | H30: 3 | I30: 4 | J30: F: scored 4; LDRRMFIP prepared and approved. DR: 10-Yr Plan includes a 10-year LDRRMFIP of PHP 14.63 B (80% construction; 52% digital governance) with no anticipatory action line. | K30: Validate the CDRRMC resolution and link to LDRRMP PPAs. | L30: Maintain; add the AA line (A4.6) and EOC operations line (B7.5) explicitly. | M30: =IF(ISNUMBER(I30),(4-I30)*H30*IF(E30="M",1.5,1),"") -> 0 | N30: =IF(M30="","",IF(M30>=9,"High",IF(M30>=4,"Medium","Low"))) -> Low | O30: =IF(NOT(ISNUMBER(I30)),IF(I30="NA","N/A","Not scored"),IF(E30="M",IF(I30>=3,"Compliant","Non-compliant"),IF(I30>=3,"Meets GP","Below GP"))) -> Compliant | P30: MOO Ch.5 Financing | Q30: =IF(ISNUMBER(I30),I30*H30,0) -> 12 | R30: =IF(ISNUMBER(I30),4*H30,0) -> 12 | S30: =IF(ISNUMBER(I30),1,0) -> 1 | T30: =IF(AND(E30="M",ISNUMBER(I30)),1,0) -> 1 | U30: =IF(AND(E30="M",ISNUMBER(I30)),IF(I30>=3,1,0),0) -> 1
A31: A3.6 | B31: A3 | C31: Evacuation plan with mapped routes, safe zones, centers and pre-emptive evacuation triggers per barangay | D31: RA 10121; RA 12076; DILG Operation L!sto | E31: M | F31: Evacuation maps; plans per barangay | G31: DR, OBS | H31: 3 | I31: 2 | J31: F: incomplete. DR: 10-Yr Plan lists EC database/geotagging and Operation L!sto manual as PPAs; 46 barangays are critical flood barangays. | K31: Routes, maps and safe zones not aligned with SOPs; pre-emptive evacuation triggers per barangay missing. | L31: Produce barangay evacuation maps (routes, safe zones, ECs) for all 85 barangays, starting with the 46 critical flood barangays, and link triggers to the warning-action matrix (A6.2). | M31: =IF(ISNUMBER(I31),(4-I31)*H31*IF(E31="M",1.5,1),"") -> 9 | N31: =IF(M31="","",IF(M31>=9,"High",IF(M31>=4,"Medium","Low"))) -> High | O31: =IF(NOT(ISNUMBER(I31)),IF(I31="NA","N/A","Not scored"),IF(E31="M",IF(I31>=3,"Compliant","Non-compliant"),IF(I31>=3,"Meets GP","Below GP"))) -> Non-compliant | P31: MOO Ch.4 / EOC Ch.3 | Q31: =IF(ISNUMBER(I31),I31*H31,0) -> 6 | R31: =IF(ISNUMBER(I31),4*H31,0) -> 12 | S31: =IF(ISNUMBER(I31),1,0) -> 1 | T31: =IF(AND(E31="M",ISNUMBER(I31)),1,0) -> 1 | U31: =IF(AND(E31="M",ISNUMBER(I31)),IF(I31>=3,1,0),0) -> 0
A32: A3.7 | B32: A3 | C32: Barangay DRRM plans (85 barangays) reviewed/consolidated by CDRRMO | D32: RA 10121 Sec. 12(c)(6); DILG MC on BDRRM | E32: GP | F32: Consolidated BDRRMP status matrix | G32: DR | H32: 2 | I32: 4 | J32: F: SGLG-type compliance with good practice. | K32: Validate the consolidated BDRRMP status matrix for 85 barangays. | L32: Maintain; add AA and evacuation-map status columns to the matrix. | M32: =IF(ISNUMBER(I32),(4-I32)*H32*IF(E32="M",1.5,1),"") -> 0 | N32: =IF(M32="","",IF(M32>=9,"High",IF(M32>=4,"Medium","Low"))) -> Low | O32: =IF(NOT(ISNUMBER(I32)),IF(I32="NA","N/A","Not scored"),IF(E32="M",IF(I32>=3,"Compliant","Non-compliant"),IF(I32>=3,"Meets GP","Below GP"))) -> Meets GP | P32: MOO Ch.3 | Q32: =IF(ISNUMBER(I32),I32*H32,0) -> 8 | R32: =IF(ISNUMBER(I32),4*H32,0) -> 8 | S32: =IF(ISNUMBER(I32),1,0) -> 1 | T32: =IF(AND(E32="M",ISNUMBER(I32)),1,0) -> 0 | U32: =IF(AND(E32="M",ISNUMBER(I32)),IF(I32>=3,1,0),0) -> 0
A33: A4 DRRM FINANCING & FUND MANAGEMENT - LDRRMF allocation, utilization, QRF, trust fund, procurement
A34: A4.1 | B34: A4 | C34: LDRRMF set at not less than 5% of estimated revenue from regular sources | D34: RA 10121 Sec. 21; JMC 2013-1 | E34: M | F34: Annual budget; LDRRMF computation | G34: DR | H34: 3 | I34: 4 | J34: F: scored 4. | K34: Validate the LDRRMF computation (5% of estimated regular revenue). | L34: Maintain; keep the computation sheet with the budget. | M34: =IF(ISNUMBER(I34),(4-I34)*H34*IF(E34="M",1.5,1),"") -> 0 | N34: =IF(M34="","",IF(M34>=9,"High",IF(M34>=4,"Medium","Low"))) -> Low | O34: =IF(NOT(ISNUMBER(I34)),IF(I34="NA","N/A","Not scored"),IF(E34="M",IF(I34>=3,"Compliant","Non-compliant"),IF(I34>=3,"Meets GP","Below GP"))) -> Compliant | P34: MOO Ch.5 Financing | Q34: =IF(ISNUMBER(I34),I34*H34,0) -> 12 | R34: =IF(ISNUMBER(I34),4*H34,0) -> 12 | S34: =IF(ISNUMBER(I34),1,0) -> 1 | T34: =IF(AND(E34="M",ISNUMBER(I34)),1,0) -> 1 | U34: =IF(AND(E34="M",ISNUMBER(I34)),IF(I34>=3,1,0),0) -> 1
A35: A4.2 | B35: A4 | C35: 70% Mitigation/Preparedness and 30% Quick Response Fund (QRF) allocation observed | D35: RA 10121 Sec. 21; JMC 2013-1 | E35: M | F35: Appropriation ordinance; LDRRMFIP | G35: DR | H35: 3 | I35: 4 | J35: F: scored 4. | K35: Validate the appropriation ordinance. | L35: Maintain the 70/30 split; show the AA sub-allocation inside the 70% (A4.6). | M35: =IF(ISNUMBER(I35),(4-I35)*H35*IF(E35="M",1.5,1),"") -> 0 | N35: =IF(M35="","",IF(M35>=9,"High",IF(M35>=4,"Medium","Low"))) -> Low | O35: =IF(NOT(ISNUMBER(I35)),IF(I35="NA","N/A","Not scored"),IF(E35="M",IF(I35>=3,"Compliant","Non-compliant"),IF(I35>=3,"Meets GP","Below GP"))) -> Compliant | P35: MOO Ch.5 | Q35: =IF(ISNUMBER(I35),I35*H35,0) -> 12 | R35: =IF(ISNUMBER(I35),4*H35,0) -> 12 | S35: =IF(ISNUMBER(I35),1,0) -> 1 | T35: =IF(AND(E35="M",ISNUMBER(I35)),1,0) -> 1 | U35: =IF(AND(E35="M",ISNUMBER(I35)),IF(I35>=3,1,0),0) -> 1
A36: A4.3 | B36: A4 | C36: Unexpended LDRRMF transferred to Special Trust Fund and used within 5 years | D36: RA 10121 Sec. 21; COA Circular 2012-002 | E36: M | F36: STF ledger; COA reports | G36: DR | H36: 2 | I36: 4 | J36: F: scored 4. | K36: Validate the STF ledger and 5-year use. | L36: Maintain; list STF balances as an AA fund source (A4.6). | M36: =IF(ISNUMBER(I36),(4-I36)*H36*IF(E36="M",1.5,1),"") -> 0 | N36: =IF(M36="","",IF(M36>=9,"High",IF(M36>=4,"Medium","Low"))) -> Low | O36: =IF(NOT(ISNUMBER(I36)),IF(I36="NA","N/A","Not scored"),IF(E36="M",IF(I36>=3,"Compliant","Non-compliant"),IF(I36>=3,"Meets GP","Below GP"))) -> Compliant | P36: MOO Ch.5 | Q36: =IF(ISNUMBER(I36),I36*H36,0) -> 8 | R36: =IF(ISNUMBER(I36),4*H36,0) -> 8 | S36: =IF(ISNUMBER(I36),1,0) -> 1 | T36: =IF(AND(E36="M",ISNUMBER(I36)),1,0) -> 1 | U36: =IF(AND(E36="M",ISNUMBER(I36)),IF(I36>=3,1,0),0) -> 1
A37: A4.4 | B37: A4 | C37: LDRRMF utilization rate monitored and reported (target >= 80% of current-year 70% fund) | D37: JMC 2013-1; COA AAR findings | E37: GP | F37: Utilization reports; COA AAR | G37: DR | H37: 2 | I37: 3 | J37: F: 80% utilisation not yet met; monitoring needed. DR: 10-Yr Plan SWOC notes QRF utilisation/accessibility is a challenge. | K37: Utilisation below target. | L37: Track LDRRMF utilisation quarterly in the CDRRMC meeting; flag PPAs at risk by Q3. | M37: =IF(ISNUMBER(I37),(4-I37)*H37*IF(E37="M",1.5,1),"") -> 2 | N37: =IF(M37="","",IF(M37>=9,"High",IF(M37>=4,"Medium","Low"))) -> Low | O37: =IF(NOT(ISNUMBER(I37)),IF(I37="NA","N/A","Not scored"),IF(E37="M",IF(I37>=3,"Compliant","Non-compliant"),IF(I37>=3,"Meets GP","Below GP"))) -> Meets GP | P37: MOO Ch.5 | Q37: =IF(ISNUMBER(I37),I37*H37,0) -> 6 | R37: =IF(ISNUMBER(I37),4*H37,0) -> 8 | S37: =IF(ISNUMBER(I37),1,0) -> 1 | T37: =IF(AND(E37="M",ISNUMBER(I37)),1,0) -> 0 | U37: =IF(AND(E37="M",ISNUMBER(I37)),IF(I37>=3,1,0),0) -> 0
A38: A4.5 | B38: A4 | C38: Emergency procurement procedures (negotiated procurement - emergency cases) documented and pre-arranged (framework agreements, pre-qualified suppliers) | D38: RA 12009 (New Government Procurement Act) & IRR | E38: M | F38: Procurement SOP; framework agreements | G38: DR, KII | H38: 2 | I38: 3 | J38: F: local suppliers' capability needs regular updating. | K38: Supplier list not refreshed; framework agreements to be confirmed. | L38: Keep a pre-qualified supplier list updated each year; set framework agreements for relief goods, fuel and heavy equipment under RA 12009 IRR, usable for AA (B6.6). | M38: =IF(ISNUMBER(I38),(4-I38)*H38*IF(E38="M",1.5,1),"") -> 3 | N38: =IF(M38="","",IF(M38>=9,"High",IF(M38>=4,"Medium","Low"))) -> Low | O38: =IF(NOT(ISNUMBER(I38)),IF(I38="NA","N/A","Not scored"),IF(E38="M",IF(I38>=3,"Compliant","Non-compliant"),IF(I38>=3,"Meets GP","Below GP"))) -> Compliant | P38: MOO Ch.5 / EOC Ch.6 | Q38: =IF(ISNUMBER(I38),I38*H38,0) -> 6 | R38: =IF(ISNUMBER(I38),4*H38,0) -> 8 | S38: =IF(ISNUMBER(I38),1,0) -> 1 | T38: =IF(AND(E38="M",ISNUMBER(I38)),1,0) -> 1 | U38: =IF(AND(E38="M",ISNUMBER(I38)),IF(I38>=3,1,0),0) -> 1
A39: A4.6 | B39: A4 | C39: Anticipatory action funding pathway: LDRRMFIP sets an AA line within the cap of 10% of the 70% LDRRMF; other sources mapped (Special Trust Fund balances, donations, ODA); Budget, Accounting and BAC procedures allow immediate disbursement and observe the 30%/70% tranche rule around the 3-day lead time | D39: RA 12287; RA 12287 IRR (2026) Rule V Secs. 1-3; RA 10121 Sec. 21; RA 12009 | E39: M | F39: LDRRMFIP AA line; Budget/Accounting guidance; disbursement and procurement SOP | G39: DR, KII | H39: 2 | I39: 0 | J39: F: not in place locally; awaiting IRR cascading. DR: IRR Rule V allows up to 10% of the 70% LDRRMF for AA; <=30% more than 3 days before impact, up to 70% within 3 days. DBM-COA guidelines pending. | K39: No AA line, no disbursement guidance. | L39: Put an AA line (up to 10% of the 70% LDRRMF) in the FY2028 LDRRMFIP; map other sources (STF, donations, ODA); write Budget/Accounting/BAC steps for immediate disbursement with the 30%/70% tranche rule. Revisit when DBM-COA guidelines issue. | M39: =IF(ISNUMBER(I39),(4-I39)*H39*IF(E39="M",1.5,1),"") -> 12 | N39: =IF(M39="","",IF(M39>=9,"High",IF(M39>=4,"Medium","Low"))) -> High | O39: =IF(NOT(ISNUMBER(I39)),IF(I39="NA","N/A","Not scored"),IF(E39="M",IF(I39>=3,"Compliant","Non-compliant"),IF(I39>=3,"Meets GP","Below GP"))) -> Non-compliant | P39: MOO Ch.5 | Q39: =IF(ISNUMBER(I39),I39*H39,0) -> 0 | R39: =IF(ISNUMBER(I39),4*H39,0) -> 8 | S39: =IF(ISNUMBER(I39),1,0) -> 1 | T39: =IF(AND(E39="M",ISNUMBER(I39)),1,0) -> 1 | U39: =IF(AND(E39="M",ISNUMBER(I39)),IF(I39>=3,1,0),0) -> 0
A40: A4.7 | B40: A4 | C40: Risk transfer/financing instruments explored (indemnity insurance of public assets, PSF access, partnerships) | D40: NDRRMP; RA 10174 (People's Survival Fund); DOF-BTr NIP | E40: GP | F40: GSIS insurance; PSF proposals | G40: DR | H40: 1 | I40: 3 | J40: F: scored 3. DR: CDRA reports that only 15% of critical-point facilities are insured and that no lifeline utility is insured. | K40: Validate GSIS coverage of public assets and PSF proposals; CDRA shows low insurance coverage of critical facilities and none for lifelines. | L40: Check that the EOC, ECs and city-owned critical facilities are on the GSIS indemnity schedule; use the CDRA facility list to set coverage priorities. | M40: =IF(ISNUMBER(I40),(4-I40)*H40*IF(E40="M",1.5,1),"") -> 1 | N40: =IF(M40="","",IF(M40>=9,"High",IF(M40>=4,"Medium","Low"))) -> Low | O40: =IF(NOT(ISNUMBER(I40)),IF(I40="NA","N/A","Not scored"),IF(E40="M",IF(I40>=3,"Compliant","Non-compliant"),IF(I40>=3,"Meets GP","Below GP"))) -> Meets GP | P40: MOO Ch.5 | Q40: =IF(ISNUMBER(I40),I40*H40,0) -> 3 | R40: =IF(ISNUMBER(I40),4*H40,0) -> 4 | S40: =IF(ISNUMBER(I40),1,0) -> 1 | T40: =IF(AND(E40="M",ISNUMBER(I40)),1,0) -> 0 | U40: =IF(AND(E40="M",ISNUMBER(I40)),IF(I40>=3,1,0),0) -> 0
A41: A4.8 | B41: A4 | C41: Clean COA findings on LDRRMF in last audit year (or findings addressed) | D41: COA Circular 2012-002 | E41: M | F41: COA Annual Audit Report; action plan | G41: DR | H41: 2 | I41: 3 | J41: F: internal audit to be ensured. | K41: Confirm the latest COA AAR has no unaddressed LDRRMF findings. | L41: Set an internal audit check of LDRRMF before year-end. | M41: =IF(ISNUMBER(I41),(4-I41)*H41*IF(E41="M",1.5,1),"") -> 3 | N41: =IF(M41="","",IF(M41>=9,"High",IF(M41>=4,"Medium","Low"))) -> Low | O41: =IF(NOT(ISNUMBER(I41)),IF(I41="NA","N/A","Not scored"),IF(E41="M",IF(I41>=3,"Compliant","Non-compliant"),IF(I41>=3,"Meets GP","Below GP"))) -> Compliant | P41: MOO Ch.5 | Q41: =IF(ISNUMBER(I41),I41*H41,0) -> 6 | R41: =IF(ISNUMBER(I41),4*H41,0) -> 8 | S41: =IF(ISNUMBER(I41),1,0) -> 1 | T41: =IF(AND(E41="M",ISNUMBER(I41)),1,0) -> 1 | U41: =IF(AND(E41="M",ISNUMBER(I41)),IF(I41>=3,1,0),0) -> 1
A42: A4.9 | B42: A4 | C42: QRF and LDRRMF adequacy tested against the most severe credible scenario (e.g., a Thelma-type flash flood or Yolanda-strength typhoon), with the shortfall and other fund sources identified | D42: UNDRR DRSC 3.2.3, 3.2.4; JMC 2013-1 | E42: GP | F42: Costed scenario; LDRRMFIP; Budget Office analysis | G42: DR, KII | H42: 2 | I42: 1 | J42: DR: 10-Yr Plan (GeoRiskPH) gives potential asset damage by hazard (flood PHP 222.4 B; rain-induced landslide PHP 205.5 B; liquefaction PHP 189.3 B; tsunami PHP 59.0 B). CLUP set the QRF at PHP 13.99 M (2017 figure). No costed response scenario compared with QRF/STF found; 10-Yr Plan SWOC notes QRF access is a challenge. | K42: Provisional desk score: asset-damage figures exist, but the cost of responding to the most severe credible event has not been set against the QRF, STF and other sources. Confirm with the City Budget Office. | L42: Cost response and early recovery (relief, evacuation, debris, emergency repair) for a Thelma-type flash flood and a Yolanda-type typhoon from the flood and TC CPs; compare with the current QRF, STF balances and NDRRM Fund access; record the shortfall and fallback sources in the LDRRMFIP. | M42: =IF(ISNUMBER(I42),(4-I42)*H42*IF(E42="M",1.5,1),"") | N42: =IF(M42="","",IF(M42>=9,"High",IF(M42>=4,"Medium","Low"))) | O42: =IF(NOT(ISNUMBER(I42)),IF(I42="NA","N/A","Not scored"),IF(E42="M",IF(I42>=3,"Compliant","Non-compliant"),IF(I42>=3,"Meets GP","Below GP"))) -> Not scored | P42: MOO Ch.5 | Q42: =IF(ISNUMBER(I42),I42*H42,0) -> 0 | R42: =IF(ISNUMBER(I42),4*H42,0) -> 0 | S42: =IF(ISNUMBER(I42),1,0) -> 0 | T42: =IF(AND(E42="M",ISNUMBER(I42)),1,0) -> 0 | U42: =IF(AND(E42="M",ISNUMBER(I42)),IF(I42>=3,1,0),0) -> 0
A43: A5 RISK ASSESSMENT, DATA & KNOWLEDGE MANAGEMENT - Hazard/risk data, CDRA, information systems, data privacy
A44: A5.1 | B44: A5 | C44: Updated hazard maps for all priority hazards (MGB, PHIVOLCS, PAGASA, GeoRiskPH/HazardHunterPH) at barangay scale | D44: RA 10121 Sec. 12(c)(3); NDRRMP | E44: M | F44: Hazard maps; GIS layers | G44: DR, OBS | H44: 3 | I44: 3 | J44: F: scored 3. DR: GeoRiskPH MOA with PHIVOLCS covers 6 hazards (10-Yr Plan). | K44: Barangay-scale coverage to validate. | L44: Maintain; publish barangay hazard maps through the shared source (A5.7). | M44: =IF(ISNUMBER(I44),(4-I44)*H44*IF(E44="M",1.5,1),"") -> 4.5 | N44: =IF(M44="","",IF(M44>=9,"High",IF(M44>=4,"Medium","Low"))) -> Medium | O44: =IF(NOT(ISNUMBER(I44)),IF(I44="NA","N/A","Not scored"),IF(E44="M",IF(I44>=3,"Compliant","Non-compliant"),IF(I44>=3,"Meets GP","Below GP"))) -> Compliant | P44: MOO Ch.3 / EOC Ch.5 | Q44: =IF(ISNUMBER(I44),I44*H44,0) -> 9 | R44: =IF(ISNUMBER(I44),4*H44,0) -> 12 | S44: =IF(ISNUMBER(I44),1,0) -> 1 | T44: =IF(AND(E44="M",ISNUMBER(I44)),1,0) -> 1 | U44: =IF(AND(E44="M",ISNUMBER(I44)),IF(I44>=3,1,0),0) -> 1
A45: A5.2 | B45: A5 | C45: Climate & Disaster Risk Assessment (CDRA)/ CRA completed with exposure (population, buildings, critical facilities) and vulnerability data | D45: DHSUD/CCC CDRA guidelines; RA 10121 Sec. 12(c)(3) | E45: M | F45: CDRA report; exposure database | G45: DR | H45: 3 | I45: 3 | J45: F: CDRA for updating. DR: CDRA Final Report (TWG under EO 2023-0025) reviewed: exposure, vulnerability and risk for flood, rain-induced landslide and storm surge across population, urban use areas, production areas, critical-point facilities and lifelines in 85 barangays, plus climate impact chains and Ch.6 policy interventions. Earthquake, liquefaction and tsunami are cited from GeoRiskPH figures, not assessed. | K45: No earthquake, liquefaction or tsunami DRA; climate-projection tables still labelled 'Municipality of Naval, Province of Biliran' (template error); SP adoption and use in plans to validate. | L45: Add earthquake, liquefaction and tsunami DRA; correct the Naval/Biliran table labels; adopt the CDRA with the CLUP update and set its update cycle (A5.9); cover exposure of critical facilities (A5.8) and non-asset losses (C1.3). | M45: =IF(ISNUMBER(I45),(4-I45)*H45*IF(E45="M",1.5,1),"") -> 4.5 | N45: =IF(M45="","",IF(M45>=9,"High",IF(M45>=4,"Medium","Low"))) -> Medium | O45: =IF(NOT(ISNUMBER(I45)),IF(I45="NA","N/A","Not scored"),IF(E45="M",IF(I45>=3,"Compliant","Non-compliant"),IF(I45>=3,"Meets GP","Below GP"))) -> Compliant | P45: MOO Ch.3 | Q45: =IF(ISNUMBER(I45),I45*H45,0) -> 9 | R45: =IF(ISNUMBER(I45),4*H45,0) -> 12 | S45: =IF(ISNUMBER(I45),1,0) -> 1 | T45: =IF(AND(E45="M",ISNUMBER(I45)),1,0) -> 1 | U45: =IF(AND(E45="M",ISNUMBER(I45)),IF(I45>=3,1,0),0) -> 1
A46: A5.3 | B46: A5 | C46: Disaggregated population database (sex, age, disability, IP, pregnant/lactating) for at-risk households | D46: RA 10121 Sec. 12(c)(5); RA 9710; RA 7277 as amended; RA 10821 | E46: M | F46: CBMS/household risk database | G46: DR, OBS | H46: 2 | I46: 4 | J46: F: scored 4. DR: 10-Yr Plan says CBMS needs updating. | K46: Conflict to validate: 4 needs a current database used in a test or event; the plan says CBMS needs updating. | L46: Validate CBMS currency; use it as the AA targeting list (A8.9). | M46: =IF(ISNUMBER(I46),(4-I46)*H46*IF(E46="M",1.5,1),"") -> 0 | N46: =IF(M46="","",IF(M46>=9,"High",IF(M46>=4,"Medium","Low"))) -> Low | O46: =IF(NOT(ISNUMBER(I46)),IF(I46="NA","N/A","Not scored"),IF(E46="M",IF(I46>=3,"Compliant","Non-compliant"),IF(I46>=3,"Meets GP","Below GP"))) -> Compliant | P46: MOO Ch.3 / EOC Ch.5 | Q46: =IF(ISNUMBER(I46),I46*H46,0) -> 8 | R46: =IF(ISNUMBER(I46),4*H46,0) -> 8 | S46: =IF(ISNUMBER(I46),1,0) -> 1 | T46: =IF(AND(E46="M",ISNUMBER(I46)),1,0) -> 1 | U46: =IF(AND(E46="M",ISNUMBER(I46)),IF(I46>=3,1,0),0) -> 1
A47: A5.4 | B47: A5 | C47: DRRM information system/ database with disaster event history, damage and losses (incl. 1991 flood, 2013 Yolanda, 2017 earthquake records) | D47: RA 10121 Sec. 12(c)(5); Sendai monitoring | E47: GP | F47: Disaster database; event records | G47: DR, OBS | H47: 2 | I47: 0 | J47: F: scored 0. DR: 10-Yr Plan has a top-6 disaster event table and cites RDANA reports and a PDNA report (Paglaum); CDRA Table 4 lists previous disasters with damage figures. CDRA MDA 8 recommends a disaster-event and loss database. | K47: Event records exist in reports but there is no database. | L47: Set up a disaster event and loss database (Sendai/DesInventar fields) and back-load past RDANA/PDNA data. | M47: =IF(ISNUMBER(I47),(4-I47)*H47*IF(E47="M",1.5,1),"") -> 8 | N47: =IF(M47="","",IF(M47>=9,"High",IF(M47>=4,"Medium","Low"))) -> Medium | O47: =IF(NOT(ISNUMBER(I47)),IF(I47="NA","N/A","Not scored"),IF(E47="M",IF(I47>=3,"Compliant","Non-compliant"),IF(I47>=3,"Meets GP","Below GP"))) -> Below GP | P47: MOO Ch.7 Knowledge Mgmt | Q47: =IF(ISNUMBER(I47),I47*H47,0) -> 0 | R47: =IF(ISNUMBER(I47),4*H47,0) -> 8 | S47: =IF(ISNUMBER(I47),1,0) -> 1 | T47: =IF(AND(E47="M",ISNUMBER(I47)),1,0) -> 0 | U47: =IF(AND(E47="M",ISNUMBER(I47)),IF(I47>=3,1,0),0) -> 0
A48: A5.5 | B48: A5 | C48: Data privacy compliance for beneficiary and affected-population data (DPO, consent, data sharing agreements) | D48: RA 10173 (Data Privacy Act); NPC circulars | E48: M | F48: DPO designation; DSA; privacy notices | G48: DR, KII | H48: 2 | I48: 2 | J48: F: for verification with CPDO (KII). | K48: No DPO designation, DSA or privacy notice sighted for DRRM data. | L48: Confirm the City DPO; sign data-sharing agreements with CSWDO/CPDO for beneficiary data; add privacy notices to registration forms. | M48: =IF(ISNUMBER(I48),(4-I48)*H48*IF(E48="M",1.5,1),"") -> 6 | N48: =IF(M48="","",IF(M48>=9,"High",IF(M48>=4,"Medium","Low"))) -> Medium | O48: =IF(NOT(ISNUMBER(I48)),IF(I48="NA","N/A","Not scored"),IF(E48="M",IF(I48>=3,"Compliant","Non-compliant"),IF(I48>=3,"Meets GP","Below GP"))) -> Non-compliant | P48: MOO Ch.7 | Q48: =IF(ISNUMBER(I48),I48*H48,0) -> 4 | R48: =IF(ISNUMBER(I48),4*H48,0) -> 8 | S48: =IF(ISNUMBER(I48),1,0) -> 1 | T48: =IF(AND(E48="M",ISNUMBER(I48)),1,0) -> 1 | U48: =IF(AND(E48="M",ISNUMBER(I48)),IF(I48>=3,1,0),0) -> 0
A49: A5.6 | B49: A5 | C49: GIS capability (software, trained staff, updated base maps) within Research & Planning | D49: JMC 2014-1 (R&P functions) | E49: GP | F49: GIS outputs; staff training | G49: OBS, KII | H49: 1 | I49: 2 | J49: F: for verification with CPDO (KII). | K49: GIS capacity in R&P not confirmed. | L49: Confirm GIS staff and software; train at least 2 R&P staff. | M49: =IF(ISNUMBER(I49),(4-I49)*H49*IF(E49="M",1.5,1),"") -> 2 | N49: =IF(M49="","",IF(M49>=9,"High",IF(M49>=4,"Medium","Low"))) -> Low | O49: =IF(NOT(ISNUMBER(I49)),IF(I49="NA","N/A","Not scored"),IF(E49="M",IF(I49>=3,"Compliant","Non-compliant"),IF(I49>=3,"Meets GP","Below GP"))) -> Below GP | P49: MOO Ch.7 | Q49: =IF(ISNUMBER(I49),I49*H49,0) -> 2 | R49: =IF(ISNUMBER(I49),4*H49,0) -> 4 | S49: =IF(ISNUMBER(I49),1,0) -> 1 | T49: =IF(AND(E49="M",ISNUMBER(I49)),1,0) -> 0 | U49: =IF(AND(E49="M",ISNUMBER(I49)),IF(I49>=3,1,0),0) -> 0
A50: A5.7 | B50: A5 | C50: One maintained, shared source of risk and readiness information (hazard maps, plans, contacts, readiness summary) open to CDRRMC member offices, with a public summary posted | D50: UNDRR DRSC 1.4.1, 6.3.1, 6.3.2; RA 10173 | E50: GP | F50: Shared drive/portal; public web posting | G50: DR, OBS | H50: 2 | I50: 1 | J50: DR: 10-Yr Plan lists a database management team and a cloud IMS as planned PPAs; CDRA MDA 8 recommends a common risk information system with data custodians, but none is in place. | K50: No single shared source for CDRRMC offices; no public summary. | L50: Set up one shared repository (hazard maps, plans, contacts, readiness summary) for CDRRMC offices and post a public summary, respecting RA 10173. | M50: =IF(ISNUMBER(I50),(4-I50)*H50*IF(E50="M",1.5,1),"") -> 6 | N50: =IF(M50="","",IF(M50>=9,"High",IF(M50>=4,"Medium","Low"))) -> Medium | O50: =IF(NOT(ISNUMBER(I50)),IF(I50="NA","N/A","Not scored"),IF(E50="M",IF(I50>=3,"Compliant","Non-compliant"),IF(I50>=3,"Meets GP","Below GP"))) -> Below GP | P50: MOO Ch.7 | Q50: =IF(ISNUMBER(I50),I50*H50,0) -> 2 | R50: =IF(ISNUMBER(I50),4*H50,0) -> 8 | S50: =IF(ISNUMBER(I50),1,0) -> 1 | T50: =IF(AND(E50="M",ISNUMBER(I50)),1,0) -> 0 | U50: =IF(AND(E50="M",ISNUMBER(I50)),IF(I50>=3,1,0),0) -> 0
A51: A5.8 | B51: A5 | C51: Critical facilities list (EOC, hospitals, evacuation centers, water, power, telecom, bridges, port) with dependencies mapped as potential failure chains and used to set protection and restoration priorities | D51: UNDRR DRSC 2.3.1; RA 12287 IRR (2026) Rule I Sec. 5(b),(d) | E51: GP | F51: Critical facilities database; dependency map | G51: DR | H51: 2 | I51: 2 | J51: DR: CDRA exposure databases list critical-point facilities (schools, hospitals, government offices, NGCP substation, geothermal plants, solar farm, Ormoc Port, fuel depot) and lifeline roads by barangay and hazard, with risk scores (e.g., 86 facilities and 101 lifelines rated high risk to rain-induced landslide). Critical infrastructure inventory update is a 10-Yr Plan PPA. | K51: A facility and lifeline list exists, but dependencies and failure chains are not mapped and are not used to set protection and restoration priorities. | L51: Start from the CDRA facility and lifeline tables; map dependencies among power, water, telecom, roads, hospitals, ECs and the EOC (CDRA MDA 2 items 1, 5, 6); use CREST systems-mapping to draw failure chains and set restoration priorities. | M51: =IF(ISNUMBER(I51),(4-I51)*H51*IF(E51="M",1.5,1),"") -> 6 | N51: =IF(M51="","",IF(M51>=9,"High",IF(M51>=4,"Medium","Low"))) -> Medium | O51: =IF(NOT(ISNUMBER(I51)),IF(I51="NA","N/A","Not scored"),IF(E51="M",IF(I51>=3,"Compliant","Non-compliant"),IF(I51>=3,"Meets GP","Below GP"))) -> Below GP | P51: MOO Ch.3 / EOC Ch.3 | Q51: =IF(ISNUMBER(I51),I51*H51,0) -> 2 | R51: =IF(ISNUMBER(I51),4*H51,0) -> 8 | S51: =IF(ISNUMBER(I51),1,0) -> 1 | T51: =IF(AND(E51="M",ISNUMBER(I51)),1,0) -> 0 | U51: =IF(AND(E51="M",ISNUMBER(I51)),IF(I51>=3,1,0),0) -> 0
A52: A5.9 | B52: A5 | C52: Agreed update cycle: hazard data every 3 years or less; exposure, vulnerability and critical-facility data every 18 months or less | D52: UNDRR DRSC 2.5.1 | E52: GP | F52: Update procedure; version dates of datasets | G52: DR | H52: 1 | I52: 1 | J52: DR: CDRA and CBMS overdue for updating (10-Yr Plan). CDRA 6.7.2 proposes annual review of exposure and critical-facility inventories and event-triggered updates; not yet adopted. | K52: No agreed update cycle. | L52: Adopt an update cycle in MOO Ch.7: hazard data <=3 years; exposure, vulnerability and critical facilities <=18 months. | M52: =IF(ISNUMBER(I52),(4-I52)*H52*IF(E52="M",1.5,1),"") -> 3 | N52: =IF(M52="","",IF(M52>=9,"High",IF(M52>=4,"Medium","Low"))) -> Low | O52: =IF(NOT(ISNUMBER(I52)),IF(I52="NA","N/A","Not scored"),IF(E52="M",IF(I52>=3,"Compliant","Non-compliant"),IF(I52>=3,"Meets GP","Below GP"))) -> Below GP | P52: MOO Ch.7 | Q52: =IF(ISNUMBER(I52),I52*H52,0) -> 1 | R52: =IF(ISNUMBER(I52),4*H52,0) -> 4 | S52: =IF(ISNUMBER(I52),1,0) -> 1 | T52: =IF(AND(E52="M",ISNUMBER(I52)),1,0) -> 0 | U52: =IF(AND(E52="M",ISNUMBER(I52)),IF(I52>=3,1,0),0) -> 0
A53: A6 EARLY WARNING & RISK COMMUNICATION - Hazard-specific EWS, last-mile warning, public information
A54: A6.1 | B54: A6 | C54: Hazard-specific EWS operational for flood (incl. Anilao/Malbasag river systems), rain-induced landslide, tsunami (Ormoc Bay) and tropical cyclone | D54: RA 10121 Sec. 12(c)(8); PAGASA/PHIVOLCS protocols | E54: M | F54: EWS inventory; functionality logs; maps of sensors/gauges | G54: DR, OBS, TST | H54: 3 | I54: 3 | J54: F: re-establish tech-based and strengthen indigenous EWS; barangay tools are group chat, VHF radio, public address and megaphones. DR: 10-Yr Plan plans 6 AWS, a DOST-PAGASA coastal camera, an OpCen integrated multi-hazard EWS/CCTV and EWS preventive maintenance and insurance. | K54: Tech-based gauges/sensors need re-establishing (Anilao/Malbasag). | L54: Restore and insure the flood/rain gauges; set a monthly functionality check; write an EWS SOP (planned PPA). | M54: =IF(ISNUMBER(I54),(4-I54)*H54*IF(E54="M",1.5,1),"") -> 4.5 | N54: =IF(M54="","",IF(M54>=9,"High",IF(M54>=4,"Medium","Low"))) -> Medium | O54: =IF(NOT(ISNUMBER(I54)),IF(I54="NA","N/A","Not scored"),IF(E54="M",IF(I54>=3,"Compliant","Non-compliant"),IF(I54>=3,"Meets GP","Below GP"))) -> Compliant | P54: MOO Ch.4 / EOC Ch.3 | Q54: =IF(ISNUMBER(I54),I54*H54,0) -> 9 | R54: =IF(ISNUMBER(I54),4*H54,0) -> 12 | S54: =IF(ISNUMBER(I54),1,0) -> 1 | T54: =IF(AND(E54="M",ISNUMBER(I54)),1,0) -> 1 | U54: =IF(AND(E54="M",ISNUMBER(I54)),IF(I54>=3,1,0),0) -> 1
A55: A6.2 | B55: A6 | C55: Warning thresholds linked to specific actions (alert levels -> pre-emptive evacuation, class/work suspension, State of Imminent Disaster request) in written protocols, built to take up NDRRMC impact-based triggers once issued | D55: RA 10121; RA 12287; RA 12287 IRR (2026) Rule II Sec. 2; DILG Operation L!sto | E55: M | F55: Warning-action matrix | G55: DR | H55: 3 | I55: 2 | J55: F: needs enhancement. | K55: Matrix does not yet link alert levels to SID request and AA (RA 12287). | L55: Write the warning-action matrix (PAGASA/PHIVOLCS levels -> pre-emptive evacuation, class/work suspension, EOC level, SID request), built to take NDRRMC impact-based triggers when issued. | M55: =IF(ISNUMBER(I55),(4-I55)*H55*IF(E55="M",1.5,1),"") -> 9 | N55: =IF(M55="","",IF(M55>=9,"High",IF(M55>=4,"Medium","Low"))) -> High | O55: =IF(NOT(ISNUMBER(I55)),IF(I55="NA","N/A","Not scored"),IF(E55="M",IF(I55>=3,"Compliant","Non-compliant"),IF(I55>=3,"Meets GP","Below GP"))) -> Non-compliant | P55: EOC Ch.2 Concept of Operations | Q55: =IF(ISNUMBER(I55),I55*H55,0) -> 6 | R55: =IF(ISNUMBER(I55),4*H55,0) -> 12 | S55: =IF(ISNUMBER(I55),1,0) -> 1 | T55: =IF(AND(E55="M",ISNUMBER(I55)),1,0) -> 1 | U55: =IF(AND(E55="M",ISNUMBER(I55)),IF(I55>=3,1,0),0) -> 0
A56: A6.3 | B56: A6 | C56: Last-mile dissemination channels tested to barangay/purok level (sirens, radio, SMS/ECBS, social media, barangay criers) | D56: RA 10639 (Free Mobile Disaster Alerts); NDRRMC EWS | E56: M | F56: Test logs; coverage map | G56: OBS, TST, FGD | H56: 3 | I56: 2 | J56: F: delivery is fast but fails when telecom is down; verify at barangay level. | K56: No tested fallback channel when mobile networks fail. | L56: Revise the dissemination SOP with non-telecom fallbacks (VHF, sirens, criers) and test to purok level twice a year with logs. | M56: =IF(ISNUMBER(I56),(4-I56)*H56*IF(E56="M",1.5,1),"") -> 9 | N56: =IF(M56="","",IF(M56>=9,"High",IF(M56>=4,"Medium","Low"))) -> High | O56: =IF(NOT(ISNUMBER(I56)),IF(I56="NA","N/A","Not scored"),IF(E56="M",IF(I56>=3,"Compliant","Non-compliant"),IF(I56>=3,"Meets GP","Below GP"))) -> Non-compliant | P56: MOO Ch.4 | Q56: =IF(ISNUMBER(I56),I56*H56,0) -> 6 | R56: =IF(ISNUMBER(I56),4*H56,0) -> 12 | S56: =IF(ISNUMBER(I56),1,0) -> 1 | T56: =IF(AND(E56="M",ISNUMBER(I56)),1,0) -> 1 | U56: =IF(AND(E56="M",ISNUMBER(I56)),IF(I56>=3,1,0),0) -> 0
A57: A6.4 | B57: A6 | C57: Warnings issued in local language (Cebuano/ Ormocanon) and accessible formats (sign language, visual alerts for PWD) | D57: RA 10121; RA 11106 (FSL Act); RA 7277 | E57: GP | F57: Sample advisories; IEC materials | G57: DR | H57: 2 | I57: 4 | J57: F: scored 4. | K57: Validate sample advisories in Cebuano and accessible formats. | L57: Maintain; add PWD-inclusive EWS (planned PPA). | M57: =IF(ISNUMBER(I57),(4-I57)*H57*IF(E57="M",1.5,1),"") -> 0 | N57: =IF(M57="","",IF(M57>=9,"High",IF(M57>=4,"Medium","Low"))) -> Low | O57: =IF(NOT(ISNUMBER(I57)),IF(I57="NA","N/A","Not scored"),IF(E57="M",IF(I57>=3,"Compliant","Non-compliant"),IF(I57>=3,"Meets GP","Below GP"))) -> Meets GP | P57: MOO Ch.4 | Q57: =IF(ISNUMBER(I57),I57*H57,0) -> 8 | R57: =IF(ISNUMBER(I57),4*H57,0) -> 8 | S57: =IF(ISNUMBER(I57),1,0) -> 1 | T57: =IF(AND(E57="M",ISNUMBER(I57)),1,0) -> 0 | U57: =IF(AND(E57="M",ISNUMBER(I57)),IF(I57>=3,1,0),0) -> 0
A58: A6.5 | B58: A6 | C58: Designated public information officer and risk communication plan (incl. rumor/misinformation management) | D58: NDRRMC public info protocols | E58: GP | F58: Risk communication plan; spokesperson designation | G58: DR, KII | H58: 1 | I58: 2 | J58: F: for training and updating. DR: risk communication plan is a planned PPA in 10-Yr Plan. | K58: No approved risk communication plan. | L58: Designate the PIO and write the risk communication plan, including rumour management. | M58: =IF(ISNUMBER(I58),(4-I58)*H58*IF(E58="M",1.5,1),"") -> 2 | N58: =IF(M58="","",IF(M58>=9,"High",IF(M58>=4,"Medium","Low"))) -> Low | O58: =IF(NOT(ISNUMBER(I58)),IF(I58="NA","N/A","Not scored"),IF(E58="M",IF(I58>=3,"Compliant","Non-compliant"),IF(I58>=3,"Meets GP","Below GP"))) -> Below GP | P58: EOC Ch.5 | Q58: =IF(ISNUMBER(I58),I58*H58,0) -> 2 | R58: =IF(ISNUMBER(I58),4*H58,0) -> 4 | S58: =IF(ISNUMBER(I58),1,0) -> 1 | T58: =IF(AND(E58="M",ISNUMBER(I58)),1,0) -> 0 | U58: =IF(AND(E58="M",ISNUMBER(I58)),IF(I58>=3,1,0),0) -> 0
A59: A6.6 | B59: A6 | C59: IEC program on hazards and preparedness with annual reach targets | D59: RA 10121 Sec. 12(c)(13) | E59: GP | F59: IEC plan; reach reports | G59: DR | H59: 1 | I59: 3 | J59: F: for verification at barangay level. | K59: Reach targets to validate. | L59: Set annual reach targets per barangay and report them. | M59: =IF(ISNUMBER(I59),(4-I59)*H59*IF(E59="M",1.5,1),"") -> 1 | N59: =IF(M59="","",IF(M59>=9,"High",IF(M59>=4,"Medium","Low"))) -> Low | O59: =IF(NOT(ISNUMBER(I59)),IF(I59="NA","N/A","Not scored"),IF(E59="M",IF(I59>=3,"Compliant","Non-compliant"),IF(I59>=3,"Meets GP","Below GP"))) -> Meets GP | P59: MOO Ch.6 | Q59: =IF(ISNUMBER(I59),I59*H59,0) -> 3 | R59: =IF(ISNUMBER(I59),4*H59,0) -> 4 | S59: =IF(ISNUMBER(I59),1,0) -> 1 | T59: =IF(AND(E59="M",ISNUMBER(I59)),1,0) -> 0 | U59: =IF(AND(E59="M",ISNUMBER(I59)),IF(I59>=3,1,0),0) -> 0
A60: A6.7 | B60: A6 | C60: Templates and channels for public notice of a State of Imminent Disaster and of the anticipatory actions required, incl. sector-specific impact-based advisories and reach to geographically isolated barangays | D60: RA 12287 IRR (2026) Rule IV Sec. 2 | E60: M | F60: Advisory templates; dissemination log | G60: DR | H60: 2 | I60: 0 | J60: DR: no SID public-notice templates found. | K60: New mandatory item (IRR Rule IV Sec. 2). | L60: Prepare SID public notice templates and sector-specific advisories with channels to isolated barangays. | M60: =IF(ISNUMBER(I60),(4-I60)*H60*IF(E60="M",1.5,1),"") -> 12 | N60: =IF(M60="","",IF(M60>=9,"High",IF(M60>=4,"Medium","Low"))) -> High | O60: =IF(NOT(ISNUMBER(I60)),IF(I60="NA","N/A","Not scored"),IF(E60="M",IF(I60>=3,"Compliant","Non-compliant"),IF(I60>=3,"Meets GP","Below GP"))) -> Non-compliant | P60: MOO Ch.4 / EOC Ch.5 | Q60: =IF(ISNUMBER(I60),I60*H60,0) -> 0 | R60: =IF(ISNUMBER(I60),4*H60,0) -> 8 | S60: =IF(ISNUMBER(I60),1,0) -> 1 | T60: =IF(AND(E60="M",ISNUMBER(I60)),1,0) -> 1 | U60: =IF(AND(E60="M",ISNUMBER(I60)),IF(I60>=3,1,0),0) -> 0
A61: A7 PREPAREDNESS & COMMUNITY CAPACITY - Training, drills, BDRRMCs, evacuation centers, inclusive DRRM
A62: A7.1 | B62: A7 | C62: Annual training program for city personnel, BDRRMCs, schools and communities implemented | D62: RA 10121 Sec. 12(c)(12), Sec. 14 | E62: M | F62: Training calendar; reports; attendance | G62: DR | H62: 2 | I62: 3 | J62: F: for verification. | K62: Validate the training calendar and attendance. | L62: Maintain; merge with the TNA plan (A2.6). | M62: =IF(ISNUMBER(I62),(4-I62)*H62*IF(E62="M",1.5,1),"") -> 3 | N62: =IF(M62="","",IF(M62>=9,"High",IF(M62>=4,"Medium","Low"))) -> Low | O62: =IF(NOT(ISNUMBER(I62)),IF(I62="NA","N/A","Not scored"),IF(E62="M",IF(I62>=3,"Compliant","Non-compliant"),IF(I62>=3,"Meets GP","Below GP"))) -> Compliant | P62: MOO Ch.6 Capacity Development | Q62: =IF(ISNUMBER(I62),I62*H62,0) -> 6 | R62: =IF(ISNUMBER(I62),4*H62,0) -> 8 | S62: =IF(ISNUMBER(I62),1,0) -> 1 | T62: =IF(AND(E62="M",ISNUMBER(I62)),1,0) -> 1 | U62: =IF(AND(E62="M",ISNUMBER(I62)),IF(I62>=3,1,0),0) -> 1
A63: A7.2 | B63: A7 | C63: Participation in quarterly Nationwide Simultaneous Earthquake Drill (NSED) and hazard-specific drills with evaluation | D63: NDRRMC NSED guidelines | E63: M | F63: Drill reports; evaluation forms | G63: DR | H63: 2 | I63: 4 | J63: F: scored 4. | K63: Validate drill evaluation reports. | L63: Maintain. | M63: =IF(ISNUMBER(I63),(4-I63)*H63*IF(E63="M",1.5,1),"") -> 0 | N63: =IF(M63="","",IF(M63>=9,"High",IF(M63>=4,"Medium","Low"))) -> Low | O63: =IF(NOT(ISNUMBER(I63)),IF(I63="NA","N/A","Not scored"),IF(E63="M",IF(I63>=3,"Compliant","Non-compliant"),IF(I63>=3,"Meets GP","Below GP"))) -> Compliant | P63: MOO Ch.6 | Q63: =IF(ISNUMBER(I63),I63*H63,0) -> 8 | R63: =IF(ISNUMBER(I63),4*H63,0) -> 8 | S63: =IF(ISNUMBER(I63),1,0) -> 1 | T63: =IF(AND(E63="M",ISNUMBER(I63)),1,0) -> 1 | U63: =IF(AND(E63="M",ISNUMBER(I63)),IF(I63>=3,1,0),0) -> 1
A64: A7.3 | B64: A7 | C64: BDRRMC functionality across 85 barangays assessed (e.g., Listo si KAP) with support plan for low-functioning barangays | D64: RA 10121; DILG MC 2025-035 (Listo si KAP) | E64: GP | F64: BDRRMC functionality matrix | G64: DR, FGD | H64: 2 | I64: 3 | J64: F: for verification. | K64: Validate the BDRRMC functionality matrix (85 barangays). | L64: Maintain; target low-functioning barangays first. | M64: =IF(ISNUMBER(I64),(4-I64)*H64*IF(E64="M",1.5,1),"") -> 2 | N64: =IF(M64="","",IF(M64>=9,"High",IF(M64>=4,"Medium","Low"))) -> Low | O64: =IF(NOT(ISNUMBER(I64)),IF(I64="NA","N/A","Not scored"),IF(E64="M",IF(I64>=3,"Compliant","Non-compliant"),IF(I64>=3,"Meets GP","Below GP"))) -> Meets GP | P64: MOO Ch.6 | Q64: =IF(ISNUMBER(I64),I64*H64,0) -> 6 | R64: =IF(ISNUMBER(I64),4*H64,0) -> 8 | S64: =IF(ISNUMBER(I64),1,0) -> 1 | T64: =IF(AND(E64="M",ISNUMBER(I64)),1,0) -> 0 | U64: =IF(AND(E64="M",ISNUMBER(I64)),IF(I64>=3,1,0),0) -> 0
A65: A7.4 | B65: A7 | C65: Permanent evacuation center(s) planned/established and existing ECs meet minimum standards (WASH, privacy, PWD access, child-friendly space) | D65: RA 12076 (Ligtas Pinoy Centers Act); RA 10821; DSWD standards | E65: M | F65: EC inventory & audit; site inspection | G65: DR, OBS | H65: 3 | I65: 2 | J65: F: for observation; other ECs need enhancement. DR: 10-Yr Plan plans retrofitting 30 ECs (open covered courts) and MOAs for private alternate ECs. | K65: ECs do not yet meet RA 12076 standards. | L65: Audit ECs against RA 12076/DSWD standards; prioritise retrofits for the 46 critical flood barangays. | M65: =IF(ISNUMBER(I65),(4-I65)*H65*IF(E65="M",1.5,1),"") -> 9 | N65: =IF(M65="","",IF(M65>=9,"High",IF(M65>=4,"Medium","Low"))) -> High | O65: =IF(NOT(ISNUMBER(I65)),IF(I65="NA","N/A","Not scored"),IF(E65="M",IF(I65>=3,"Compliant","Non-compliant"),IF(I65>=3,"Meets GP","Below GP"))) -> Non-compliant | P65: MOO Ch.4 / EOC Ch.6 | Q65: =IF(ISNUMBER(I65),I65*H65,0) -> 6 | R65: =IF(ISNUMBER(I65),4*H65,0) -> 12 | S65: =IF(ISNUMBER(I65),1,0) -> 1 | T65: =IF(AND(E65="M",ISNUMBER(I65)),1,0) -> 1 | U65: =IF(AND(E65="M",ISNUMBER(I65)),IF(I65>=3,1,0),0) -> 0
A66: A7.5 | B66: A7 | C66: Prepositioned relief stocks/food packs and non-food items with inventory and replenishment triggers | D66: RA 10121; DSWD-LGU protocols; Operation L!sto | E66: M | F66: Stock inventory; warehouse inspection | G66: OBS, DR | H66: 2 | I66: 4 | J66: F: scored 4. DR: 10-Yr Plan plans 7 storage facilities and a digital inventory. | K66: Validate warehouse inventory and replenishment triggers. | L66: Maintain; add AA prepositioning triggers. | M66: =IF(ISNUMBER(I66),(4-I66)*H66*IF(E66="M",1.5,1),"") -> 0 | N66: =IF(M66="","",IF(M66>=9,"High",IF(M66>=4,"Medium","Low"))) -> Low | O66: =IF(NOT(ISNUMBER(I66)),IF(I66="NA","N/A","Not scored"),IF(E66="M",IF(I66>=3,"Compliant","Non-compliant"),IF(I66>=3,"Meets GP","Below GP"))) -> Compliant | P66: EOC Ch.6 Logistics | Q66: =IF(ISNUMBER(I66),I66*H66,0) -> 8 | R66: =IF(ISNUMBER(I66),4*H66,0) -> 8 | S66: =IF(ISNUMBER(I66),1,0) -> 1 | T66: =IF(AND(E66="M",ISNUMBER(I66)),1,0) -> 1 | U66: =IF(AND(E66="M",ISNUMBER(I66)),IF(I66>=3,1,0),0) -> 1
A67: A7.6 | B67: A7 | C67: Inclusive DRRM: GAD, PWD, senior citizen, children, IP considerations embedded in plans and services, with vulnerable-sector representatives confirming they were engaged | D67: RA 9710; RA 7277 as amended; RA 9994; RA 10821; RA 8371; RA 12287 IRR (2026) Rule IV Sec. 1(a); UNDRR DRSC 7.2.2 | E67: M | F67: Plans; GAD-tagged budget; inclusion checklist; sector representatives' confirmation (FGD) | G67: DR, FGD | H67: 2 | I67: 3 | J67: F: scored 3. | K67: Sector representatives' confirmation (FGD) not yet gathered. | L67: Hold a short FGD with PWD, senior, women and youth representatives to confirm engagement. | M67: =IF(ISNUMBER(I67),(4-I67)*H67*IF(E67="M",1.5,1),"") -> 3 | N67: =IF(M67="","",IF(M67>=9,"High",IF(M67>=4,"Medium","Low"))) -> Low | O67: =IF(NOT(ISNUMBER(I67)),IF(I67="NA","N/A","Not scored"),IF(E67="M",IF(I67>=3,"Compliant","Non-compliant"),IF(I67>=3,"Meets GP","Below GP"))) -> Compliant | P67: MOO Ch.3 / Ch.4 | Q67: =IF(ISNUMBER(I67),I67*H67,0) -> 6 | R67: =IF(ISNUMBER(I67),4*H67,0) -> 8 | S67: =IF(ISNUMBER(I67),1,0) -> 1 | T67: =IF(AND(E67="M",ISNUMBER(I67)),1,0) -> 1 | U67: =IF(AND(E67="M",ISNUMBER(I67)),IF(I67>=3,1,0),0) -> 1
A68: A7.7 | B68: A7 | C68: Schools, hospitals and critical facilities included in preparedness planning and drills | D68: DepEd/DOH DRRM policies; Safe Schools/Hospitals | E68: GP | F68: Coordination records; joint drills | G68: DR, KII | H68: 1 | I68: 3 | J68: F: for online FGDs. | K68: Validate joint drills with schools and hospitals. | L68: Maintain; include schools and hospitals in the next CP tabletop. | M68: =IF(ISNUMBER(I68),(4-I68)*H68*IF(E68="M",1.5,1),"") -> 1 | N68: =IF(M68="","",IF(M68>=9,"High",IF(M68>=4,"Medium","Low"))) -> Low | O68: =IF(NOT(ISNUMBER(I68)),IF(I68="NA","N/A","Not scored"),IF(E68="M",IF(I68>=3,"Compliant","Non-compliant"),IF(I68>=3,"Meets GP","Below GP"))) -> Meets GP | P68: MOO Ch.6 | Q68: =IF(ISNUMBER(I68),I68*H68,0) -> 3 | R68: =IF(ISNUMBER(I68),4*H68,0) -> 4 | S68: =IF(ISNUMBER(I68),1,0) -> 1 | T68: =IF(AND(E68="M",ISNUMBER(I68)),1,0) -> 0 | U68: =IF(AND(E68="M",ISNUMBER(I68)),IF(I68>=3,1,0),0) -> 0
A69: A7.8 | B69: A7 | C69: Refresher cycle (at least annual) set for trained responders, EOC staff and BDRRMC members, with attendance tracked | D69: UNDRR DRSC 6.4.2 | E69: GP | F69: Training calendar; attendance records | G69: DR | H69: 1 | I69: 1 | J69: F (A8.2): need for continuous training. | K69: No refresher cycle set. | L69: Set an annual refresher cycle for responders, EOC staff and BDRRMC members and track attendance. | M69: =IF(ISNUMBER(I69),(4-I69)*H69*IF(E69="M",1.5,1),"") -> 3 | N69: =IF(M69="","",IF(M69>=9,"High",IF(M69>=4,"Medium","Low"))) -> Low | O69: =IF(NOT(ISNUMBER(I69)),IF(I69="NA","N/A","Not scored"),IF(E69="M",IF(I69>=3,"Compliant","Non-compliant"),IF(I69>=3,"Meets GP","Below GP"))) -> Below GP | P69: MOO Ch.6 | Q69: =IF(ISNUMBER(I69),I69*H69,0) -> 1 | R69: =IF(ISNUMBER(I69),4*H69,0) -> 4 | S69: =IF(ISNUMBER(I69),1,0) -> 1 | T69: =IF(AND(E69="M",ISNUMBER(I69)),1,0) -> 0 | U69: =IF(AND(E69="M",ISNUMBER(I69)),IF(I69>=3,1,0),0) -> 0
A70: A7.9 | B70: A7 | C70: BDRRMCs can account for residents of affected puroks within 12 hours of impact (welfare check), shown in a drill or a real event | D70: UNDRR DRSC 7.2.1 | E70: GP | F70: Drill or AAR record; barangay reports | G70: DR, FGD | H70: 2 | I70: 1 | J70: DR: no drill or AAR record of purok welfare checks found; BDRRMC functionality rated 3 (A7.3); CDRA gives exposed households by barangay for flood, landslide and storm surge. | K70: Provisional desk score: accounting for residents is assumed to be informal (BDRRMC/purok headcounts) with no time standard or record. Confirm in FGDs in sampled barangays. | L70: Add a 12-hour welfare-check step to BDRRMC protocols, using purok household lists (CBMS) and the CDRA exposed-household counts; test it in the next drill and log the time taken. | M70: =IF(ISNUMBER(I70),(4-I70)*H70*IF(E70="M",1.5,1),"") | N70: =IF(M70="","",IF(M70>=9,"High",IF(M70>=4,"Medium","Low"))) | O70: =IF(NOT(ISNUMBER(I70)),IF(I70="NA","N/A","Not scored"),IF(E70="M",IF(I70>=3,"Compliant","Non-compliant"),IF(I70>=3,"Meets GP","Below GP"))) -> Not scored | P70: MOO Ch.4 / EOC Ch.6 | Q70: =IF(ISNUMBER(I70),I70*H70,0) -> 0 | R70: =IF(ISNUMBER(I70),4*H70,0) -> 0 | S70: =IF(ISNUMBER(I70),1,0) -> 0 | T70: =IF(AND(E70="M",ISNUMBER(I70)),1,0) -> 0 | U70: =IF(AND(E70="M",ISNUMBER(I70)),IF(I70>=3,1,0),0) -> 0
A71: A8 RESPONSE CAPABILITY - ICS/IMT, SAR, EMS, equipment, cluster coordination, anticipatory action
A72: A8.1 | B72: A8 | C72: Incident Command System institutionalized: EO on ICS, trained IMT roster, pre-designated Incident Commanders | D72: NDRRMC MC No. 4, s. 2012 (ICS) | E72: M | F72: EO; IMT roster; ICS certificates | G72: DR | H72: 3 | I72: 1 | J72: F: no EO or ordinance on ICS. DR: 10-Yr Plan plans ICS all levels training and an IMT EO (2025). | K72: No ICS EO or IMT roster. | L72: Issue an EO institutionalising ICS with pre-designated ICs and IMT roster; complete ICS training. | M72: =IF(ISNUMBER(I72),(4-I72)*H72*IF(E72="M",1.5,1),"") -> 13.5 | N72: =IF(M72="","",IF(M72>=9,"High",IF(M72>=4,"Medium","Low"))) -> High | O72: =IF(NOT(ISNUMBER(I72)),IF(I72="NA","N/A","Not scored"),IF(E72="M",IF(I72>=3,"Compliant","Non-compliant"),IF(I72>=3,"Meets GP","Below GP"))) -> Non-compliant | P72: MOO Ch.4 Response Operations | Q72: =IF(ISNUMBER(I72),I72*H72,0) -> 3 | R72: =IF(ISNUMBER(I72),4*H72,0) -> 12 | S72: =IF(ISNUMBER(I72),1,0) -> 1 | T72: =IF(AND(E72="M",ISNUMBER(I72)),1,0) -> 1 | U72: =IF(AND(E72="M",ISNUMBER(I72)),IF(I72>=3,1,0),0) -> 0
A73: A8.2 | B73: A8 | C73: Organized and trained response teams: SAR (WASAR/CSSR/HAZMAT as relevant), EMS/ambulance, fire coordination with BFP | D73: RA 10121 Sec. 12(c)(16); RA 11589 (BFP) | E73: M | F73: Team roster; certificates; MOA with BFP | G73: DR, OBS | H73: 3 | I73: 2 | J73: F: continuous training needed; EO needs updating. | K73: Team EO outdated. | L73: Update the response team EO and the BFP MOA; keep certificates current. | M73: =IF(ISNUMBER(I73),(4-I73)*H73*IF(E73="M",1.5,1),"") -> 9 | N73: =IF(M73="","",IF(M73>=9,"High",IF(M73>=4,"Medium","Low"))) -> High | O73: =IF(NOT(ISNUMBER(I73)),IF(I73="NA","N/A","Not scored"),IF(E73="M",IF(I73>=3,"Compliant","Non-compliant"),IF(I73>=3,"Meets GP","Below GP"))) -> Non-compliant | P73: MOO Ch.4 | Q73: =IF(ISNUMBER(I73),I73*H73,0) -> 6 | R73: =IF(ISNUMBER(I73),4*H73,0) -> 12 | S73: =IF(ISNUMBER(I73),1,0) -> 1 | T73: =IF(AND(E73="M",ISNUMBER(I73)),1,0) -> 1 | U73: =IF(AND(E73="M",ISNUMBER(I73)),IF(I73>=3,1,0),0) -> 0
A74: A8.3 | B74: A8 | C74: Response equipment and vehicles inventoried, serviceable and maintained (preventive maintenance schedule) | D74: COA property rules; RA 10121 | E74: M | F74: Property inventory; PM logs; site check | G74: OBS, DR | H74: 2 | I74: 3 | J74: F: PMS needs programming. DR: maintenance engineer and property custodian are planned hires. | K74: No preventive maintenance schedule. | L74: Program a PM schedule for vehicles and equipment and keep logs. | M74: =IF(ISNUMBER(I74),(4-I74)*H74*IF(E74="M",1.5,1),"") -> 3 | N74: =IF(M74="","",IF(M74>=9,"High",IF(M74>=4,"Medium","Low"))) -> Low | O74: =IF(NOT(ISNUMBER(I74)),IF(I74="NA","N/A","Not scored"),IF(E74="M",IF(I74>=3,"Compliant","Non-compliant"),IF(I74>=3,"Meets GP","Below GP"))) -> Compliant | P74: MOO Ch.4 / EOC Ch.6 | Q74: =IF(ISNUMBER(I74),I74*H74,0) -> 6 | R74: =IF(ISNUMBER(I74),4*H74,0) -> 8 | S74: =IF(ISNUMBER(I74),1,0) -> 1 | T74: =IF(AND(E74="M",ISNUMBER(I74)),1,0) -> 1 | U74: =IF(AND(E74="M",ISNUMBER(I74)),IF(I74>=3,1,0),0) -> 1
A75: A8.4 | B75: A8 | C75: Emergency hotline integrated with E911 and dispatch protocol (call-taking to dispatch time tracked) | D75: EO 56 s. 2018 (E911); DILG guidelines | E75: GP | F75: Dispatch logs; SOP; response time data | G75: OBS, DR | H75: 2 | I75: 0 | J75: F: scored 0. DR: 911 emergency dispatch system is a planned PPA in 10-Yr Plan. | K75: No E911 integration or dispatch protocol. | L75: Integrate the hotline with E911 and write the dispatch SOP with response-time tracking. | M75: =IF(ISNUMBER(I75),(4-I75)*H75*IF(E75="M",1.5,1),"") -> 8 | N75: =IF(M75="","",IF(M75>=9,"High",IF(M75>=4,"Medium","Low"))) -> Medium | O75: =IF(NOT(ISNUMBER(I75)),IF(I75="NA","N/A","Not scored"),IF(E75="M",IF(I75>=3,"Compliant","Non-compliant"),IF(I75>=3,"Meets GP","Below GP"))) -> Below GP | P75: EOC Ch.4 | Q75: =IF(ISNUMBER(I75),I75*H75,0) -> 0 | R75: =IF(ISNUMBER(I75),4*H75,0) -> 8 | S75: =IF(ISNUMBER(I75),1,0) -> 1 | T75: =IF(AND(E75="M",ISNUMBER(I75)),1,0) -> 0 | U75: =IF(AND(E75="M",ISNUMBER(I75)),IF(I75>=3,1,0),0) -> 0
A76: A8.5 | B76: A8 | C76: Response clusters organized at city level mirroring national cluster approach (Food & NFI, Health, WASH, CCCM, Logistics, Search Rescue & Retrieval, Law & Order, Education, Protection, ETC, MDM) | D76: NDCC MC No. 12, s. 2008; NDRRM Plan Response pillar | E76: M | F76: EO on clusters; cluster leads list | G76: DR | H76: 2 | I76: 3 | J76: F: CPs for review; cluster capability assessment needed. DR: 10-Yr Plan says response cluster offices are assigned; institutionalisation planned. | K76: Cluster capability not assessed. | L76: Assess cluster capability and adopt a cluster EO aligned to the national response clusters (RDRRMOC SOPG 2022, Table 6: 11 clusters), naming lead and member offices. | M76: =IF(ISNUMBER(I76),(4-I76)*H76*IF(E76="M",1.5,1),"") -> 3 | N76: =IF(M76="","",IF(M76>=9,"High",IF(M76>=4,"Medium","Low"))) -> Low | O76: =IF(NOT(ISNUMBER(I76)),IF(I76="NA","N/A","Not scored"),IF(E76="M",IF(I76>=3,"Compliant","Non-compliant"),IF(I76>=3,"Meets GP","Below GP"))) -> Compliant | P76: EOC Ch.4 | Q76: =IF(ISNUMBER(I76),I76*H76,0) -> 6 | R76: =IF(ISNUMBER(I76),4*H76,0) -> 8 | S76: =IF(ISNUMBER(I76),1,0) -> 1 | T76: =IF(AND(E76="M",ISNUMBER(I76)),1,0) -> 1 | U76: =IF(AND(E76="M",ISNUMBER(I76)),IF(I76>=3,1,0),0) -> 1
A77: A8.6 | B77: A8 | C77: Pre-Disaster Risk Assessment (PDRA) conducted before forecast hazards, with anticipatory actions recorded | D77: NDRRMC PDRA protocol; RA 12287; RA 12287 IRR (2026) Rule II Sec. 5 | E77: M | F77: PDRA minutes/reports (last season) | G77: DR, KII | H77: 3 | I77: 3 | J77: F: scored 3. | K77: AA records in PDRA to be added. | L77: Maintain; record anticipatory actions in each PDRA. | M77: =IF(ISNUMBER(I77),(4-I77)*H77*IF(E77="M",1.5,1),"") -> 4.5 | N77: =IF(M77="","",IF(M77>=9,"High",IF(M77>=4,"Medium","Low"))) -> Medium | O77: =IF(NOT(ISNUMBER(I77)),IF(I77="NA","N/A","Not scored"),IF(E77="M",IF(I77>=3,"Compliant","Non-compliant"),IF(I77>=3,"Meets GP","Below GP"))) -> Compliant | P77: EOC Ch.2 | Q77: =IF(ISNUMBER(I77),I77*H77,0) -> 9 | R77: =IF(ISNUMBER(I77),4*H77,0) -> 12 | S77: =IF(ISNUMBER(I77),1,0) -> 1 | T77: =IF(AND(E77="M",ISNUMBER(I77)),1,0) -> 1 | U77: =IF(AND(E77="M",ISNUMBER(I77)),IF(I77>=3,1,0),0) -> 1
A78: A8.7 | B78: A8 | C78: Management of the Dead and Missing (MDM) and Rapid Damage Assessment & Needs Analysis (RDANA) teams designated and trained | D78: NDRRMC MDM & RDANA guidelines | E78: M | F78: Team EO; certificates; templates | G78: DR | H78: 2 | I78: 1 | J78: F: orientation only. DR: 10-Yr Plan says RDANA/PDNA teams not organised; MDM training planned. | K78: Teams not designated or trained. | L78: Designate MDM and RDANA teams by EO and train them. | M78: =IF(ISNUMBER(I78),(4-I78)*H78*IF(E78="M",1.5,1),"") -> 9 | N78: =IF(M78="","",IF(M78>=9,"High",IF(M78>=4,"Medium","Low"))) -> High | O78: =IF(NOT(ISNUMBER(I78)),IF(I78="NA","N/A","Not scored"),IF(E78="M",IF(I78>=3,"Compliant","Non-compliant"),IF(I78>=3,"Meets GP","Below GP"))) -> Non-compliant | P78: MOO Ch.4 | Q78: =IF(ISNUMBER(I78),I78*H78,0) -> 2 | R78: =IF(ISNUMBER(I78),4*H78,0) -> 8 | S78: =IF(ISNUMBER(I78),1,0) -> 1 | T78: =IF(AND(E78="M",ISNUMBER(I78)),1,0) -> 1 | U78: =IF(AND(E78="M",ISNUMBER(I78)),IF(I78>=3,1,0),0) -> 0
A79: A8.8 | B79: A8 | C79: Anticipatory action protocols by hazard and lead time: office-order templates for prepositioning (relief, medical supplies, animal feed, water and power for evacuation centers), deployment of heavy equipment, transport and personnel, pre-emptive evacuation incl. livestock and pets, CCCM, and safeguarding of critical infrastructure; aligned with CPs, Oplan L!sto and evacuation plans | D79: RA 12287 IRR (2026) Rule IV Secs. 1, 3, 4, 6 | E79: M | F79: AA protocol; office-order template; CP annexes | G79: DR, KII | H79: 3 | I79: 1 | J79: DR: PDRA practised (A8.6), CPs exist, but no hazard/lead-time AA protocol or office-order template found. | K79: New mandatory item (IRR Rule IV). | L79: Write AA protocols by hazard and lead time with office-order templates; walk them through in a PDRA tabletop to reach 3. | M79: =IF(ISNUMBER(I79),(4-I79)*H79*IF(E79="M",1.5,1),"") -> 13.5 | N79: =IF(M79="","",IF(M79>=9,"High",IF(M79>=4,"Medium","Low"))) -> High | O79: =IF(NOT(ISNUMBER(I79)),IF(I79="NA","N/A","Not scored"),IF(E79="M",IF(I79>=3,"Compliant","Non-compliant"),IF(I79>=3,"Meets GP","Below GP"))) -> Non-compliant | P79: EOC Ch.2 / MOO Ch.4 | Q79: =IF(ISNUMBER(I79),I79*H79,0) -> 3 | R79: =IF(ISNUMBER(I79),4*H79,0) -> 12 | S79: =IF(ISNUMBER(I79),1,0) -> 1 | T79: =IF(AND(E79="M",ISNUMBER(I79)),1,0) -> 1 | U79: =IF(AND(E79="M",ISNUMBER(I79)),IF(I79>=3,1,0),0) -> 0
A80: A8.9 | B80: A8 | C80: Anticipatory social amelioration: families identified and prioritized using CBMS or the prevailing registry; data-sharing agreements compliant with RA 10173; local guidelines for anticipatory cash or vouchers issued with the CSWDO | D80: RA 12287 IRR (2026) Rule IV Sec. 7; RA 11315 (CBMS); RA 10173 | E80: M | F80: Local guidelines; data-sharing agreement; targeting method | G80: DR, KII | H80: 2 | I80: 1 | J80: DR: CBMS needs updating; no DSA for beneficiary data (A5.5). | K80: No local AA social amelioration guidelines. | L80: Issue local guidelines with CSWDO for anticipatory cash/vouchers using CBMS, with a DSA. | M80: =IF(ISNUMBER(I80),(4-I80)*H80*IF(E80="M",1.5,1),"") -> 9 | N80: =IF(M80="","",IF(M80>=9,"High",IF(M80>=4,"Medium","Low"))) -> High | O80: =IF(NOT(ISNUMBER(I80)),IF(I80="NA","N/A","Not scored"),IF(E80="M",IF(I80>=3,"Compliant","Non-compliant"),IF(I80>=3,"Meets GP","Below GP"))) -> Non-compliant | P80: MOO Ch.4 | Q80: =IF(ISNUMBER(I80),I80*H80,0) -> 2 | R80: =IF(ISNUMBER(I80),4*H80,0) -> 8 | S80: =IF(ISNUMBER(I80),1,0) -> 1 | T80: =IF(AND(E80="M",ISNUMBER(I80)),1,0) -> 1 | U80: =IF(AND(E80="M",ISNUMBER(I80)),IF(I80>=3,1,0),0) -> 0
A81: A9 REHABILITATION & RECOVERY - PDNA/RDANA, recovery planning, build-back-better
A82: A9.1 | B82: A9 | C82: Post-Disaster Needs Assessment (PDNA) capacity: trained team and templates ready | D82: NDRRMC PDNA guidelines; OCD | E82: GP | F82: Certificates; PDNA templates | G82: DR | H82: 2 | I82: 1 | J82: F: PDNA team not in place. DR: 10-Yr Plan plans 5 PDNA positions (2025). | K82: No trained PDNA team. | L82: Form and train a PDNA team using OCD templates. | M82: =IF(ISNUMBER(I82),(4-I82)*H82*IF(E82="M",1.5,1),"") -> 6 | N82: =IF(M82="","",IF(M82>=9,"High",IF(M82>=4,"Medium","Low"))) -> Medium | O82: =IF(NOT(ISNUMBER(I82)),IF(I82="NA","N/A","Not scored"),IF(E82="M",IF(I82>=3,"Compliant","Non-compliant"),IF(I82>=3,"Meets GP","Below GP"))) -> Below GP | P82: MOO Ch.8 Recovery | Q82: =IF(ISNUMBER(I82),I82*H82,0) -> 2 | R82: =IF(ISNUMBER(I82),4*H82,0) -> 8 | S82: =IF(ISNUMBER(I82),1,0) -> 1 | T82: =IF(AND(E82="M",ISNUMBER(I82)),1,0) -> 0 | U82: =IF(AND(E82="M",ISNUMBER(I82)),IF(I82>=3,1,0),0) -> 0
A83: A9.2 | B83: A9 | C83: Rehabilitation & recovery plan prepared after major events, with build-back-better and resettlement provisions | D83: RA 10121 Sec. 12(c)(11); NDRRMP Pillar 4 | E83: M | F83: Rehab plans; implementation reports | G83: DR | H83: 2 | I83: 4 | J83: F: scored 4; assumptions for projections to be stated. | K83: Validate rehab plans and implementation reports. | L83: Maintain; state assumptions in projections. | M83: =IF(ISNUMBER(I83),(4-I83)*H83*IF(E83="M",1.5,1),"") -> 0 | N83: =IF(M83="","",IF(M83>=9,"High",IF(M83>=4,"Medium","Low"))) -> Low | O83: =IF(NOT(ISNUMBER(I83)),IF(I83="NA","N/A","Not scored"),IF(E83="M",IF(I83>=3,"Compliant","Non-compliant"),IF(I83>=3,"Meets GP","Below GP"))) -> Compliant | P83: MOO Ch.8 | Q83: =IF(ISNUMBER(I83),I83*H83,0) -> 8 | R83: =IF(ISNUMBER(I83),4*H83,0) -> 8 | S83: =IF(ISNUMBER(I83),1,0) -> 1 | T83: =IF(AND(E83="M",ISNUMBER(I83)),1,0) -> 1 | U83: =IF(AND(E83="M",ISNUMBER(I83)),IF(I83>=3,1,0),0) -> 1
A84: A9.3 | B84: A9 | C84: Recovery data (damage, losses, livelihood, housing) tracked to completion | D84: Sendai Framework targets C-D | E84: GP | F84: Recovery monitoring matrix | G84: DR | H84: 1 | I84: 1 | J84: F: not scored. DR: PDNA (Paglaum) and RDANA reports exist but no recovery monitoring matrix. | K84: Provisional: recovery not tracked to completion. | L84: Add a recovery monitoring matrix to the event database (A5.4). | M84: =IF(ISNUMBER(I84),(4-I84)*H84*IF(E84="M",1.5,1),"") -> 3 | N84: =IF(M84="","",IF(M84>=9,"High",IF(M84>=4,"Medium","Low"))) -> Low | O84: =IF(NOT(ISNUMBER(I84)),IF(I84="NA","N/A","Not scored"),IF(E84="M",IF(I84>=3,"Compliant","Non-compliant"),IF(I84>=3,"Meets GP","Below GP"))) -> Below GP | P84: MOO Ch.8 | Q84: =IF(ISNUMBER(I84),I84*H84,0) -> 1 | R84: =IF(ISNUMBER(I84),4*H84,0) -> 4 | S84: =IF(ISNUMBER(I84),1,0) -> 1 | T84: =IF(AND(E84="M",ISNUMBER(I84)),1,0) -> 0 | U84: =IF(AND(E84="M",ISNUMBER(I84)),IF(I84>=3,1,0),0) -> 0
A85: A9.4 | B85: A9 | C85: Psychosocial and livelihood recovery services coordinated with CSWDO, CHO, PESO | D85: RA 11036; DSWD protocols | E85: GP | F85: Referral pathways; MOAs | G85: KII | H85: 1 | I85: 2 | J85: F: not scored. DR: 10-Yr Plan cites a cash-for-work programme. | K85: Provisional: referral pathways and MOAs not sighted. | L85: Write referral pathways with CSWDO, CHO and PESO. | M85: =IF(ISNUMBER(I85),(4-I85)*H85*IF(E85="M",1.5,1),"") -> 2 | N85: =IF(M85="","",IF(M85>=9,"High",IF(M85>=4,"Medium","Low"))) -> Low | O85: =IF(NOT(ISNUMBER(I85)),IF(I85="NA","N/A","Not scored"),IF(E85="M",IF(I85>=3,"Compliant","Non-compliant"),IF(I85>=3,"Meets GP","Below GP"))) -> Below GP | P85: MOO Ch.8 | Q85: =IF(ISNUMBER(I85),I85*H85,0) -> 2 | R85: =IF(ISNUMBER(I85),4*H85,0) -> 4 | S85: =IF(ISNUMBER(I85),1,0) -> 1 | T85: =IF(AND(E85="M",ISNUMBER(I85)),1,0) -> 0 | U85: =IF(AND(E85="M",ISNUMBER(I85)),IF(I85>=3,1,0),0) -> 0
A86: A9.5 | B86: A9 | C86: Pre-disaster recovery framework: roles, PDNA activation, temporary shelter, debris management and recovery fund sources agreed before an event | D86: UNDRR DRSC Essential 10; NDRRMP Pillar 4 | E86: GP | F86: Recovery framework or CP recovery annex | G86: DR | H86: 2 | I86: 1 | J86: DR: recovery plan using PlanSmart Ready to Rebuild is a planned PPA in 10-Yr Plan. | K86: No pre-disaster recovery framework. | L86: Use the OCD/World Bank Ready to Rebuild workbook to prepare a pre-disaster recovery framework. | M86: =IF(ISNUMBER(I86),(4-I86)*H86*IF(E86="M",1.5,1),"") -> 6 | N86: =IF(M86="","",IF(M86>=9,"High",IF(M86>=4,"Medium","Low"))) -> Medium | O86: =IF(NOT(ISNUMBER(I86)),IF(I86="NA","N/A","Not scored"),IF(E86="M",IF(I86>=3,"Compliant","Non-compliant"),IF(I86>=3,"Meets GP","Below GP"))) -> Below GP | P86: MOO Ch.8 | Q86: =IF(ISNUMBER(I86),I86*H86,0) -> 2 | R86: =IF(ISNUMBER(I86),4*H86,0) -> 8 | S86: =IF(ISNUMBER(I86),1,0) -> 1 | T86: =IF(AND(E86="M",ISNUMBER(I86)),1,0) -> 0 | U86: =IF(AND(E86="M",ISNUMBER(I86)),IF(I86>=3,1,0),0) -> 0
A87: A10 PARTNERSHIPS, M&E & ACCOUNTABILITY - MOAs, CSO/private sector, reporting, transparency, learning
A88: A10.1 | B88: A10 | C88: MOAs/ mutual aid agreements with neighbouring LGUs (Kananga, Albuera, Merida, Isabel etc.) and Province of Leyte | D88: RA 10121 Sec. 12(c)(15); RA 7160 Sec. 33 | E88: GP | F88: Signed MOAs | G88: DR | H88: 2 | I88: 1 | J88: F: political dynamics; for reframing. | K88: No mutual aid MOAs. | L88: Reframe as technical mutual-aid MOAs with Kananga, Albuera, Merida, Isabel and the Province; join the Leyte DRRMCs Telecom and Response Network (planned PPA). | M88: =IF(ISNUMBER(I88),(4-I88)*H88*IF(E88="M",1.5,1),"") -> 6 | N88: =IF(M88="","",IF(M88>=9,"High",IF(M88>=4,"Medium","Low"))) -> Medium | O88: =IF(NOT(ISNUMBER(I88)),IF(I88="NA","N/A","Not scored"),IF(E88="M",IF(I88>=3,"Compliant","Non-compliant"),IF(I88>=3,"Meets GP","Below GP"))) -> Below GP | P88: MOO Ch.9 Partnerships / EOC Ch.6 | Q88: =IF(ISNUMBER(I88),I88*H88,0) -> 2 | R88: =IF(ISNUMBER(I88),4*H88,0) -> 8 | S88: =IF(ISNUMBER(I88),1,0) -> 1 | T88: =IF(AND(E88="M",ISNUMBER(I88)),1,0) -> 0 | U88: =IF(AND(E88="M",ISNUMBER(I88)),IF(I88>=3,1,0),0) -> 0
A89: A10.2 | B89: A10 | C89: Partnerships with CSOs, private sector (incl. energy/geothermal operators), academe and faith-based groups documented, with pre- and post-event roles defined and at least annual coordination meetings | D89: RA 10121 Sec. 12(c)(15); UNDRR DRSC 6.1.2, 6.1.4 | E89: GP | F89: MOAs; partner registry; meeting records | G89: DR, KII | H89: 1 | I89: 4 | J89: F: execution instruments in place. DR: EDC partnership cited in 10-Yr Plan. | K89: Validate MOAs and annual coordination meetings. | L89: Maintain; add AA roles to partner MOAs. | M89: =IF(ISNUMBER(I89),(4-I89)*H89*IF(E89="M",1.5,1),"") -> 0 | N89: =IF(M89="","",IF(M89>=9,"High",IF(M89>=4,"Medium","Low"))) -> Low | O89: =IF(NOT(ISNUMBER(I89)),IF(I89="NA","N/A","Not scored"),IF(E89="M",IF(I89>=3,"Compliant","Non-compliant"),IF(I89>=3,"Meets GP","Below GP"))) -> Meets GP | P89: MOO Ch.9 | Q89: =IF(ISNUMBER(I89),I89*H89,0) -> 4 | R89: =IF(ISNUMBER(I89),4*H89,0) -> 4 | S89: =IF(ISNUMBER(I89),1,0) -> 1 | T89: =IF(AND(E89="M",ISNUMBER(I89)),1,0) -> 0 | U89: =IF(AND(E89="M",ISNUMBER(I89)),IF(I89>=3,1,0),0) -> 0
A90: A10.3 | B90: A10 | C90: Regular reporting to OCD Region VIII/RDRRMC and DILG (SitReps, LDRRMF reports, Operation L!sto) | D90: RA 10121; DILG MCs | E90: M | F90: Submission logs | G90: DR | H90: 2 | I90: 4 | J90: F: scored 4. DR: RDRRMC8 Res. 12-006 (DILG VIII memo, 26 Feb 2025) requires the harmonized reporting template. | K90: Confirm the harmonized template is used. | L90: Adopt RDRRMC8 Res. 12-006 locally by CDRRMC resolution. | M90: =IF(ISNUMBER(I90),(4-I90)*H90*IF(E90="M",1.5,1),"") -> 0 | N90: =IF(M90="","",IF(M90>=9,"High",IF(M90>=4,"Medium","Low"))) -> Low | O90: =IF(NOT(ISNUMBER(I90)),IF(I90="NA","N/A","Not scored"),IF(E90="M",IF(I90>=3,"Compliant","Non-compliant"),IF(I90>=3,"Meets GP","Below GP"))) -> Compliant | P90: MOO Ch.7 / EOC Ch.5 | Q90: =IF(ISNUMBER(I90),I90*H90,0) -> 8 | R90: =IF(ISNUMBER(I90),4*H90,0) -> 8 | S90: =IF(ISNUMBER(I90),1,0) -> 1 | T90: =IF(AND(E90="M",ISNUMBER(I90)),1,0) -> 1 | U90: =IF(AND(E90="M",ISNUMBER(I90)),IF(I90>=3,1,0),0) -> 1
A91: A10.4 | B91: A10 | C91: Monitoring & evaluation framework for LDRRMP with indicators and annual review | D91: RA 10121 Sec. 12(c)(6) | E91: M | F91: M&E framework; annual review report | G91: DR | H91: 2 | I91: 2 | J91: F: scored 2. DR: 10-Yr Plan Ch.5 sets a results-based M&E design (UNDRR Ten Essentials base; NDRRMP, DILG capacity pillars and Sendai overlays), a Form 5D monitoring tool and five outputs (annual progress report each January, physical/financial report each December, mid-term report 2029), reported to the CDRRMC and LDC. | K91: Design is approved, but no annual RBME report or baseline database was sighted. | L91: Produce the first annual RBME report (Form 5D) and baseline database; present it to the CDRRMC and LDC; include the IAT results and the CDRA monitoring indicators (CDRA 6.7.1). | M91: =IF(ISNUMBER(I91),(4-I91)*H91*IF(E91="M",1.5,1),"") -> 6 | N91: =IF(M91="","",IF(M91>=9,"High",IF(M91>=4,"Medium","Low"))) -> Medium | O91: =IF(NOT(ISNUMBER(I91)),IF(I91="NA","N/A","Not scored"),IF(E91="M",IF(I91>=3,"Compliant","Non-compliant"),IF(I91>=3,"Meets GP","Below GP"))) -> Non-compliant | P91: MOO Ch.7 | Q91: =IF(ISNUMBER(I91),I91*H91,0) -> 4 | R91: =IF(ISNUMBER(I91),4*H91,0) -> 8 | S91: =IF(ISNUMBER(I91),1,0) -> 1 | T91: =IF(AND(E91="M",ISNUMBER(I91)),1,0) -> 1 | U91: =IF(AND(E91="M",ISNUMBER(I91)),IF(I91>=3,1,0),0) -> 0
A92: A10.5 | B92: A10 | C92: Full Disclosure Policy: LDRRMF and utilization posted publicly | D92: DILG FDP MCs; RA 10121 Sec. 21 | E92: M | F92: FDP portal/board postings | G92: DR, OBS | H92: 1 | I92: 4 | J92: F: scored 4. | K92: Validate FDP postings. | L92: Maintain. | M92: =IF(ISNUMBER(I92),(4-I92)*H92*IF(E92="M",1.5,1),"") -> 0 | N92: =IF(M92="","",IF(M92>=9,"High",IF(M92>=4,"Medium","Low"))) -> Low | O92: =IF(NOT(ISNUMBER(I92)),IF(I92="NA","N/A","Not scored"),IF(E92="M",IF(I92>=3,"Compliant","Non-compliant"),IF(I92>=3,"Meets GP","Below GP"))) -> Compliant | P92: MOO Ch.5 | Q92: =IF(ISNUMBER(I92),I92*H92,0) -> 4 | R92: =IF(ISNUMBER(I92),4*H92,0) -> 4 | S92: =IF(ISNUMBER(I92),1,0) -> 1 | T92: =IF(AND(E92="M",ISNUMBER(I92)),1,0) -> 1 | U92: =IF(AND(E92="M",ISNUMBER(I92)),IF(I92>=3,1,0),0) -> 1
A93: A10.6 | B93: A10 | C93: After-action reviews conducted after significant events and lessons integrated into plans | D93: NDRRMC; good practice | E93: GP | F93: AAR reports; plan revisions | G93: DR, KII | H93: 2 | I93: 4 | J93: F: scored 4. | K93: Validate AAR reports and resulting plan revisions. | L93: Maintain. | M93: =IF(ISNUMBER(I93),(4-I93)*H93*IF(E93="M",1.5,1),"") -> 0 | N93: =IF(M93="","",IF(M93>=9,"High",IF(M93>=4,"Medium","Low"))) -> Low | O93: =IF(NOT(ISNUMBER(I93)),IF(I93="NA","N/A","Not scored"),IF(E93="M",IF(I93>=3,"Compliant","Non-compliant"),IF(I93>=3,"Meets GP","Below GP"))) -> Meets GP | P93: MOO Ch.7 | Q93: =IF(ISNUMBER(I93),I93*H93,0) -> 8 | R93: =IF(ISNUMBER(I93),4*H93,0) -> 8 | S93: =IF(ISNUMBER(I93),1,0) -> 1 | T93: =IF(AND(E93="M",ISNUMBER(I93)),1,0) -> 0 | U93: =IF(AND(E93="M",ISNUMBER(I93)),IF(I93>=3,1,0),0) -> 0
A94: A10.7 | B94: A10 | C94: Participation in performance recognition/assessment systems (Gawad KALASAG Seal, SGLG Disaster Preparedness) and gaps acted upon | D94: NDRRMC GKS guidelines; RA 11292 (SGLG Act) | E94: GP | F94: GKS/SGLG results; action plans | G94: DR | H94: 1 | I94: 3 | J94: F: not scored. DR: 10-Yr Plan cites the Gawad KALASAG Seal of Excellence and SGLG disaster preparedness. | K94: Provisional: action plans on remaining gaps not sighted. | L94: Keep participating; track gaps from GKS/SGLG results. | M94: =IF(ISNUMBER(I94),(4-I94)*H94*IF(E94="M",1.5,1),"") -> 1 | N94: =IF(M94="","",IF(M94>=9,"High",IF(M94>=4,"Medium","Low"))) -> Low | O94: =IF(NOT(ISNUMBER(I94)),IF(I94="NA","N/A","Not scored"),IF(E94="M",IF(I94>=3,"Compliant","Non-compliant"),IF(I94>=3,"Meets GP","Below GP"))) -> Meets GP | P94: MOO Ch.7 | Q94: =IF(ISNUMBER(I94),I94*H94,0) -> 3 | R94: =IF(ISNUMBER(I94),4*H94,0) -> 4 | S94: =IF(ISNUMBER(I94),1,0) -> 1 | T94: =IF(AND(E94="M",ISNUMBER(I94)),1,0) -> 0 | U94: =IF(AND(E94="M",ISNUMBER(I94)),IF(I94>=3,1,0),0) -> 0
A95: A10.8 | B95: A10 | C95: Post-declaration report within 45 days of lifting a State of Imminent Disaster (declaration status, AA fund utilization, estimated economic and social costs minimized); reporting route confirmed with OCD VIII | D95: RA 12287 IRR (2026) Rule VI Sec. 1 | E95: M | F95: Report template; submission log | G95: DR | H95: 2 | I95: 0 | J95: DR: no 45-day report template found. | K95: New mandatory item (IRR Rule VI Sec. 1). | L95: Prepare the 45-day post-declaration report template and confirm the reporting route with OCD VIII. | M95: =IF(ISNUMBER(I95),(4-I95)*H95*IF(E95="M",1.5,1),"") -> 12 | N95: =IF(M95="","",IF(M95>=9,"High",IF(M95>=4,"Medium","Low"))) -> High | O95: =IF(NOT(ISNUMBER(I95)),IF(I95="NA","N/A","Not scored"),IF(E95="M",IF(I95>=3,"Compliant","Non-compliant"),IF(I95>=3,"Meets GP","Below GP"))) -> Non-compliant | P95: MOO Ch.7 / EOC Ch.5 | Q95: =IF(ISNUMBER(I95),I95*H95,0) -> 0 | R95: =IF(ISNUMBER(I95),4*H95,0) -> 8 | S95: =IF(ISNUMBER(I95),1,0) -> 1 | T95: =IF(AND(E95="M",ISNUMBER(I95)),1,0) -> 1 | U95: =IF(AND(E95="M",ISNUMBER(I95)),IF(I95>=3,1,0),0) -> 0
A96: A10.9 | B96: A10 | C96: Structured learning from other LGUs and networks (exchanges, OCD forums, MCR2030), with resulting changes documented | D96: UNDRR DRSC 6.6.1 | E96: GP | F96: Exchange reports; documented changes | G96: DR, KII | H96: 1 | I96: 2 | J96: DR: MCR2030 commitment and NRC Resilient LGU Program cited in 10-Yr Plan. | K96: Changes from learning not documented. | L96: Document changes adopted from exchanges. | M96: =IF(ISNUMBER(I96),(4-I96)*H96*IF(E96="M",1.5,1),"") -> 2 | N96: =IF(M96="","",IF(M96>=9,"High",IF(M96>=4,"Medium","Low"))) -> Low | O96: =IF(NOT(ISNUMBER(I96)),IF(I96="NA","N/A","Not scored"),IF(E96="M",IF(I96>=3,"Compliant","Non-compliant"),IF(I96>=3,"Meets GP","Below GP"))) -> Below GP | P96: MOO Ch.7 | Q96: =IF(ISNUMBER(I96),I96*H96,0) -> 2 | R96: =IF(ISNUMBER(I96),4*H96,0) -> 4 | S96: =IF(ISNUMBER(I96),1,0) -> 1 | T96: =IF(AND(E96="M",ISNUMBER(I96)),1,0) -> 0 | U96: =IF(AND(E96="M",ISNUMBER(I96)),IF(I96>=3,1,0),0) -> 0

Sheet B_EOC
A1: PART B - EMERGENCY OPERATIONS CENTER (EOC) ASSESSMENT
A2: Score in yellow cells only. Type: M = Mandatory (legal/policy compliance), GP = Good practice. Methods: DR document review, KII interview, FGD focus group, OBS observation, TST test/demonstration.
A4: ID | B4: Domain | C4: Indicator | D4: Standard / Policy Reference | E4: Type (M/GP) | F4: Means of Verification | G4: Method | H4: Weight | I4: Score (0-4/NA) | J4: Evidence Observed | K4: Gap / Remarks | L4: Recommended Action | M4: Gap Priority Score | N4: Priority | O4: Compliance Status | P4: Feeds Manual Chapter | Q4: w*score | R4: w*4 | S4: Scored | T4: M scored | U4: M compliant
A5: B1 EOC LEGAL BASIS & CONCEPT OF OPERATIONS - EO/ordinance, alert levels, activation/deactivation triggers
A6: B1.1 | B6: B1 | C6: EOC established by EO/ordinance with defined mandate, authority and relationship to CDRRMC and ICS | D6: NDRRMC MC No. 131, s. 2018 (EOC Guidelines); RA 10121 | E6: M | F6: EO/ordinance | G6: DR | H6: 3 | I6: 2 | J6: DR: activation SOP exists but is not SP-approved (field note, A2.5); no EO creating the EOC was sighted. 10-Yr Plan: OpCen/EOC operates 24/7 but needs a manual/SOP. | K6: Provisional. No EO defining the EOC mandate and its relation to the CDRRMC and ICS. | L6: Issue an EO establishing the City EOC per NDRRMC Memo 131 s.2018: OpCen becomes the EOC on activation; EOC links clusters (resource providers) and IMT (resource user); EOC not co-located with the ICP. | M6: =IF(ISNUMBER(I6),(4-I6)*H6*IF(E6="M",1.5,1),"") -> 9 | N6: =IF(M6="","",IF(M6>=9,"High",IF(M6>=4,"Medium","Low"))) -> High | O6: =IF(NOT(ISNUMBER(I6)),IF(I6="NA","N/A","Not scored"),IF(E6="M",IF(I6>=3,"Compliant","Non-compliant"),IF(I6>=3,"Meets GP","Below GP"))) -> Non-compliant | P6: EOC Ch.1 Legal Basis | Q6: =IF(ISNUMBER(I6),I6*H6,0) -> 6 | R6: =IF(ISNUMBER(I6),4*H6,0) -> 12 | S6: =IF(ISNUMBER(I6),1,0) -> 1 | T6: =IF(AND(E6="M",ISNUMBER(I6)),1,0) -> 1 | U6: =IF(AND(E6="M",ISNUMBER(I6)),IF(I6>=3,1,0),0) -> 0
A7: B1.2 | B7: B1 | C7: Alert/activation levels defined (e.g., White-normal, Blue-alert, Red-full activation) with hazard-based triggers and a defined EOC posture when a State of Imminent Disaster is declared | D7: NDRRMC EOC Guidelines; NDRRMC alert protocol; RA 12287 IRR (2026) Rule IV Sec. 1 | E7: M | F7: Activation matrix | G7: DR | H7: 3 | I7: 2 | J7: DR: activation SOP (field note) and RDRRMC8 Res. 12-006 define White/Blue/Red; Blue = at least 50% of resources ready. RDRRMOC SOPG 2022 (OCD VIII) sets White, Blue and Red alerts with raising and downgrading rules for the regional OpCen. | K7: Provisional. Hazard-based triggers and EOC posture under a State of Imminent Disaster not defined. | L7: Write the activation matrix using NDRRMC Memo 131 s.2018 triggers (9.2.1) and standard alert codes, with the SID posture (IRR Rule IV Sec. 1). Use the RDRRMOC SOPG 2022 alert model (White/Blue/Red; Standby/Alpha/Bravo/Charlie protocols) as the template. | M7: =IF(ISNUMBER(I7),(4-I7)*H7*IF(E7="M",1.5,1),"") -> 9 | N7: =IF(M7="","",IF(M7>=9,"High",IF(M7>=4,"Medium","Low"))) -> High | O7: =IF(NOT(ISNUMBER(I7)),IF(I7="NA","N/A","Not scored"),IF(E7="M",IF(I7>=3,"Compliant","Non-compliant"),IF(I7>=3,"Meets GP","Below GP"))) -> Non-compliant | P7: EOC Ch.2 Concept of Operations | Q7: =IF(ISNUMBER(I7),I7*H7,0) -> 6 | R7: =IF(ISNUMBER(I7),4*H7,0) -> 12 | S7: =IF(ISNUMBER(I7),1,0) -> 1 | T7: =IF(AND(E7="M",ISNUMBER(I7)),1,0) -> 1 | U7: =IF(AND(E7="M",ISNUMBER(I7)),IF(I7>=3,1,0),0) -> 0
A8: B1.3 | B8: B1 | C8: Activation, escalation, de-escalation and deactivation procedures with designated authority | D8: NDRRMC EOC Guidelines | E8: M | F8: SOP; activation logs | G8: DR, KII | H8: 3 | I8: 2 | J8: DR: activation SOP exists (field note, A2.5). | K8: Provisional. Escalation, de-escalation and deactivation triggers and authority not written. | L8: Add escalation/de-escalation/deactivation steps and authority (NDRRMC Memo 131 s.2018 deactivation triggers; RDRRMOC SOPG 2022 raising and downgrading rules) to EOC Manual Ch.2. | M8: =IF(ISNUMBER(I8),(4-I8)*H8*IF(E8="M",1.5,1),"") -> 9 | N8: =IF(M8="","",IF(M8>=9,"High",IF(M8>=4,"Medium","Low"))) -> High | O8: =IF(NOT(ISNUMBER(I8)),IF(I8="NA","N/A","Not scored"),IF(E8="M",IF(I8>=3,"Compliant","Non-compliant"),IF(I8>=3,"Meets GP","Below GP"))) -> Non-compliant | P8: EOC Ch.2 | Q8: =IF(ISNUMBER(I8),I8*H8,0) -> 6 | R8: =IF(ISNUMBER(I8),4*H8,0) -> 12 | S8: =IF(ISNUMBER(I8),1,0) -> 1 | T8: =IF(AND(E8="M",ISNUMBER(I8)),1,0) -> 1 | U8: =IF(AND(E8="M",ISNUMBER(I8)),IF(I8>=3,1,0),0) -> 0
A9: B1.4 | B9: B1 | C9: Concept of operations documents EOC functions: coordination, information management, resource management, policy support | D9: NDRRMC EOC Guidelines | E9: M | F9: ConOps document | G9: DR | H9: 2 | I9: 1 | J9: DR: 10-Yr Plan says EOC operations need institutionalising through a manual/SOP. | K9: Provisional. No ConOps document. | L9: Write the ConOps in EOC Manual Ch.2 around the five NDRRMC Memo 131 s.2018 functions: Management, Operations, Planning, Logistics, Finance/Admin. | M9: =IF(ISNUMBER(I9),(4-I9)*H9*IF(E9="M",1.5,1),"") -> 9 | N9: =IF(M9="","",IF(M9>=9,"High",IF(M9>=4,"Medium","Low"))) -> High | O9: =IF(NOT(ISNUMBER(I9)),IF(I9="NA","N/A","Not scored"),IF(E9="M",IF(I9>=3,"Compliant","Non-compliant"),IF(I9>=3,"Meets GP","Below GP"))) -> Non-compliant | P9: EOC Ch.2 | Q9: =IF(ISNUMBER(I9),I9*H9,0) -> 2 | R9: =IF(ISNUMBER(I9),4*H9,0) -> 8 | S9: =IF(ISNUMBER(I9),1,0) -> 1 | T9: =IF(AND(E9="M",ISNUMBER(I9)),1,0) -> 1 | U9: =IF(AND(E9="M",ISNUMBER(I9)),IF(I9>=3,1,0),0) -> 0
A10: B1.5 | B10: B1 | C10: EOC linkage to Provincial (Leyte) and Regional (OCD VIII) EOCs defined | D10: NDRRMC EOC Guidelines | E10: M | F10: Reporting/coordination protocol | G10: DR, KII | H10: 2 | I10: 2 | J10: DR: regular reporting to OCD VIII/RDRRMC (A10.3 = 4); RDRRMC8 Res. 12-006 sets LGU reporting at 6AM/6PM (White). | K10: Provisional. Coordination protocol with Leyte PDRRMO and OCD VIII EOC not written; ICC-Province relation to confirm. | L10: Write the vertical coordination protocol (reporting times by alert level, channels, RDRRMC 24-h reply for SID requests). | M10: =IF(ISNUMBER(I10),(4-I10)*H10*IF(E10="M",1.5,1),"") -> 6 | N10: =IF(M10="","",IF(M10>=9,"High",IF(M10>=4,"Medium","Low"))) -> Medium | O10: =IF(NOT(ISNUMBER(I10)),IF(I10="NA","N/A","Not scored"),IF(E10="M",IF(I10>=3,"Compliant","Non-compliant"),IF(I10>=3,"Meets GP","Below GP"))) -> Non-compliant | P10: EOC Ch.2 | Q10: =IF(ISNUMBER(I10),I10*H10,0) -> 4 | R10: =IF(ISNUMBER(I10),4*H10,0) -> 8 | S10: =IF(ISNUMBER(I10),1,0) -> 1 | T10: =IF(AND(E10="M",ISNUMBER(I10)),1,0) -> 1 | U10: =IF(AND(E10="M",ISNUMBER(I10)),IF(I10>=3,1,0),0) -> 0
A11: B2 EOC FACILITY, SITE & RESILIENCE - Location safety, structure, power, water, security, alternate EOC
A12: B2.1 | B12: B2 | C12: EOC site located outside high flood, landslide, tsunami and liquefaction zones (checked vs hazard maps) | D12: NDRRMC EOC Guidelines; hazard maps | E12: M | F12: Site hazard overlay; inspection | G12: OBS, DR | H12: 3 | I12: 1 | J12: DR: the EOC site is not located in the 10-Yr Plan, CLUP or CDRA. CDRA and GeoRiskPH flood, landslide and storm-surge maps are available for an overlay; CDRA rates the city highly susceptible to flood and storm surge at the head of Ormoc Bay. | K12: Provisional desk score pending site inspection: no hazard overlay of the EOC site has been done, so compliance cannot be shown. | L12: Overlay the primary and alternate EOC sites on CDRA/GeoRiskPH flood, landslide, storm-surge, liquefaction and tsunami maps; record results on the Site Selection and Mitigation sheets of the OCD EOC Capability Assessment Checklist; if a site is in a high-hazard zone, record mitigation (elevated floor, relocation trigger). | M12: =IF(ISNUMBER(I12),(4-I12)*H12*IF(E12="M",1.5,1),"") | N12: =IF(M12="","",IF(M12>=9,"High",IF(M12>=4,"Medium","Low"))) | O12: =IF(NOT(ISNUMBER(I12)),IF(I12="NA","N/A","Not scored"),IF(E12="M",IF(I12>=3,"Compliant","Non-compliant"),IF(I12>=3,"Meets GP","Below GP"))) -> Not scored | P12: EOC Ch.3 Facility | Q12: =IF(ISNUMBER(I12),I12*H12,0) -> 0 | R12: =IF(ISNUMBER(I12),4*H12,0) -> 0 | S12: =IF(ISNUMBER(I12),1,0) -> 0 | T12: =IF(AND(E12="M",ISNUMBER(I12)),1,0) -> 0 | U12: =IF(AND(E12="M",ISNUMBER(I12)),IF(I12>=3,1,0),0) -> 0
A13: B2.2 | B13: B2 | C13: Building structural integrity assessed (seismic - Philippine Fault proximity) and certified | D13: NBC (PD 1096); NSCP; DPWH | E13: M | F13: Structural assessment; occupancy permit | G13: DR, OBS | H13: 3 | I13: 1 | J13: DR: no structural assessment or occupancy permit for the EOC building sighted. 10-Yr Plan records city hall retrofitting under the 2016-2020 DRRM Plan, but does not say whether the EOC is in that building. The ZO sets a 5-m easement on the Marina Fault trace. | K13: Provisional desk score pending Building Official records. | L13: Ask the Building Official for a structural and seismic assessment of the EOC building (NBCP, NSCP) and its occupancy certificate; record results on the Building Design sheet of the EOC Capability Checklist; schedule retrofit if needed (see C2.1). | M13: =IF(ISNUMBER(I13),(4-I13)*H13*IF(E13="M",1.5,1),"") | N13: =IF(M13="","",IF(M13>=9,"High",IF(M13>=4,"Medium","Low"))) | O13: =IF(NOT(ISNUMBER(I13)),IF(I13="NA","N/A","Not scored"),IF(E13="M",IF(I13>=3,"Compliant","Non-compliant"),IF(I13>=3,"Meets GP","Below GP"))) -> Not scored | P13: EOC Ch.3 | Q13: =IF(ISNUMBER(I13),I13*H13,0) -> 0 | R13: =IF(ISNUMBER(I13),4*H13,0) -> 0 | S13: =IF(ISNUMBER(I13),1,0) -> 0 | T13: =IF(AND(E13="M",ISNUMBER(I13)),1,0) -> 0 | U13: =IF(AND(E13="M",ISNUMBER(I13)),IF(I13>=3,1,0),0) -> 0
A14: B2.3 | B14: B2 | C14: Backup power (generator + fuel for >=72 hours, UPS) tested regularly | D14: NDRRMC EOC Guidelines; good practice | E14: M | F14: Generator test logs; fuel stock | G14: OBS, TST | H14: 3 | I14: 1 | J14: DR: 10-Yr Plan OpCen Program funds fuel, preventive maintenance, supplies and telco; no generator or UPS capacity, test log or 72-hour fuel stock record sighted. | K14: Provisional desk score pending OBS/TST: backup power capability not evidenced. | L14: Inventory the generator (kVA) and UPS; test the generator at full load monthly with a log; keep 72-hour fuel on site and a fuel supply contract for longer events (EOC Checklist, SOP and Supplies sheets). | M14: =IF(ISNUMBER(I14),(4-I14)*H14*IF(E14="M",1.5,1),"") | N14: =IF(M14="","",IF(M14>=9,"High",IF(M14>=4,"Medium","Low"))) | O14: =IF(NOT(ISNUMBER(I14)),IF(I14="NA","N/A","Not scored"),IF(E14="M",IF(I14>=3,"Compliant","Non-compliant"),IF(I14>=3,"Meets GP","Below GP"))) -> Not scored | P14: EOC Ch.3 | Q14: =IF(ISNUMBER(I14),I14*H14,0) -> 0 | R14: =IF(ISNUMBER(I14),4*H14,0) -> 0 | S14: =IF(ISNUMBER(I14),1,0) -> 0 | T14: =IF(AND(E14="M",ISNUMBER(I14)),1,0) -> 0 | U14: =IF(AND(E14="M",ISNUMBER(I14)),IF(I14>=3,1,0),0) -> 0
A15: B2.4 | B15: B2 | C15: Functional layout: operations floor, briefing/decision room, comms room, rest area, sanitation, kitchen | D15: NDRRMC EOC Guidelines | E15: GP | F15: Floor plan; observation | G15: OBS | H15: 2 | I15: 1 | J15: DR: 10-Yr Plan says the City has a fully functional 24/7 EOC with trained personnel; no floor plan or room list sighted. | K15: Provisional desk score pending OBS: operations floor, decision room, comms room, rest and sanitation spaces not confirmed. | L15: Draw the EOC floor plan and check it against the Room Design and Personnel Space sheets of the EOC Capability Checklist (operations room, comms room, briefing room, rest, food, sanitation); list fixes in an EOC Manual annex. | M15: =IF(ISNUMBER(I15),(4-I15)*H15*IF(E15="M",1.5,1),"") | N15: =IF(M15="","",IF(M15>=9,"High",IF(M15>=4,"Medium","Low"))) | O15: =IF(NOT(ISNUMBER(I15)),IF(I15="NA","N/A","Not scored"),IF(E15="M",IF(I15>=3,"Compliant","Non-compliant"),IF(I15>=3,"Meets GP","Below GP"))) -> Not scored | P15: EOC Ch.3 | Q15: =IF(ISNUMBER(I15),I15*H15,0) -> 0 | R15: =IF(ISNUMBER(I15),4*H15,0) -> 0 | S15: =IF(ISNUMBER(I15),1,0) -> 0 | T15: =IF(AND(E15="M",ISNUMBER(I15)),1,0) -> 0 | U15: =IF(AND(E15="M",ISNUMBER(I15)),IF(I15>=3,1,0),0) -> 0
A16: B2.5 | B16: B2 | C16: Water, food and sanitation supplies for EOC staff for >=72 hours | D16: Good practice; PSCP | E16: GP | F16: Inventory | G16: OBS | H16: 1 | I16: 1 | J16: DR: OpCen Program budgets meals support (10-Yr Plan); no 72-hour stock of water, food or sanitation supplies for EOC staff recorded. | K16: Provisional desk score pending OBS. | L16: Stock and log 72-hour water, food, hygiene and medical supplies for the full activated EOC roster; check them quarterly with the warehouse inventory (A7.5). | M16: =IF(ISNUMBER(I16),(4-I16)*H16*IF(E16="M",1.5,1),"") | N16: =IF(M16="","",IF(M16>=9,"High",IF(M16>=4,"Medium","Low"))) | O16: =IF(NOT(ISNUMBER(I16)),IF(I16="NA","N/A","Not scored"),IF(E16="M",IF(I16>=3,"Compliant","Non-compliant"),IF(I16>=3,"Meets GP","Below GP"))) -> Not scored | P16: EOC Ch.3 | Q16: =IF(ISNUMBER(I16),I16*H16,0) -> 0 | R16: =IF(ISNUMBER(I16),4*H16,0) -> 0 | S16: =IF(ISNUMBER(I16),1,0) -> 0 | T16: =IF(AND(E16="M",ISNUMBER(I16)),1,0) -> 0 | U16: =IF(AND(E16="M",ISNUMBER(I16)),IF(I16>=3,1,0),0) -> 0
A17: B2.6 | B17: B2 | C17: Physical security and access control (ID, visitor log, CCTV) | D17: Good practice | E17: GP | F17: Access log; observation | G17: OBS | H17: 1 | I17: 1 | J17: DR: CCTV in the 10-Yr Plan is for hazard monitoring (OpCen integrated EWS); no EOC access-control rule, ID system or visitor log sighted. | K17: Provisional desk score pending OBS. | L17: Write access rules in the EOC Manual: staff IDs, visitor log, badges for agency liaisons, restricted areas (comms, servers); add CCTV at entrances when the OpCen CCTV system is procured. | M17: =IF(ISNUMBER(I17),(4-I17)*H17*IF(E17="M",1.5,1),"") | N17: =IF(M17="","",IF(M17>=9,"High",IF(M17>=4,"Medium","Low"))) | O17: =IF(NOT(ISNUMBER(I17)),IF(I17="NA","N/A","Not scored"),IF(E17="M",IF(I17>=3,"Compliant","Non-compliant"),IF(I17>=3,"Meets GP","Below GP"))) -> Not scored | P17: EOC Ch.3 | Q17: =IF(ISNUMBER(I17),I17*H17,0) -> 0 | R17: =IF(ISNUMBER(I17),4*H17,0) -> 0 | S17: =IF(ISNUMBER(I17),1,0) -> 0 | T17: =IF(AND(E17="M",ISNUMBER(I17)),1,0) -> 0 | U17: =IF(AND(E17="M",ISNUMBER(I17)),IF(I17>=3,1,0),0) -> 0
A18: B2.7 | B18: B2 | C18: Designated and equipped alternate EOC with relocation procedure | D18: PSCP Guidebook; NDRRMC EOC Guidelines | E18: M | F18: Alternate site plan; relocation drill | G18: DR, OBS | H18: 2 | I18: 0 | J18: DR: no alternate EOC designated in the documents reviewed; PSCP not completed (A3.4). NDRRMC Memo 131 s.2018 requires an alternate EOC based on the CP/PSCP; CDRA MDA 7 recommends stronger EOC continuity arrangements. | K18: No alternate EOC, relocation trigger or relocation procedure. Mandatory gap. | L18: Designate an alternate EOC outside the primary site's hazard zones through the PSCP; equip it with a go-kit (radios, laptops, forms, power); write relocation triggers and steps; drill relocation once a year. | M18: =IF(ISNUMBER(I18),(4-I18)*H18*IF(E18="M",1.5,1),"") | N18: =IF(M18="","",IF(M18>=9,"High",IF(M18>=4,"Medium","Low"))) | O18: =IF(NOT(ISNUMBER(I18)),IF(I18="NA","N/A","Not scored"),IF(E18="M",IF(I18>=3,"Compliant","Non-compliant"),IF(I18>=3,"Meets GP","Below GP"))) -> Not scored | P18: EOC Ch.3 / Ch.7 | Q18: =IF(ISNUMBER(I18),I18*H18,0) -> 0 | R18: =IF(ISNUMBER(I18),4*H18,0) -> 0 | S18: =IF(ISNUMBER(I18),1,0) -> 0 | T18: =IF(AND(E18="M",ISNUMBER(I18)),1,0) -> 0 | U18: =IF(AND(E18="M",ISNUMBER(I18)),IF(I18>=3,1,0),0) -> 0
A19: B3 EOC COMMUNICATIONS & ICT - Redundant comms, connectivity, systems, cybersecurity
A20: B3.1 | B20: B3 | C20: Redundant communications: VHF/UHF radio, HF, satellite phone, landline, mobile, internet (min. 3 independent channels) | D20: NDRRMC EOC Guidelines; NTC frequency assignment | E20: M | F20: Comms inventory; radio net test | G20: OBS, TST | H20: 3 | I20: 2 | J20: F (A6.1/A6.3): group chat, VHF radio, PA and megaphones in use; warnings fail when telecom is down. DR: 10-Yr Plan plans the Leyte DRRMCs Telecom and Response Network. | K20: Provisional. Fewer than 3 independent channels proven; HF/satellite not confirmed. | L20: Inventory comms and test at least 3 independent channels (VHF, HF or satellite, landline/mobile); log a weekly radio check (RDRRMC8 practice: HF Tue/Fri, VHF Wed/Fri). | M20: =IF(ISNUMBER(I20),(4-I20)*H20*IF(E20="M",1.5,1),"") -> 9 | N20: =IF(M20="","",IF(M20>=9,"High",IF(M20>=4,"Medium","Low"))) -> High | O20: =IF(NOT(ISNUMBER(I20)),IF(I20="NA","N/A","Not scored"),IF(E20="M",IF(I20>=3,"Compliant","Non-compliant"),IF(I20>=3,"Meets GP","Below GP"))) -> Non-compliant | P20: EOC Ch.4 Communications | Q20: =IF(ISNUMBER(I20),I20*H20,0) -> 6 | R20: =IF(ISNUMBER(I20),4*H20,0) -> 12 | S20: =IF(ISNUMBER(I20),1,0) -> 1 | T20: =IF(AND(E20="M",ISNUMBER(I20)),1,0) -> 1 | U20: =IF(AND(E20="M",ISNUMBER(I20)),IF(I20>=3,1,0),0) -> 0
A21: B3.2 | B21: B3 | C21: Radio network covering all 85 barangays and responders, with call signs and net-control procedure | D21: NTC licensing; ETC cluster | E21: M | F21: Coverage test; frequency licenses | G21: TST, DR | H21: 2 | I21: 2 | J21: F: barangays use VHF radio. Barangay count corrected to 85. | K21: Provisional. Coverage across 85 barangays, call signs and net control not tested. | L21: Run a radio coverage test for all 85 barangays; write net-control procedure and call signs; confirm NTC licences. | M21: =IF(ISNUMBER(I21),(4-I21)*H21*IF(E21="M",1.5,1),"") -> 6 | N21: =IF(M21="","",IF(M21>=9,"High",IF(M21>=4,"Medium","Low"))) -> Medium | O21: =IF(NOT(ISNUMBER(I21)),IF(I21="NA","N/A","Not scored"),IF(E21="M",IF(I21>=3,"Compliant","Non-compliant"),IF(I21>=3,"Meets GP","Below GP"))) -> Non-compliant | P21: EOC Ch.4 | Q21: =IF(ISNUMBER(I21),I21*H21,0) -> 4 | R21: =IF(ISNUMBER(I21),4*H21,0) -> 8 | S21: =IF(ISNUMBER(I21),1,0) -> 1 | T21: =IF(AND(E21="M",ISNUMBER(I21)),1,0) -> 1 | U21: =IF(AND(E21="M",ISNUMBER(I21)),IF(I21>=3,1,0),0) -> 0
A22: B3.3 | B22: B3 | C22: Backup internet (secondary ISP/satellite) and continuity of digital systems | D22: Good practice; DICT | E22: GP | F22: ISP contracts; failover test | G22: OBS, TST | H22: 2 | I22: 1 | J22: DR: 10-Yr Plan OpCen Program funds telco expenses; no second ISP, satellite link or failover test sighted. | K22: Provisional desk score pending KII/OBS. | L22: Contract a second ISP or satellite terminal on a separate path; test failover quarterly; keep offline copies of forms and contact lists (the DRRM platform works offline). | M22: =IF(ISNUMBER(I22),(4-I22)*H22*IF(E22="M",1.5,1),"") | N22: =IF(M22="","",IF(M22>=9,"High",IF(M22>=4,"Medium","Low"))) | O22: =IF(NOT(ISNUMBER(I22)),IF(I22="NA","N/A","Not scored"),IF(E22="M",IF(I22>=3,"Compliant","Non-compliant"),IF(I22>=3,"Meets GP","Below GP"))) -> Not scored | P22: EOC Ch.4 | Q22: =IF(ISNUMBER(I22),I22*H22,0) -> 0 | R22: =IF(ISNUMBER(I22),4*H22,0) -> 0 | S22: =IF(ISNUMBER(I22),1,0) -> 0 | T22: =IF(AND(E22="M",ISNUMBER(I22)),1,0) -> 0 | U22: =IF(AND(E22="M",ISNUMBER(I22)),IF(I22>=3,1,0),0) -> 0
A23: B3.4 | B23: B3 | C23: Communications plan/ directory (agencies, barangays, clusters) updated within last 6 months | D23: NDRRMC EOC Guidelines | E23: M | F23: Directory; version date | G23: DR | H23: 2 | I23: 1 | J23: DR: daily reporting to OCD VIII (A10.3) shows working contacts, but no dated directory of agencies, 85 barangays and clusters was sighted. | K23: Provisional desk score: contacts are held informally by duty staff. | L23: Publish a dated directory (agencies, 85 barangays, cluster leads, utilities, media) as an EOC Manual annex; update it every 6 months and after elections or reassignments. | M23: =IF(ISNUMBER(I23),(4-I23)*H23*IF(E23="M",1.5,1),"") | N23: =IF(M23="","",IF(M23>=9,"High",IF(M23>=4,"Medium","Low"))) | O23: =IF(NOT(ISNUMBER(I23)),IF(I23="NA","N/A","Not scored"),IF(E23="M",IF(I23>=3,"Compliant","Non-compliant"),IF(I23>=3,"Meets GP","Below GP"))) -> Not scored | P23: EOC Ch.4 | Q23: =IF(ISNUMBER(I23),I23*H23,0) -> 0 | R23: =IF(ISNUMBER(I23),4*H23,0) -> 0 | S23: =IF(ISNUMBER(I23),1,0) -> 0 | T23: =IF(AND(E23="M",ISNUMBER(I23)),1,0) -> 0 | U23: =IF(AND(E23="M",ISNUMBER(I23)),IF(I23>=3,1,0),0) -> 0
A24: B3.5 | B24: B3 | C24: Cybersecurity and information security measures for EOC systems | D24: RA 10173; DICT National Cybersecurity Plan | E24: GP | F24: Password/access policy; backups | G24: KII, OBS | H24: 1 | I24: 1 | J24: DR: cloud IMS planned (10-Yr Plan); City DPO and data-sharing agreements not confirmed (A5.5); no EOC access or backup policy sighted. | K24: Provisional desk score pending KII with City ICT. | L24: Adopt an EOC information-security policy: named accounts and role-based access, MFA for admin accounts, daily backups, device sign-out rules, incident reporting to the City DPO (RA 10173). | M24: =IF(ISNUMBER(I24),(4-I24)*H24*IF(E24="M",1.5,1),"") | N24: =IF(M24="","",IF(M24>=9,"High",IF(M24>=4,"Medium","Low"))) | O24: =IF(NOT(ISNUMBER(I24)),IF(I24="NA","N/A","Not scored"),IF(E24="M",IF(I24>=3,"Compliant","Non-compliant"),IF(I24>=3,"Meets GP","Below GP"))) -> Not scored | P24: EOC Ch.4 | Q24: =IF(ISNUMBER(I24),I24*H24,0) -> 0 | R24: =IF(ISNUMBER(I24),4*H24,0) -> 0 | S24: =IF(ISNUMBER(I24),1,0) -> 0 | T24: =IF(AND(E24="M",ISNUMBER(I24)),1,0) -> 0 | U24: =IF(AND(E24="M",ISNUMBER(I24)),IF(I24>=3,1,0),0) -> 0
A25: B3.6 | B25: B3 | C25: Display and monitoring equipment (video wall/monitors, weather feeds, CCTV feeds) | D25: Good practice | E25: GP | F25: Observation | G25: OBS | H25: 1 | I25: 1 | J25: DR: 10-Yr Plan PPA (2023-2025) to procure and install CCTV and hazard monitoring equipment for the OpCen Integrated Multi-hazard EWS; installation status and displays not confirmed. | K25: Provisional desk score pending OBS. | L25: Confirm displays for PAGASA/PHIVOLCS feeds, CCTV and the common operating picture; if missing, include a display wall in the OpCen EWS procurement. | M25: =IF(ISNUMBER(I25),(4-I25)*H25*IF(E25="M",1.5,1),"") | N25: =IF(M25="","",IF(M25>=9,"High",IF(M25>=4,"Medium","Low"))) | O25: =IF(NOT(ISNUMBER(I25)),IF(I25="NA","N/A","Not scored"),IF(E25="M",IF(I25>=3,"Compliant","Non-compliant"),IF(I25>=3,"Meets GP","Below GP"))) -> Not scored | P25: EOC Ch.4 | Q25: =IF(ISNUMBER(I25),I25*H25,0) -> 0 | R25: =IF(ISNUMBER(I25),4*H25,0) -> 0 | S25: =IF(ISNUMBER(I25),1,0) -> 0 | T25: =IF(AND(E25="M",ISNUMBER(I25)),1,0) -> 0 | U25: =IF(AND(E25="M",ISNUMBER(I25)),IF(I25>=3,1,0),0) -> 0
A26: B4 EOC ORGANIZATION & STAFFING - EOC structure, duty roster, cluster/agency desks, fatigue management
A27: B4.1 | B27: B4 | C27: EOC organizational structure defined (EOC Manager, Operations, Planning/Information, Logistics, Admin/Finance, liaison desks) | D27: NDRRMC EOC Guidelines; ICS | E27: M | F27: Organogram; EO | G27: DR | H27: 3 | I27: 1 | J27: F (FGDs): Planning, Operations and Admin sections exist; chain of command and team dynamics unclear. | K27: Provisional. EOC structure with the five NDRRMC Memo 131 s.2018 functions not defined. | L27: Define the EOC organogram (EOC Manager, Operations, Planning, Logistics, Finance/Admin, liaison desks) in EOC Manual Ch.5. | M27: =IF(ISNUMBER(I27),(4-I27)*H27*IF(E27="M",1.5,1),"") -> 13.5 | N27: =IF(M27="","",IF(M27>=9,"High",IF(M27>=4,"Medium","Low"))) -> High | O27: =IF(NOT(ISNUMBER(I27)),IF(I27="NA","N/A","Not scored"),IF(E27="M",IF(I27>=3,"Compliant","Non-compliant"),IF(I27>=3,"Meets GP","Below GP"))) -> Non-compliant | P27: EOC Ch.5 Organization | Q27: =IF(ISNUMBER(I27),I27*H27,0) -> 3 | R27: =IF(ISNUMBER(I27),4*H27,0) -> 12 | S27: =IF(ISNUMBER(I27),1,0) -> 1 | T27: =IF(AND(E27="M",ISNUMBER(I27)),1,0) -> 1 | U27: =IF(AND(E27="M",ISNUMBER(I27)),IF(I27>=3,1,0),0) -> 0
A28: B4.2 | B28: B4 | C28: Pre-designated EOC staff with alternates (at least 2 deep per key position) | D28: NDRRMC EOC Guidelines | E28: M | F28: Roster with alternates | G28: DR | H28: 3 | I28: 1 | J28: DR: plantilla gaps (A2.3 = 2); 10-Yr Plan plans 10 new CDRRMO items; no EOC roster with named alternates sighted. | K28: Provisional: alternates are not named, so 72-hour activation cannot be staffed 2 deep. | L28: Name a primary and 2 alternates for each key EOC position (EOC Manager, Operations, Planning, Logistics, Finance/Admin, liaison), drawing on CDRRMC member offices where CDRRMO staff are short; review the roster each quarter. | M28: =IF(ISNUMBER(I28),(4-I28)*H28*IF(E28="M",1.5,1),"") | N28: =IF(M28="","",IF(M28>=9,"High",IF(M28>=4,"Medium","Low"))) | O28: =IF(NOT(ISNUMBER(I28)),IF(I28="NA","N/A","Not scored"),IF(E28="M",IF(I28>=3,"Compliant","Non-compliant"),IF(I28>=3,"Meets GP","Below GP"))) -> Not scored | P28: EOC Ch.5 | Q28: =IF(ISNUMBER(I28),I28*H28,0) -> 0 | R28: =IF(ISNUMBER(I28),4*H28,0) -> 0 | S28: =IF(ISNUMBER(I28),1,0) -> 0 | T28: =IF(AND(E28="M",ISNUMBER(I28)),1,0) -> 0 | U28: =IF(AND(E28="M",ISNUMBER(I28)),IF(I28>=3,1,0),0) -> 0
A29: B4.3 | B29: B4 | C29: Duty roster for sustained 24/7 operations with shift handover protocol | D29: Good practice | E29: M | F29: Roster; handover forms | G29: DR, OBS | H29: 2 | I29: 2 | J29: DR: 10-Yr Plan says the OpCen is staffed 24/7. | K29: Provisional. Roster and handover protocol not sighted. | L29: Adopt a shift handover form based on the RDRRMOC SOPG 2022 turn-over document and swapping form; keep rosters and signed handovers as proof of use. | M29: =IF(ISNUMBER(I29),(4-I29)*H29*IF(E29="M",1.5,1),"") -> 6 | N29: =IF(M29="","",IF(M29>=9,"High",IF(M29>=4,"Medium","Low"))) -> Medium | O29: =IF(NOT(ISNUMBER(I29)),IF(I29="NA","N/A","Not scored"),IF(E29="M",IF(I29>=3,"Compliant","Non-compliant"),IF(I29>=3,"Meets GP","Below GP"))) -> Non-compliant | P29: EOC Ch.5 | Q29: =IF(ISNUMBER(I29),I29*H29,0) -> 4 | R29: =IF(ISNUMBER(I29),4*H29,0) -> 8 | S29: =IF(ISNUMBER(I29),1,0) -> 1 | T29: =IF(AND(E29="M",ISNUMBER(I29)),1,0) -> 1 | U29: =IF(AND(E29="M",ISNUMBER(I29)),IF(I29>=3,1,0),0) -> 0
A30: B4.4 | B30: B4 | C30: Agency/cluster liaison desks identified (CSWDO, CHO, CEO, PNP, BFP, AFP, DepEd, utilities, Red Cross) | D30: NDCC MC 12 s. 2008; EOC Guidelines | E30: M | F30: Desk assignments | G30: DR | H30: 2 | I30: 2 | J30: DR: 10-Yr Plan says response cluster offices are assigned. | K30: Provisional. Desk assignments not written. | L30: List liaison desks (CSWDO, CHO, CEO, PNP, BFP, AFP, DepEd, utilities, Red Cross) with focal persons. | M30: =IF(ISNUMBER(I30),(4-I30)*H30*IF(E30="M",1.5,1),"") -> 6 | N30: =IF(M30="","",IF(M30>=9,"High",IF(M30>=4,"Medium","Low"))) -> Medium | O30: =IF(NOT(ISNUMBER(I30)),IF(I30="NA","N/A","Not scored"),IF(E30="M",IF(I30>=3,"Compliant","Non-compliant"),IF(I30>=3,"Meets GP","Below GP"))) -> Non-compliant | P30: EOC Ch.5 | Q30: =IF(ISNUMBER(I30),I30*H30,0) -> 4 | R30: =IF(ISNUMBER(I30),4*H30,0) -> 8 | S30: =IF(ISNUMBER(I30),1,0) -> 1 | T30: =IF(AND(E30="M",ISNUMBER(I30)),1,0) -> 1 | U30: =IF(AND(E30="M",ISNUMBER(I30)),IF(I30>=3,1,0),0) -> 0
A31: B4.5 | B31: B4 | C31: Position checklists/job action sheets for each EOC role | D31: Good practice | E31: GP | F31: Job action sheets | G31: DR | H31: 2 | I31: 1 | J31: F (Admin FGD): job descriptions unclear. | K31: Provisional. No job action sheets. | L31: Write job action sheets for every EOC role. | M31: =IF(ISNUMBER(I31),(4-I31)*H31*IF(E31="M",1.5,1),"") -> 6 | N31: =IF(M31="","",IF(M31>=9,"High",IF(M31>=4,"Medium","Low"))) -> Medium | O31: =IF(NOT(ISNUMBER(I31)),IF(I31="NA","N/A","Not scored"),IF(E31="M",IF(I31>=3,"Compliant","Non-compliant"),IF(I31>=3,"Meets GP","Below GP"))) -> Below GP | P31: EOC Ch.5 | Q31: =IF(ISNUMBER(I31),I31*H31,0) -> 2 | R31: =IF(ISNUMBER(I31),4*H31,0) -> 8 | S31: =IF(ISNUMBER(I31),1,0) -> 1 | T31: =IF(AND(E31="M",ISNUMBER(I31)),1,0) -> 0 | U31: =IF(AND(E31="M",ISNUMBER(I31)),IF(I31>=3,1,0),0) -> 0
A32: B4.6 | B32: B4 | C32: Responder welfare in EOC: rest cycles, meals, MHPSS, family support | D32: RA 11036; good practice | E32: GP | F32: Policy; observation | G32: KII | H32: 1 | I32: 1 | J32: F (A2.7): welfare programme scored 1. NDRRMC Memo 131 s.2018 requires EOC personnel welfare. | K32: Provisional. | L32: Add rest cycles, meals and MHPSS to EOC Manual Ch.5. | M32: =IF(ISNUMBER(I32),(4-I32)*H32*IF(E32="M",1.5,1),"") -> 3 | N32: =IF(M32="","",IF(M32>=9,"High",IF(M32>=4,"Medium","Low"))) -> Low | O32: =IF(NOT(ISNUMBER(I32)),IF(I32="NA","N/A","Not scored"),IF(E32="M",IF(I32>=3,"Compliant","Non-compliant"),IF(I32>=3,"Meets GP","Below GP"))) -> Below GP | P32: EOC Ch.5 | Q32: =IF(ISNUMBER(I32),I32*H32,0) -> 1 | R32: =IF(ISNUMBER(I32),4*H32,0) -> 4 | S32: =IF(ISNUMBER(I32),1,0) -> 1 | T32: =IF(AND(E32="M",ISNUMBER(I32)),1,0) -> 0 | U32: =IF(AND(E32="M",ISNUMBER(I32)),IF(I32>=3,1,0),0) -> 0
A33: B5 INFORMATION MANAGEMENT & REPORTING - SitReps, common operating picture, GIS, reporting timelines
A34: B5.1 | B34: B5 | C34: Standard SitRep/ Report templates aligned with NDRRMC/OCD formats and fixed reporting schedule | D34: NDRRMC reporting protocol | E34: M | F34: Templates; sample SitReps | G34: DR | H34: 3 | I34: 2 | J34: DR: RDRRMC8 Res. 12-006 harmonized template (pre-, during, post- and terminal reports) directed for LDRRMC adoption by DILG VIII memo of 26 Feb 2025; regular reporting scored 4 (A10.3). | K34: Provisional. Local adoption not shown. | L34: Adopt the harmonized template and reporting schedule by CDRRMC resolution and put it in EOC Manual Ch.6, with file-naming rules modelled on RDRRMOC SOPG 2022 (Tables 4-5). | M34: =IF(ISNUMBER(I34),(4-I34)*H34*IF(E34="M",1.5,1),"") -> 9 | N34: =IF(M34="","",IF(M34>=9,"High",IF(M34>=4,"Medium","Low"))) -> High | O34: =IF(NOT(ISNUMBER(I34)),IF(I34="NA","N/A","Not scored"),IF(E34="M",IF(I34>=3,"Compliant","Non-compliant"),IF(I34>=3,"Meets GP","Below GP"))) -> Non-compliant | P34: EOC Ch.6 Information Mgmt | Q34: =IF(ISNUMBER(I34),I34*H34,0) -> 6 | R34: =IF(ISNUMBER(I34),4*H34,0) -> 12 | S34: =IF(ISNUMBER(I34),1,0) -> 1 | T34: =IF(AND(E34="M",ISNUMBER(I34)),1,0) -> 1 | U34: =IF(AND(E34="M",ISNUMBER(I34)),IF(I34>=3,1,0),0) -> 0
A35: B5.2 | B35: B5 | C35: Barangay-to-city reporting flow (BDRRMC -> EOC) with defined timelines and formats | D35: RA 10121; DILG | E35: M | F35: Flowchart; sample reports | G35: DR, FGD | H35: 3 | I35: 1 | J35: DR: city-barangay coordination protocol and standardised reporting templates are planned PPAs (10-Yr Plan). | K35: Provisional. No barangay-to-EOC flow with times. | L35: Write the BDRRMC -> EOC reporting flow with times (before the city's 6AM/6PM submission) and formats. | M35: =IF(ISNUMBER(I35),(4-I35)*H35*IF(E35="M",1.5,1),"") -> 13.5 | N35: =IF(M35="","",IF(M35>=9,"High",IF(M35>=4,"Medium","Low"))) -> High | O35: =IF(NOT(ISNUMBER(I35)),IF(I35="NA","N/A","Not scored"),IF(E35="M",IF(I35>=3,"Compliant","Non-compliant"),IF(I35>=3,"Meets GP","Below GP"))) -> Non-compliant | P35: EOC Ch.6 | Q35: =IF(ISNUMBER(I35),I35*H35,0) -> 3 | R35: =IF(ISNUMBER(I35),4*H35,0) -> 12 | S35: =IF(ISNUMBER(I35),1,0) -> 1 | T35: =IF(AND(E35="M",ISNUMBER(I35)),1,0) -> 1 | U35: =IF(AND(E35="M",ISNUMBER(I35)),IF(I35>=3,1,0),0) -> 0
A36: B5.3 | B36: B5 | C36: Common Operating Picture maintained (dashboard/ GIS map of incidents, evacuees, resources) | D36: NDRRMC EOC Guidelines | E36: GP | F36: Dashboard; observation | G36: OBS | H36: 2 | I36: 1 | J36: DR: cloud IMS planned. | K36: Provisional. No COP dashboard sighted. | L36: Set up a COP map of incidents, evacuees and resources (the DRRM platform can serve). | M36: =IF(ISNUMBER(I36),(4-I36)*H36*IF(E36="M",1.5,1),"") -> 6 | N36: =IF(M36="","",IF(M36>=9,"High",IF(M36>=4,"Medium","Low"))) -> Medium | O36: =IF(NOT(ISNUMBER(I36)),IF(I36="NA","N/A","Not scored"),IF(E36="M",IF(I36>=3,"Compliant","Non-compliant"),IF(I36>=3,"Meets GP","Below GP"))) -> Below GP | P36: EOC Ch.6 | Q36: =IF(ISNUMBER(I36),I36*H36,0) -> 2 | R36: =IF(ISNUMBER(I36),4*H36,0) -> 8 | S36: =IF(ISNUMBER(I36),1,0) -> 1 | T36: =IF(AND(E36="M",ISNUMBER(I36)),1,0) -> 0 | U36: =IF(AND(E36="M",ISNUMBER(I36)),IF(I36>=3,1,0),0) -> 0
A37: B5.4 | B37: B5 | C37: Evacuation center and affected-family tracking (DAFAC/ registration) feeds EOC data | D37: DSWD DAFAC; RA 10821 | E37: M | F37: DAFAC records; EC reports | G37: DR | H37: 2 | I37: 2 | J37: DR: OpCen compiles RDANA reports with affected families and damage (cited as sources in the 10-Yr Plan); digitised IDP registration is a 10-Yr Plan PPA; DAFAC use not sighted. | K37: Provisional: EC data reach the EOC through RDANA reports and SitReps, but not through a defined DAFAC feed with fixed times. | L37: Use DSWD DAFAC at all ECs; set an EC-to-EOC count report (families, persons, sex/age/PWD) at fixed times; keep names in CSWDO records only and counts in EOC dashboards (RA 10173). | M37: =IF(ISNUMBER(I37),(4-I37)*H37*IF(E37="M",1.5,1),"") | N37: =IF(M37="","",IF(M37>=9,"High",IF(M37>=4,"Medium","Low"))) | O37: =IF(NOT(ISNUMBER(I37)),IF(I37="NA","N/A","Not scored"),IF(E37="M",IF(I37>=3,"Compliant","Non-compliant"),IF(I37>=3,"Meets GP","Below GP"))) -> Not scored | P37: EOC Ch.6 | Q37: =IF(ISNUMBER(I37),I37*H37,0) -> 0 | R37: =IF(ISNUMBER(I37),4*H37,0) -> 0 | S37: =IF(ISNUMBER(I37),1,0) -> 0 | T37: =IF(AND(E37="M",ISNUMBER(I37)),1,0) -> 0 | U37: =IF(AND(E37="M",ISNUMBER(I37)),IF(I37>=3,1,0),0) -> 0
A38: B5.5 | B38: B5 | C38: EOC logbook/ significant events log and document retention | D38: Good practice; NAP rules | E38: M | F38: Logbook; records schedule | G38: DR, OBS | H38: 2 | I38: 1 | J38: DR: no EOC logbook or records retention schedule sighted; the RDRRMOC SOPG 2022 model requires a duty personnel journal/logbook and turn-over document. | K38: Provisional desk score pending OBS. | L38: Keep a bound or append-only digital significant-events log (time, source, action, initials); adopt a records retention schedule with the City Records Officer. | M38: =IF(ISNUMBER(I38),(4-I38)*H38*IF(E38="M",1.5,1),"") | N38: =IF(M38="","",IF(M38>=9,"High",IF(M38>=4,"Medium","Low"))) | O38: =IF(NOT(ISNUMBER(I38)),IF(I38="NA","N/A","Not scored"),IF(E38="M",IF(I38>=3,"Compliant","Non-compliant"),IF(I38>=3,"Meets GP","Below GP"))) -> Not scored | P38: EOC Ch.6 | Q38: =IF(ISNUMBER(I38),I38*H38,0) -> 0 | R38: =IF(ISNUMBER(I38),4*H38,0) -> 0 | S38: =IF(ISNUMBER(I38),1,0) -> 0 | T38: =IF(AND(E38="M",ISNUMBER(I38)),1,0) -> 0 | U38: =IF(AND(E38="M",ISNUMBER(I38)),IF(I38>=3,1,0),0) -> 0
A39: B5.6 | B39: B5 | C39: Weather/hazard monitoring routine (PAGASA, PHIVOLCS feeds) with bulletins logged and disseminated | D39: RA 10121; PAGASA protocols | E39: M | F39: Monitoring log | G39: DR, OBS | H39: 2 | I39: 2 | J39: DR: PDRA conducted before forecast hazards (A8.6 = 3) implies bulletin monitoring. | K39: Provisional. Monitoring log not sighted. | L39: Keep a bulletin log with time received and disseminated. | M39: =IF(ISNUMBER(I39),(4-I39)*H39*IF(E39="M",1.5,1),"") -> 6 | N39: =IF(M39="","",IF(M39>=9,"High",IF(M39>=4,"Medium","Low"))) -> Medium | O39: =IF(NOT(ISNUMBER(I39)),IF(I39="NA","N/A","Not scored"),IF(E39="M",IF(I39>=3,"Compliant","Non-compliant"),IF(I39>=3,"Meets GP","Below GP"))) -> Non-compliant | P39: EOC Ch.6 | Q39: =IF(ISNUMBER(I39),I39*H39,0) -> 4 | R39: =IF(ISNUMBER(I39),4*H39,0) -> 8 | S39: =IF(ISNUMBER(I39),1,0) -> 1 | T39: =IF(AND(E39="M",ISNUMBER(I39)),1,0) -> 1 | U39: =IF(AND(E39="M",ISNUMBER(I39)),IF(I39>=3,1,0),0) -> 0
A40: B5.7 | B40: B5 | C40: Inbound citizen reporting (hotline, SMS, social media) feeds the common operating picture after a verification step | D40: UNDRR DRSC 7.4.2 | E40: GP | F40: Intake log; verification SOP; dashboard | G40: OBS, DR | H40: 1 | I40: 1 | J40: DR: no E911 (A8.4 = 0). | K40: Provisional. | L40: Add an intake and verification step for hotline/SMS/social media reports. | M40: =IF(ISNUMBER(I40),(4-I40)*H40*IF(E40="M",1.5,1),"") -> 3 | N40: =IF(M40="","",IF(M40>=9,"High",IF(M40>=4,"Medium","Low"))) -> Low | O40: =IF(NOT(ISNUMBER(I40)),IF(I40="NA","N/A","Not scored"),IF(E40="M",IF(I40>=3,"Compliant","Non-compliant"),IF(I40>=3,"Meets GP","Below GP"))) -> Below GP | P40: EOC Ch.6 | Q40: =IF(ISNUMBER(I40),I40*H40,0) -> 1 | R40: =IF(ISNUMBER(I40),4*H40,0) -> 4 | S40: =IF(ISNUMBER(I40),1,0) -> 1 | T40: =IF(AND(E40="M",ISNUMBER(I40)),1,0) -> 0 | U40: =IF(AND(E40="M",ISNUMBER(I40)),IF(I40>=3,1,0),0) -> 0
A41: B6 COORDINATION & RESOURCE MANAGEMENT - ICS-EOC interface, clusters, resource tracking, mutual aid
A42: B6.1 | B42: B6 | C42: ICS-EOC interface defined: EOC supports Incident Commander(s); no duplication of command | D42: NDRRMC MC No. 4 s. 2012; EOC Guidelines | E42: M | F42: SOP; organigram showing relationships | G42: DR, KII | H42: 3 | I42: 1 | J42: F (Operations FGD, formerly under A1.2): chain of command unclear; section SOPs not harmonised. No ICS EO (A8.1 = 1). | K42: Provisional. ICS-EOC interface not defined. | L42: Define the interface per NDRRMC Memo 131 s.2018: EOC supports the IC; clusters provide resources; no command from the EOC. | M42: =IF(ISNUMBER(I42),(4-I42)*H42*IF(E42="M",1.5,1),"") -> 13.5 | N42: =IF(M42="","",IF(M42>=9,"High",IF(M42>=4,"Medium","Low"))) -> High | O42: =IF(NOT(ISNUMBER(I42)),IF(I42="NA","N/A","Not scored"),IF(E42="M",IF(I42>=3,"Compliant","Non-compliant"),IF(I42>=3,"Meets GP","Below GP"))) -> Non-compliant | P42: EOC Ch.7 Coordination | Q42: =IF(ISNUMBER(I42),I42*H42,0) -> 3 | R42: =IF(ISNUMBER(I42),4*H42,0) -> 12 | S42: =IF(ISNUMBER(I42),1,0) -> 1 | T42: =IF(AND(E42="M",ISNUMBER(I42)),1,0) -> 1 | U42: =IF(AND(E42="M",ISNUMBER(I42)),IF(I42>=3,1,0),0) -> 0
A43: B6.2 | B43: B6 | C43: Resource management system: request, tracking, mobilization and demobilization of resources | D43: ICS resource management; EOC Guidelines | E43: M | F43: Resource request forms; tracking sheet | G43: DR, OBS | H43: 3 | I43: 1 | J43: DR: digital inventory planned (10-Yr Plan). | K43: Provisional. No request/tracking forms sighted. | L43: Adopt ICS resource request and tracking forms. | M43: =IF(ISNUMBER(I43),(4-I43)*H43*IF(E43="M",1.5,1),"") -> 13.5 | N43: =IF(M43="","",IF(M43>=9,"High",IF(M43>=4,"Medium","Low"))) -> High | O43: =IF(NOT(ISNUMBER(I43)),IF(I43="NA","N/A","Not scored"),IF(E43="M",IF(I43>=3,"Compliant","Non-compliant"),IF(I43>=3,"Meets GP","Below GP"))) -> Non-compliant | P43: EOC Ch.7 | Q43: =IF(ISNUMBER(I43),I43*H43,0) -> 3 | R43: =IF(ISNUMBER(I43),4*H43,0) -> 12 | S43: =IF(ISNUMBER(I43),1,0) -> 1 | T43: =IF(AND(E43="M",ISNUMBER(I43)),1,0) -> 1 | U43: =IF(AND(E43="M",ISNUMBER(I43)),IF(I43>=3,1,0),0) -> 0
A44: B6.3 | B44: B6 | C44: Resource inventory (city, barangays, partners, private sector) accessible from EOC | D44: RA 10121; ICS | E44: M | F44: Resource database | G44: DR, OBS | H44: 2 | I44: 2 | J44: F (A8.3): equipment inventoried. | K44: Provisional. Barangay, partner and private-sector resources not included. | L44: Extend the inventory to barangays, partners and suppliers. | M44: =IF(ISNUMBER(I44),(4-I44)*H44*IF(E44="M",1.5,1),"") -> 6 | N44: =IF(M44="","",IF(M44>=9,"High",IF(M44>=4,"Medium","Low"))) -> Medium | O44: =IF(NOT(ISNUMBER(I44)),IF(I44="NA","N/A","Not scored"),IF(E44="M",IF(I44>=3,"Compliant","Non-compliant"),IF(I44>=3,"Meets GP","Below GP"))) -> Non-compliant | P44: EOC Ch.7 | Q44: =IF(ISNUMBER(I44),I44*H44,0) -> 4 | R44: =IF(ISNUMBER(I44),4*H44,0) -> 8 | S44: =IF(ISNUMBER(I44),1,0) -> 1 | T44: =IF(AND(E44="M",ISNUMBER(I44)),1,0) -> 1 | U44: =IF(AND(E44="M",ISNUMBER(I44)),IF(I44>=3,1,0),0) -> 0
A45: B6.4 | B45: B6 | C45: Procedures for receiving and managing external assistance/ donations and volunteers | D45: NDRRMC guidelines on international/ external assistance | E45: GP | F45: SOP | G45: DR | H45: 1 | I45: 2 | J45: DR: 10-Yr Plan says a donations/relief system is established. | K45: Provisional. SOP not sighted. | L45: Write the donations and volunteer SOP. | M45: =IF(ISNUMBER(I45),(4-I45)*H45*IF(E45="M",1.5,1),"") -> 2 | N45: =IF(M45="","",IF(M45>=9,"High",IF(M45>=4,"Medium","Low"))) -> Low | O45: =IF(NOT(ISNUMBER(I45)),IF(I45="NA","N/A","Not scored"),IF(E45="M",IF(I45>=3,"Compliant","Non-compliant"),IF(I45>=3,"Meets GP","Below GP"))) -> Below GP | P45: EOC Ch.7 | Q45: =IF(ISNUMBER(I45),I45*H45,0) -> 2 | R45: =IF(ISNUMBER(I45),4*H45,0) -> 4 | S45: =IF(ISNUMBER(I45),1,0) -> 1 | T45: =IF(AND(E45="M",ISNUMBER(I45)),1,0) -> 0 | U45: =IF(AND(E45="M",ISNUMBER(I45)),IF(I45>=3,1,0),0) -> 0
A46: B6.5 | B46: B6 | C46: Decision-support briefings to CDRRMC/Mayor at fixed intervals during activation | D46: EOC Guidelines | E46: GP | F46: Briefing records | G46: DR, KII | H46: 2 | I46: 2 | J46: DR: PDRA meetings are held before forecast hazards (A8.6 = 3) and the CDRRMC meets as needed (A1.3 = 4); no fixed briefing intervals or briefing records during activation sighted. | K46: Provisional: briefings happen through PDRA and CDRRMC meetings, but not at fixed intervals by alert level. | L46: Set briefing times by alert level (e.g., Blue: twice daily; Red: every 6 hours) to the Mayor/CDRRMC; use a one-page briefing template linked to the SitRep; file the briefing notes. | M46: =IF(ISNUMBER(I46),(4-I46)*H46*IF(E46="M",1.5,1),"") | N46: =IF(M46="","",IF(M46>=9,"High",IF(M46>=4,"Medium","Low"))) | O46: =IF(NOT(ISNUMBER(I46)),IF(I46="NA","N/A","Not scored"),IF(E46="M",IF(I46>=3,"Compliant","Non-compliant"),IF(I46>=3,"Meets GP","Below GP"))) -> Not scored | P46: EOC Ch.7 | Q46: =IF(ISNUMBER(I46),I46*H46,0) -> 0 | R46: =IF(ISNUMBER(I46),4*H46,0) -> 0 | S46: =IF(ISNUMBER(I46),1,0) -> 0 | T46: =IF(AND(E46="M",ISNUMBER(I46)),1,0) -> 0 | U46: =IF(AND(E46="M",ISNUMBER(I46)),IF(I46>=3,1,0),0) -> 0
A47: B6.6 | B47: B6 | C47: Pre-arranged resource commitments from partners and suppliers set out by item, quantity, activation trigger and contact in signed agreements (incl. supplier agreements tapped for anticipatory action) | D47: UNDRR DRSC 1.2.4; RA 12287 IRR (2026) Rule IV Sec. 6(a)(ii) | E47: GP | F47: Signed agreements with schedules | G47: DR | H47: 2 | I47: 1 | J47: DR: telco restoration and construction-firm debris MOAs are planned PPAs (10-Yr Plan); supplier list exists (A4.5). | K47: Provisional. No signed schedules of committed resources. | L47: Sign agreements listing item, quantity, trigger and contact, usable for AA (IRR Rule IV Sec. 6). | M47: =IF(ISNUMBER(I47),(4-I47)*H47*IF(E47="M",1.5,1),"") -> 6 | N47: =IF(M47="","",IF(M47>=9,"High",IF(M47>=4,"Medium","Low"))) -> Medium | O47: =IF(NOT(ISNUMBER(I47)),IF(I47="NA","N/A","Not scored"),IF(E47="M",IF(I47>=3,"Compliant","Non-compliant"),IF(I47>=3,"Meets GP","Below GP"))) -> Below GP | P47: EOC Ch.7 | Q47: =IF(ISNUMBER(I47),I47*H47,0) -> 2 | R47: =IF(ISNUMBER(I47),4*H47,0) -> 8 | S47: =IF(ISNUMBER(I47),1,0) -> 1 | T47: =IF(AND(E47="M",ISNUMBER(I47)),1,0) -> 0 | U47: =IF(AND(E47="M",ISNUMBER(I47)),IF(I47>=3,1,0),0) -> 0
A48: B7 EOC SOPS, TRAINING, EXERCISES & CONTINUITY - SOPs, exercises, after-action review, sustainability
A49: B7.1 | B49: B7 | C49: Written EOC SOPs/ Manual approved and disseminated to all EOC staff | D49: NDRRMC EOC Guidelines | E49: M | F49: Approved manual; distribution log | G49: DR | H49: 3 | I49: 2 | J49: DR: activation SOP (draft, not approved); EOC Manual being prepared under this MOP engagement. | K49: Provisional. | L49: Complete, approve and distribute the EOC Manual. | M49: =IF(ISNUMBER(I49),(4-I49)*H49*IF(E49="M",1.5,1),"") -> 9 | N49: =IF(M49="","",IF(M49>=9,"High",IF(M49>=4,"Medium","Low"))) -> High | O49: =IF(NOT(ISNUMBER(I49)),IF(I49="NA","N/A","Not scored"),IF(E49="M",IF(I49>=3,"Compliant","Non-compliant"),IF(I49>=3,"Meets GP","Below GP"))) -> Non-compliant | P49: EOC Manual (whole) | Q49: =IF(ISNUMBER(I49),I49*H49,0) -> 6 | R49: =IF(ISNUMBER(I49),4*H49,0) -> 12 | S49: =IF(ISNUMBER(I49),1,0) -> 1 | T49: =IF(AND(E49="M",ISNUMBER(I49)),1,0) -> 1 | U49: =IF(AND(E49="M",ISNUMBER(I49)),IF(I49>=3,1,0),0) -> 0
A50: B7.2 | B50: B7 | C50: EOC staff trained (EOC operations course, ICS, IM) with records | D50: OCD/DRRM training; NDRRMC EOC Guidelines | E50: M | F50: Training records | G50: DR | H50: 2 | I50: 2 | J50: DR: 10-Yr Plan says trained personnel staff the EOC but need ICS all levels, EOC Management and MDM training. | K50: Provisional. | L50: Complete EOC Management and ICS courses for all EOC staff. | M50: =IF(ISNUMBER(I50),(4-I50)*H50*IF(E50="M",1.5,1),"") -> 6 | N50: =IF(M50="","",IF(M50>=9,"High",IF(M50>=4,"Medium","Low"))) -> Medium | O50: =IF(NOT(ISNUMBER(I50)),IF(I50="NA","N/A","Not scored"),IF(E50="M",IF(I50>=3,"Compliant","Non-compliant"),IF(I50>=3,"Meets GP","Below GP"))) -> Non-compliant | P50: EOC Ch.8 Training & Exercises | Q50: =IF(ISNUMBER(I50),I50*H50,0) -> 4 | R50: =IF(ISNUMBER(I50),4*H50,0) -> 8 | S50: =IF(ISNUMBER(I50),1,0) -> 1 | T50: =IF(AND(E50="M",ISNUMBER(I50)),1,0) -> 1 | U50: =IF(AND(E50="M",ISNUMBER(I50)),IF(I50>=3,1,0),0) -> 0
A51: B7.3 | B51: B7 | C51: Annual exercise program (tabletop, functional, full-scale) testing EOC activation | D51: NDRRMC; HSEEP-style good practice | E51: M | F51: Exercise reports | G51: DR | H51: 2 | I51: 2 | J51: F: NSED drills (A7.2 = 4); CPs tested for earthquake and flooding (A3.3). | K51: Provisional. EOC activation not tested on its own. | L51: Add an annual EOC functional exercise. | M51: =IF(ISNUMBER(I51),(4-I51)*H51*IF(E51="M",1.5,1),"") -> 6 | N51: =IF(M51="","",IF(M51>=9,"High",IF(M51>=4,"Medium","Low"))) -> Medium | O51: =IF(NOT(ISNUMBER(I51)),IF(I51="NA","N/A","Not scored"),IF(E51="M",IF(I51>=3,"Compliant","Non-compliant"),IF(I51>=3,"Meets GP","Below GP"))) -> Non-compliant | P51: EOC Ch.8 | Q51: =IF(ISNUMBER(I51),I51*H51,0) -> 4 | R51: =IF(ISNUMBER(I51),4*H51,0) -> 8 | S51: =IF(ISNUMBER(I51),1,0) -> 1 | T51: =IF(AND(E51="M",ISNUMBER(I51)),1,0) -> 1 | U51: =IF(AND(E51="M",ISNUMBER(I51)),IF(I51>=3,1,0),0) -> 0
A52: B7.4 | B52: B7 | C52: After-action review after each activation with improvement plan tracked | D52: Good practice | E52: GP | F52: AAR; improvement plan | G52: DR | H52: 2 | I52: 2 | J52: F: AARs conducted (A10.6 = 4). | K52: Provisional. EOC improvement plan tracking not sighted. | L52: Track AAR actions in an improvement plan. | M52: =IF(ISNUMBER(I52),(4-I52)*H52*IF(E52="M",1.5,1),"") -> 4 | N52: =IF(M52="","",IF(M52>=9,"High",IF(M52>=4,"Medium","Low"))) -> Medium | O52: =IF(NOT(ISNUMBER(I52)),IF(I52="NA","N/A","Not scored"),IF(E52="M",IF(I52>=3,"Compliant","Non-compliant"),IF(I52>=3,"Meets GP","Below GP"))) -> Below GP | P52: EOC Ch.8 | Q52: =IF(ISNUMBER(I52),I52*H52,0) -> 4 | R52: =IF(ISNUMBER(I52),4*H52,0) -> 8 | S52: =IF(ISNUMBER(I52),1,0) -> 1 | T52: =IF(AND(E52="M",ISNUMBER(I52)),1,0) -> 0 | U52: =IF(AND(E52="M",ISNUMBER(I52)),IF(I52>=3,1,0),0) -> 0
A53: B7.5 | B53: B7 | C53: Dedicated EOC budget for operations, maintenance and upgrades in LDRRMFIP | D53: JMC 2013-1 | E53: M | F53: LDRRMFIP line items | G53: DR | H53: 2 | I53: 3 | J53: DR: 10-Yr Plan (SP-adopted) has an 'Ormoc City DRRM Operations Center Program' line (maintenance, fuel, meals, telco, capacity building); OpCen operates 24/7. | K53: Validate utilisation reports. | L53: Keep the line in each LDRRMFIP. | M53: =IF(ISNUMBER(I53),(4-I53)*H53*IF(E53="M",1.5,1),"") -> 3 | N53: =IF(M53="","",IF(M53>=9,"High",IF(M53>=4,"Medium","Low"))) -> Low | O53: =IF(NOT(ISNUMBER(I53)),IF(I53="NA","N/A","Not scored"),IF(E53="M",IF(I53>=3,"Compliant","Non-compliant"),IF(I53>=3,"Meets GP","Below GP"))) -> Compliant | P53: EOC Ch.9 Sustainability | Q53: =IF(ISNUMBER(I53),I53*H53,0) -> 6 | R53: =IF(ISNUMBER(I53),4*H53,0) -> 8 | S53: =IF(ISNUMBER(I53),1,0) -> 1 | T53: =IF(AND(E53="M",ISNUMBER(I53)),1,0) -> 1 | U53: =IF(AND(E53="M",ISNUMBER(I53)),IF(I53>=3,1,0),0) -> 1
A54: B7.6 | B54: B7 | C54: Equipment maintenance schedule and annual EOC readiness self-check | D54: Good practice; PSCP | E54: GP | F54: PM schedule; checklist | G54: DR, OBS | H54: 1 | I54: 1 | J54: F (A8.3): PMS needs programming. | K54: Provisional. | L54: Set a PM schedule and an annual EOC readiness self-check (EOC Capability Assessment Checklist). | M54: =IF(ISNUMBER(I54),(4-I54)*H54*IF(E54="M",1.5,1),"") -> 3 | N54: =IF(M54="","",IF(M54>=9,"High",IF(M54>=4,"Medium","Low"))) -> Low | O54: =IF(NOT(ISNUMBER(I54)),IF(I54="NA","N/A","Not scored"),IF(E54="M",IF(I54>=3,"Compliant","Non-compliant"),IF(I54>=3,"Meets GP","Below GP"))) -> Below GP | P54: EOC Ch.9 | Q54: =IF(ISNUMBER(I54),I54*H54,0) -> 1 | R54: =IF(ISNUMBER(I54),4*H54,0) -> 4 | S54: =IF(ISNUMBER(I54),1,0) -> 1 | T54: =IF(AND(E54="M",ISNUMBER(I54)),1,0) -> 0 | U54: =IF(AND(E54="M",ISNUMBER(I54)),IF(I54>=3,1,0),0) -> 0

Sheet C_Interface
A1: PART C - INTERFACE INDICATORS (reported separately; not part of the Institutional Maturity Index)
A2: Score in yellow cells only. These items are owned by other offices or partners; they measure whether the CDRRMO has, uses or coordinates them. Same 0-4 rubric and evidence rule. Gap priority uses the Good Practice factor (x1.0). Sources: UNDRR Disaster Resilience Scorecard for Cities, Detailed Level (DRSC) and RA 12287 IRR (2026).
A4: ID | B4: Domain | C4: Indicator | D4: Standard / Policy Reference | E4: Lead Office / Owner | F4: Means of Verification | G4: Method | H4: Weight | I4: Score (0-4/NA) | J4: Evidence Observed | K4: Gap / Remarks | L4: Recommended Action | M4: Gap Priority Score | N4: Priority | O4: Status | P4: Feeds Manual Chapter | Q4: w*score | R4: w*4 | S4: Scored
A5: C1 RISK-INFORMED PLANNING & DEVELOPMENT - use of risk data in city plans, budgets and permits
A6: C1.1 | B6: C1 | C6: Most-probable and most-severe risk scenarios inform CDP/CLUP priorities and the location of major investments | D6: UNDRR DRSC 1.1.1; RA 10121 Sec. 2; DHSUD CLUP guidelines | E6: CPDO | F6: CDP/CLUP; CDRA references | G6: DR, KII | H6: 2 | I6: 2 | J6: DR: CLUP 2017-2027 (110 barangays) has a DRRM-CCA chapter but predates the CDRA. CDRA Final Report rates risk by likelihood and severity per hazard and cites GeoRiskPH damage estimates, but defines no explicit most-probable and most-severe scenarios. | K6: Provisional. Scenarios not defined; CLUP not yet updated with CDRA results; CPDO KII pending. | L6: Define most-probable and most-severe scenarios per priority hazard from the CDRA and GeoRiskPH; use them to set CDP/CLUP priorities and the siting of major investments in the CLUP update (CDRA MDA 1). | M6: =IF(ISNUMBER(I6),(4-I6)*H6,"") -> 4 | N6: =IF(M6="","",IF(M6>=9,"High",IF(M6>=4,"Medium","Low"))) -> Medium | O6: =IF(NOT(ISNUMBER(I6)),IF(I6="NA","N/A","Not scored"),IF(I6>=3,"Meets","Below")) -> Below | P6: MOO Ch.3 | Q6: =IF(ISNUMBER(I6),I6*H6,0) -> 4 | R6: =IF(ISNUMBER(I6),4*H6,0) -> 8 | S6: =IF(ISNUMBER(I6),1,0) -> 1
A7: C1.2 | B7: C1 | C7: DRR/CCA screening step in project and budget approval (LDC, LFC) | D7: UNDRR DRSC 1.3.1; climate change expenditure tagging guidelines | E7: CPDO; City Budget Office | F7: Screening form; LDC/LFC minutes | G7: DR, KII | H7: 1 | I7: 1 | J7: DR: CDRA 6.7.1 proposes 'share of development proposals screened against hazard information' as a future indicator; CLUP 2.5.3 proposes an LDC monitoring team; DRRM sits in the LDC and LFC (A1.7). No screening form or LDC/LFC record sighted. | K7: Provisional: DRRM input to LDC/LFC is informal; no screening step. CPDO and Budget KII pending. | L7: Add a one-page DRR/CCA screening form to LDC/LFC project review (hazard overlay, exposure, design standard, climate expenditure tag), owned by CPDO with CDRRMO sign-off. | M7: =IF(ISNUMBER(I7),(4-I7)*H7,"") | N7: =IF(M7="","",IF(M7>=9,"High",IF(M7>=4,"Medium","Low"))) | O7: =IF(NOT(ISNUMBER(I7)),IF(I7="NA","N/A","Not scored"),IF(I7>=3,"Meets","Below")) -> Not scored | P7: MOO Ch.3 / Ch.5 | Q7: =IF(ISNUMBER(I7),I7*H7,0) -> 0 | R7: =IF(ISNUMBER(I7),4*H7,0) -> 0 | S7: =IF(ISNUMBER(I7),1,0) -> 0
A8: C1.3 | B8: C1 | C8: CDRA estimates losses beyond physical assets: livelihoods and jobs, housing and displacement, agriculture, ecosystems, cultural heritage | D8: UNDRR DRSC 2.2.2; DHSUD/CCC CDRA guidelines | E8: CPDO | F8: CDRA report | G8: DR | H8: 1 | I8: 2 | J8: DR: CDRA Final Report estimates exposure and risk for population (incl. informal settlers, light-material houses and households below poverty), urban use areas (PHP values), agriculture and fisheries production areas, critical-point facilities and lifelines; ecosystems are covered by qualitative impact chains. | K8: Jobs and income losses, ecosystem service losses and cultural heritage (CLUP Heritage Overlay Zone) are not quantified. Desk-review cap of 2. | L8: In the CDRA update, estimate jobs and income lost, displacement days, ecosystem services and heritage assets in the Heritage Overlay Zone; use the 10-Yr Plan business data (establishments, employment) as the baseline. | M8: =IF(ISNUMBER(I8),(4-I8)*H8,"") | N8: =IF(M8="","",IF(M8>=9,"High",IF(M8>=4,"Medium","Low"))) | O8: =IF(NOT(ISNUMBER(I8)),IF(I8="NA","N/A","Not scored"),IF(I8>=3,"Meets","Below")) -> Not scored | P8: MOO Ch.3 | Q8: =IF(ISNUMBER(I8),I8*H8,0) -> 0 | R8: =IF(ISNUMBER(I8),4*H8,0) -> 0 | S8: =IF(ISNUMBER(I8),1,0) -> 0
A9: C1.4 | B9: C1 | C9: Risk-sensitive development guidelines applied in zoning and building permits, based on hazard maps | D9: UNDRR DRSC 2.4.1; CLUP/ZO | E9: CPDO; Zoning Administrator | F9: Guidelines; sample permit reviews | G9: DR, KII | H9: 2 | I9: 2 | J9: DR: ZO (CLUP 2017-2027) requires a locational clearance before a building permit, Water Code easements, a 5-m Marina Fault easement and no-build zones; no flood, landslide or storm-surge overlay. CENRO/CDRRMO sit on the Local Zoning Review Committee. | K9: Provisional. Hazard-based permit review is limited to easements; permit records not sighted. | L9: Add hazard overlay zones and permit conditions (floor elevation, setbacks, geotechnical study) in the ZO update; have the Zoning Administrator check hazard maps for each locational clearance; use the CDRRMO seat on the LZRC to review hazard cases. | M9: =IF(ISNUMBER(I9),(4-I9)*H9,"") -> 4 | N9: =IF(M9="","",IF(M9>=9,"High",IF(M9>=4,"Medium","Low"))) -> Medium | O9: =IF(NOT(ISNUMBER(I9)),IF(I9="NA","N/A","Not scored"),IF(I9>=3,"Meets","Below")) -> Below | P9: MOO Ch.3 | Q9: =IF(ISNUMBER(I9),I9*H9,0) -> 4 | R9: =IF(ISNUMBER(I9),4*H9,0) -> 8 | S9: =IF(ISNUMBER(I9),1,0) -> 1
A10: C2 CRITICAL FACILITIES & LIFELINES - structural safety, utilities, transport
A11: C2.1 | B11: C2 | C11: Structural safety of the EOC, evacuation centers and critical public facilities assessed by the Building Official, with a rapid safety inspection procedure before forecast impact | D11: UNDRR DRSC 4.3.1, 4.4.2; PD 1096; RA 12076; RA 12287 IRR (2026) Rule IV Sec. 4(c)(i) | E11: City Engineer / Building Official | F11: Assessment reports; inspection checklist | G11: DR, OBS | H11: 3 | I11: 1 | J11: DR: CDRA scores critical-point facility vulnerability (e.g., ECs and covered courts rated 'Poor'; most facilities lack landslide mitigation measures); 10-Yr Plan plans retrofitting of 30 ECs. No Building Official structural assessment or pre-impact inspection procedure sighted. | K11: Provisional: a desk vulnerability scoring exists, but no engineering assessment or rapid pre-impact inspection. | L11: Have the Building Official assess the EOC, ECs and critical public facilities, starting with those rated 'Poor' in the CDRA; write a rapid pre-impact inspection checklist used at the PDRA stage. | M11: =IF(ISNUMBER(I11),(4-I11)*H11,"") | N11: =IF(M11="","",IF(M11>=9,"High",IF(M11>=4,"Medium","Low"))) | O11: =IF(NOT(ISNUMBER(I11)),IF(I11="NA","N/A","Not scored"),IF(I11>=3,"Meets","Below")) -> Not scored | P11: EOC Ch.3 / MOO Ch.4 | Q11: =IF(ISNUMBER(I11),I11*H11,0) -> 0 | R11: =IF(ISNUMBER(I11),4*H11,0) -> 0 | S11: =IF(ISNUMBER(I11),1,0) -> 0
A12: C2.2 | B12: C2 | C12: Pre-crisis and priority-restoration arrangements with power, water and telecom providers (load-shedding and water-rationing plans, cell-on-wheels, restoration priority list) | D12: UNDRR DRSC Essential 8; RA 12287 IRR (2026) Rule IV Sec. 4(c)(ii)-(iv) | E12: CDRRMO with utility providers | F12: Agreements; restoration priority list | G12: DR, KII | H12: 2 | I12: 1 | J12: DR: telco restoration MOA planned (10-Yr Plan); CDRA rates lifeline exposure by barangay and notes no lifeline utility is insured; CDRA MDA 2 recommends lifeline dependency maps and restoration priorities. | K12: Provisional. | L12: Sign restoration-priority arrangements with power, water and telecom providers. | M12: =IF(ISNUMBER(I12),(4-I12)*H12,"") -> 6 | N12: =IF(M12="","",IF(M12>=9,"High",IF(M12>=4,"Medium","Low"))) -> Medium | O12: =IF(NOT(ISNUMBER(I12)),IF(I12="NA","N/A","Not scored"),IF(I12>=3,"Meets","Below")) -> Below | P12: MOO Ch.9 / EOC Ch.7 | Q12: =IF(ISNUMBER(I12),I12*H12,0) -> 2 | R12: =IF(ISNUMBER(I12),4*H12,0) -> 8 | S12: =IF(ISNUMBER(I12),1,0) -> 1
A13: C2.3 | B13: C2 | C13: Transport anticipatory actions: pre-inspection of bridges, alternate routes and traffic teams, coordination with seaport and terminal operators | D13: UNDRR DRSC Essential 8; RA 12287 IRR (2026) Rule IV Sec. 10(b) | E13: City Engineer; traffic office; DPWH; port operator | F13: Route plan; inspection list; coordination records | G13: DR, KII | H13: 2 | I13: 1 | J13: DR: CDRA identifies high-consequence lifeline roads (e.g., Macabug Road, Sumangga Road, PNOC roads, Lake Danao Circumferential Road) and Ormoc Port's exposure to storm surge; CDRA MDA 2 recommends identifying critical road segments, bridges and alternate routes. No bridge pre-inspection list, route plan or port coordination protocol sighted. | K13: Provisional desk score pending KII with City Engineer, DPWH and the port. | L13: With DPWH, the City Engineer, the traffic office and the port authority, write transport anticipatory actions: bridge pre-inspection list, alternate routes, traffic teams, port and terminal suspension, and care for stranded passengers. | M13: =IF(ISNUMBER(I13),(4-I13)*H13,"") | N13: =IF(M13="","",IF(M13>=9,"High",IF(M13>=4,"Medium","Low"))) | O13: =IF(NOT(ISNUMBER(I13)),IF(I13="NA","N/A","Not scored"),IF(I13>=3,"Meets","Below")) -> Not scored | P13: EOC Ch.7 | Q13: =IF(ISNUMBER(I13),I13*H13,0) -> 0 | R13: =IF(ISNUMBER(I13),4*H13,0) -> 0 | S13: =IF(ISNUMBER(I13),1,0) -> 0
A14: C3 ECOSYSTEMS & WATERSHED - protective ecosystems and environmental anticipatory action
A15: C3.1 | B15: C3 | C15: Critical protective ecosystems (upper Anilao-Malbasag watershed, upland forest cover, coastal mangroves) identified and monitored as risk-reduction assets | D15: UNDRR DRSC 5.1.1; RA 9729 as amended | E15: CENRO; DENR CENRO | F15: Ecosystem inventory; monitoring reports | G15: DR, KII | H15: 2 | I15: 2 | J15: DR: CLUP/ZO maps Critical Habitat and Key Biodiversity Area overlay zones and protected areas; CDRA impact chains cover forest and coastal (mangrove) ecosystems; watershed characterization (Malbasag, Pagsanga-an, Haubon) and mangrove restoration are 10-Yr Plan PPAs. | K15: Protective ecosystems are identified in plans but not monitored as risk-reduction assets. Desk-review cap of 2. | L15: Complete the watershed study; monitor forest cover in the upper Anilao-Malbasag watershed and mangrove area each year and report it to the CDRRMC (CDRA MDA 3 and 5). | M15: =IF(ISNUMBER(I15),(4-I15)*H15,"") -> 6 | N15: =IF(M15="","",IF(M15>=9,"High",IF(M15>=4,"Medium","Low"))) -> Medium | O15: =IF(NOT(ISNUMBER(I15)),IF(I15="NA","N/A","Not scored"),IF(I15>=3,"Meets","Below")) -> Below | P15: MOO Ch.3 | Q15: =IF(ISNUMBER(I15),I15*H15,0) -> 2 | R15: =IF(ISNUMBER(I15),4*H15,0) -> 8 | S15: =IF(ISNUMBER(I15),1,0) -> 1
A16: C3.2 | B16: C3 | C16: Arrangements with neighbouring LGUs and DENR where watersheds or protective ecosystems extend beyond city limits | D16: UNDRR DRSC 5.3.1, 5.3.2; RA 7160 Sec. 33 | E16: CENRO | F16: MOAs; watershed council records | G16: DR, KII | H16: 1 | I16: 1 | J16: DR: watershed PPAs list ENRO, DENR and EDC as partners. | K16: Provisional. | L16: Formalise watershed arrangements with DENR, EDC and neighbouring LGUs. | M16: =IF(ISNUMBER(I16),(4-I16)*H16,"") -> 3 | N16: =IF(M16="","",IF(M16>=9,"High",IF(M16>=4,"Medium","Low"))) -> Low | O16: =IF(NOT(ISNUMBER(I16)),IF(I16="NA","N/A","Not scored"),IF(I16>=3,"Meets","Below")) -> Below | P16: MOO Ch.9 | Q16: =IF(ISNUMBER(I16),I16*H16,0) -> 1 | R16: =IF(ISNUMBER(I16),4*H16,0) -> 4 | S16: =IF(ISNUMBER(I16),1,0) -> 1
A17: C3.3 | B17: C3 | C17: Environmental anticipatory actions: declogging of waterways and drainage, slope stabilization, safe debris and carcass disposal | D17: RA 12287 IRR (2026) Rule IV Sec. 10(d) | E17: CENRO; City Engineer; GSO | F17: Protocol; work orders from last season | G17: DR, KII | H17: 2 | I17: 1 | J17: DR: construction-firm MOA for debris clearing and a Drainage and Sewerage Master Plan are planned PPAs (10-Yr Plan); ZO sets river easements. | K17: Provisional. | L17: Write the declogging and debris protocol. | M17: =IF(ISNUMBER(I17),(4-I17)*H17,"") -> 6 | N17: =IF(M17="","",IF(M17>=9,"High",IF(M17>=4,"Medium","Low"))) -> Medium | O17: =IF(NOT(ISNUMBER(I17)),IF(I17="NA","N/A","Not scored"),IF(I17>=3,"Meets","Below")) -> Below | P17: EOC Ch.2 | Q17: =IF(ISNUMBER(I17),I17*H17,0) -> 2 | R17: =IF(ISNUMBER(I17),4*H17,0) -> 8 | S17: =IF(ISNUMBER(I17),1,0) -> 1
A18: C4 SECTORAL ANTICIPATORY ACTION - health, education, agri-fisheries, prices
A19: C4.1 | B19: C4 | C19: Health anticipatory action: Health Cluster activation, facility service-continuity and surge plans, prepositioned commodities, health emergency response teams on standby | D19: RA 12287 IRR (2026) Rule IV Sec. 9 | E19: City Health Office; hospitals | F19: Health AA plan; surge plans | G19: DR, KII | H19: 3 | I19: 1 | J19: DR: HEMS/ESU ordinance and DRRM-H plan planned (10-Yr Plan). | K19: Provisional. | L19: Prepare the health AA plan with CHO and hospitals. | M19: =IF(ISNUMBER(I19),(4-I19)*H19,"") -> 9 | N19: =IF(M19="","",IF(M19>=9,"High",IF(M19>=4,"Medium","Low"))) -> High | O19: =IF(NOT(ISNUMBER(I19)),IF(I19="NA","N/A","Not scored"),IF(I19>=3,"Meets","Below")) -> Below | P19: EOC Ch.4 | Q19: =IF(ISNUMBER(I19),I19*H19,0) -> 3 | R19: =IF(ISNUMBER(I19),4*H19,0) -> 12 | S19: =IF(ISNUMBER(I19),1,0) -> 1
A20: C4.2 | B20: C4 | C20: Education anticipatory action: schools' AA plans and learning-continuity modalities | D20: RA 12287 IRR (2026) Rule IV Sec. 10(a); RA 10821 | E20: DepEd Schools Division of Ormoc City | F20: AA plans; learning continuity plan | G20: DR, KII | H20: 2 | I20: 1 | J20: DR: school DRRM coordinator training is a 10-Yr Plan PPA; DepEd SDO school AA plans and learning-continuity modalities not sighted. | K20: Provisional desk score pending DepEd KII. | L20: Ask DepEd SDO Ormoc for school contingency/AA plans and learning-continuity modalities; agree triggers for class suspension and school use as ECs (link A1.5, A6.2). | M20: =IF(ISNUMBER(I20),(4-I20)*H20,"") | N20: =IF(M20="","",IF(M20>=9,"High",IF(M20>=4,"Medium","Low"))) | O20: =IF(NOT(ISNUMBER(I20)),IF(I20="NA","N/A","Not scored"),IF(I20>=3,"Meets","Below")) -> Not scored | P20: EOC Ch.4 | Q20: =IF(ISNUMBER(I20),I20*H20,0) -> 0 | R20: =IF(ISNUMBER(I20),4*H20,0) -> 0 | S20: =IF(ISNUMBER(I20),1,0) -> 0
A21: C4.3 | B21: C4 | C21: Agri-fisheries anticipatory action using RSBSA, FishR and livestock registries; early action guidelines on storage, inputs and animal health | D21: RA 12287 IRR (2026) Rule IV Sec. 8 | E21: City Agriculture Office; City Veterinary Office | F21: Guidelines; registry extracts | G21: DR, KII | H21: 2 | I21: 1 | J21: DR: 5,470 farmers (RSBSA 2021) and 5,295 fisherfolk (FishR) registered (10-Yr Plan); buffer seed stock and storage facilities are PPAs; CDRA rates production-area risk by barangay. No early action guidelines sighted. | K21: Provisional: registries exist, but no agri-fisheries early action guidelines. CAO/CVO KII pending. | L21: With CAO and CVO, draft agri-fisheries early action guidelines (early harvest advisories, seed and input prepositioning, livestock evacuation, animal health) using RSBSA/FishR lists and the CDRA high-risk production areas. | M21: =IF(ISNUMBER(I21),(4-I21)*H21,"") | N21: =IF(M21="","",IF(M21>=9,"High",IF(M21>=4,"Medium","Low"))) | O21: =IF(NOT(ISNUMBER(I21)),IF(I21="NA","N/A","Not scored"),IF(I21>=3,"Meets","Below")) -> Not scored | P21: EOC Ch.4 | Q21: =IF(ISNUMBER(I21),I21*H21,0) -> 0 | R21: =IF(ISNUMBER(I21),4*H21,0) -> 0 | S21: =IF(ISNUMBER(I21),1,0) -> 0
A22: C4.4 | B22: C4 | C22: Pre-impact price monitoring and anti-profiteering of basic goods | D22: RA 12287 IRR (2026) Rule IV Sec. 10(c); RA 7581 (Price Act) | E22: DTI Leyte; city market office | F22: Monitoring reports | G22: DR, KII | H22: 1 | I22: 1 | J22: DR: no pre-impact price monitoring arrangement with DTI found; price freeze is treated only as a post-declaration measure under the State of Calamity protocol (A1.6). | K22: Provisional desk score pending DTI KII. | L22: Agree with DTI Leyte and the city market office to monitor basic-goods prices from the PDRA stage and report them to the EOC (RA 7581). | M22: =IF(ISNUMBER(I22),(4-I22)*H22,"") | N22: =IF(M22="","",IF(M22>=9,"High",IF(M22>=4,"Medium","Low"))) | O22: =IF(NOT(ISNUMBER(I22)),IF(I22="NA","N/A","Not scored"),IF(I22>=3,"Meets","Below")) -> Not scored | P22: EOC Ch.4 | Q22: =IF(ISNUMBER(I22),I22*H22,0) -> 0 | R22: =IF(ISNUMBER(I22),4*H22,0) -> 0 | S22: =IF(ISNUMBER(I22),1,0) -> 0
A23: C5 ECONOMIC CONTINUITY - business continuity outreach
A24: C5.1 | B24: C5 | C24: Business continuity outreach to local businesses based on shared hazard scenarios (outreach only; no mandate implied) | D24: UNDRR DRSC 7.3.2 | E24: CDRRMO with Chamber of Commerce | F24: Outreach records; materials | G24: DR, KII | H24: 1 | I24: 1 | J24: DR: 10-Yr Plan PPA: policy granting incentives to MSMEs with business continuity plans; the Chamber of Commerce sits on the Local Zoning Review Committee (CLUP). No outreach records. | K24: Provisional: outreach not yet started; Chamber KII pending. | L24: Run BCP outreach with the Chamber using CDRA hazard scenarios; track the number of MSMEs with BCPs as the 10-Yr Plan indicator. | M24: =IF(ISNUMBER(I24),(4-I24)*H24,"") | N24: =IF(M24="","",IF(M24>=9,"High",IF(M24>=4,"Medium","Low"))) | O24: =IF(NOT(ISNUMBER(I24)),IF(I24="NA","N/A","Not scored"),IF(I24>=3,"Meets","Below")) -> Not scored | P24: MOO Ch.9 | Q24: =IF(ISNUMBER(I24),I24*H24,0) -> 0 | R24: =IF(ISNUMBER(I24),4*H24,0) -> 0 | S24: =IF(ISNUMBER(I24),1,0) -> 0

Sheet Action_Plan
A1: IMPROVEMENT ACTION PLAN (feeds the Manual of Operations drafting)
A2: Grey columns pull from the assessment sheets. Filter 'Priority' = High first. Fill yellow columns during the validation workshop. Part C rows (Type = IF) pre-fill the lead office; confirm it in the workshop.
A3: ID | B3: Indicator | C3: Type | D3: Score | E3: Priority | F3: Compliance | G3: Recommended Action (from assessment) | H3: Responsible Office / Person | I3: Target Date | J3: Resources / Budget Source | K3: Manual Chapter | L3: Status
A4: =A_CDRRMO!A6 -> A1.1 | B4: =A_CDRRMO!C6 -> City ordinance/EO creating the CDRRMO as a regular office (not ad hoc), with defined functions mirroring RA 10121 Sec. 12(c) | C4: =A_CDRRMO!E6 -> M | D4: =IF(A_CDRRMO!I6="","",A_CDRRMO!I6) -> 2 | E4: =A_CDRRMO!N6 -> High | F4: =A_CDRRMO!O6 -> Non-compliant | G4: =IF(A_CDRRMO!L6="","",A_CDRRMO!L6) -> Draft an ordinance creating the CDRRMO as a regular department with Admin & Training, Research & Planning and Operations & Warning divisions and their functions (RA 10121 Sec. 12(c); JMC 2014-1). Attach the organogram and staffing pattern from MOO Ch.2. | H4: CDRRMO Head; City Legal Office; SP Committee on DRRM | I4: Q1 2027 (SP filing) | J4: No cost (legislative); staffing cost under A2.3 | K4: =A_CDRRMO!P6 -> MOO Ch.1 Legal & Institutional Framework | L4: Not started
A5: =A_CDRRMO!A7 -> A1.2 | B5: =A_CDRRMO!C7 -> CDRRMC constituted with complete membership per RA 10121 Sec. 11 (incl. CSO and private sector reps) | C5: =A_CDRRMO!E7 -> M | D5: =IF(A_CDRRMO!I7="","",A_CDRRMO!I7) -> 2 | E5: =A_CDRRMO!N7 -> Medium | F5: =A_CDRRMO!O7 -> Non-compliant | G5: =IF(A_CDRRMO!L7="","",A_CDRRMO!L7) -> Issue an updated EO on CDRRMC composition listing every RA 10121 Sec. 11 seat by office, with at least 4 accredited CSOs and a private-sector seat (e.g., EDC). Record the roster as an MOO Ch.1 annex and review it yearly. | H5: Mayor's Office; CDRRMO (secretariat) | I5: Dec 2026 | J5: No cost | K5: =A_CDRRMO!P7 -> MOO Ch.1 | L5: Not started
A6: =A_CDRRMO!A8 -> A1.3 | B6: =A_CDRRMO!C8 -> CDRRMC meets at least quarterly (and as needed); minutes and resolutions on file | C6: =A_CDRRMO!E8 -> M | D6: =IF(A_CDRRMO!I8="","",A_CDRRMO!I8) -> 4 | E6: =A_CDRRMO!N8 -> Low | F6: =A_CDRRMO!O8 -> Compliant | G6: =IF(A_CDRRMO!L8="","",A_CDRRMO!L8) -> Keep the quarterly schedule; add a standing agenda item on RA 12287 readiness and the action plan from this assessment. Use the minutes template in MOO Ch.1. | H6: CDRRMO (secretariat) | I6: Quarterly | J6: LDRRMF 70% (meetings) | K6: =A_CDRRMO!P8 -> MOO Ch.1 | L6: Ongoing
A7: =A_CDRRMO!A9 -> A1.4 | B7: =A_CDRRMO!C9 -> CDRRMO serves as CDRRMC secretariat with documented secretariat procedures | C7: =A_CDRRMO!E9 -> M | D7: =IF(A_CDRRMO!I9="","",A_CDRRMO!I9) -> 4 | E7: =A_CDRRMO!N9 -> Low | F7: =A_CDRRMO!O9 -> Compliant | G7: =IF(A_CDRRMO!L9="","",A_CDRRMO!L9) -> Write the secretariat procedure (notice, agenda, quorum, minutes, resolutions, tracking) into MOO Ch.2. | H7: CDRRMO Admin & Training | I7: Jan 2027 (with MOP) | J7: No cost | K7: =A_CDRRMO!P9 -> MOO Ch.2 Office Organization | L7: Ongoing
A8: =A_CDRRMO!A10 -> A1.5 | B8: =A_CDRRMO!C10 -> Local DRRM-related ordinances in force (e.g., pre-emptive/forced evacuation, no-build zones, hazard-based zoning) | C8: =A_CDRRMO!E10 -> GP | D8: =IF(A_CDRRMO!I10="","",A_CDRRMO!I10) -> 3 | E8: =A_CDRRMO!N10 -> Low | F8: =A_CDRRMO!O10 -> Meets GP | G8: =IF(A_CDRRMO!L10="","",A_CDRRMO!L10) -> Amend the evacuation ordinance to add procedural statements: triggers tied to the warning-action matrix (A6.2), authority to order, assistance to PWD/elderly, livestock and pets (RA 12287 IRR Rule IV), and enforcement. Add granular (barangay/school-level) class and work suspension. | H8: CDRRMO; City Legal Office; SP | I8: Q2 2027 | J8: No cost | K8: =A_CDRRMO!P10 -> MOO Ch.1 | L8: Not started
A9: =A_CDRRMO!A11 -> A1.6 | B9: =A_CDRRMO!C11 -> Protocol for declaring a State of Calamity, incl. CDRRMC recommendation steps and post-declaration measures (State of Imminent Disaster now assessed separately under A1.8) | C9: =A_CDRRMO!E11 -> M | D9: =IF(A_CDRRMO!I11="","",A_CDRRMO!I11) -> 3 | E9: =A_CDRRMO!N11 -> Medium | F9: =A_CDRRMO!O11 -> Compliant | G9: =IF(A_CDRRMO!L11="","",A_CDRRMO!L11) -> Write a State of Calamity protocol in MOO Ch.1: criteria (NDRRMC Memo on SoC criteria), RDANA/PDNA basis, CDRRMC recommendation, SP resolution template, post-declaration measures (price freeze, QRF use, reporting). Add a note on how to read national/regional declarations that affect Ormoc. | H9: CDRRMO Research & Planning; City Legal Office | I9: Jan 2027 (with MOP) | J9: No cost | K9: =A_CDRRMO!P11 -> MOO Ch.1 | L9: Ongoing
A10: =A_CDRRMO!A12 -> A1.7 | B10: =A_CDRRMO!C12 -> DRRM is represented in City Development Council and Local Finance Committee deliberations | C10: =A_CDRRMO!E12 -> GP | D10: =IF(A_CDRRMO!I12="","",A_CDRRMO!I12) -> 4 | E10: =A_CDRRMO!N12 -> Low | F10: =A_CDRRMO!O12 -> Meets GP | G10: =IF(A_CDRRMO!L12="","",A_CDRRMO!L12) -> Keep representation; use the LFC seat to secure the AA line (A4.6) and the EOC budget (B7.5) in the FY2028 budget call. | H10: CDRRMO Head | I10: Budget call 2027 | J10: No cost | K10: =A_CDRRMO!P12 -> MOO Ch.1 | L10: Ongoing
A11: =A_CDRRMO!A13 -> A1.8 | B11: =A_CDRRMO!C13 -> State of Imminent Disaster procedure: CDRRMC coordinates with RDRRMC VIII when the pre-disaster risk assessment shows reasonable certainty of severe impact; request format to RDRRMC (24-hour reply); Mayor's EO template; adoption rule when the Region (or Province, applicability to an ICC to be confirmed) is declared; lifting grounds and authority | C11: =A_CDRRMO!E13 -> M | D11: =IF(A_CDRRMO!I13="","",A_CDRRMO!I13) -> 1 | E11: =A_CDRRMO!N13 -> High | F11: =A_CDRRMO!O13 -> Non-compliant | G11: =IF(A_CDRRMO!L13="","",A_CDRRMO!L13) -> Draft the State of Imminent Disaster procedure (IRR Rule II Sec. 6; Rule III Secs. 2-4): PDRA trigger, CDRRMC resolution, request to RDRRMC VIII, Mayor's EO template, adoption rule, lifting and the 45-day report (A10.8). Confirm with OCD VIII whether a Provincial declaration applies to an ICC. Walk it through in a tabletop to reach score 3. | H11: CDRRMO Head; City Legal Office; Mayor's Office | I11: Jan 2027 (with MOP) | J11: No cost | K11: =A_CDRRMO!P13 -> MOO Ch.1 / EOC Ch.2 | L11: Ongoing
A12: =A_CDRRMO!A15 -> A2.1 | B12: =A_CDRRMO!C15 -> Organizational structure follows JMC 2014-1: Head + Administration & Training, Research & Planning, and Operations & Warning divisions | C12: =A_CDRRMO!E15 -> M | D12: =IF(A_CDRRMO!I15="","",A_CDRRMO!I15) -> 2 | E12: =A_CDRRMO!N15 -> High | F12: =A_CDRRMO!O15 -> Non-compliant | G12: =IF(A_CDRRMO!L15="","",A_CDRRMO!L15) -> Adopt the JMC 2014-1 organogram (Head + 3 divisions) with separate normal-operations and response (EOC) roles, through the ordinance in A1.1 and MOO Ch.2. | H12: CDRRMO Head; HRMO | I12: Jan 2027 (with MOP) | J12: No cost | K12: =A_CDRRMO!P15 -> MOO Ch.2 Office Organization | L12: Ongoing
A13: =A_CDRRMO!A16 -> A2.2 | B13: =A_CDRRMO!C16 -> CDRRMO Head is a permanent plantilla position filled by a qualified appointee | C13: =A_CDRRMO!E16 -> M | D13: =IF(A_CDRRMO!I16="","",A_CDRRMO!I16) -> 4 | E13: =A_CDRRMO!N16 -> Low | F13: =A_CDRRMO!O16 -> Compliant | G13: =IF(A_CDRRMO!L16="","",A_CDRRMO!L16) -> Maintain; document succession (OIC order of precedence) in MOO Ch.2. | H13: HRMO; CDRRMO Head | I13: Jan 2027 (succession in MOO Ch.2) | J13: No cost | K13: =A_CDRRMO!P16 -> MOO Ch.2 | L13: Ongoing
A14: =A_CDRRMO!A17 -> A2.3 | B14: =A_CDRRMO!C17 -> Minimum plantilla positions per JMC 2014-1 created and filled (ratio of filled/required) | C14: =A_CDRRMO!E17 -> M | D14: =IF(A_CDRRMO!I17="","",A_CDRRMO!I17) -> 2 | E14: =A_CDRRMO!N17 -> High | F14: =A_CDRRMO!O17 -> Non-compliant | G14: =IF(A_CDRRMO!L17="","",A_CDRRMO!L17) -> Get the Plantilla of Personnel and vacancy list; compute filled/required. Request creation and funding of the 10 planned items in the FY2028 budget, prioritising Operations & Warning (24/7 OpCen) and Research & Planning (GIS). | H14: CDRRMO Head; HRMO; City Budget Office | I14: FY2028 budget | J14: General Fund (PS) | K14: =A_CDRRMO!P17 -> MOO Ch.2 | L14: Not started
A15: =A_CDRRMO!A18 -> A2.4 | B15: =A_CDRRMO!C18 -> Job descriptions/position descriptions defined for every position, aligned to RA 10121 functions | C15: =A_CDRRMO!E18 -> M | D15: =IF(A_CDRRMO!I18="","",A_CDRRMO!I18) -> 2 | E15: =A_CDRRMO!N18 -> Medium | F15: =A_CDRRMO!O18 -> Non-compliant | G15: =IF(A_CDRRMO!L18="","",A_CDRRMO!L18) -> Write position descriptions for every CDRRMO and EOC role (MOO annex), aligned to RA 10121 functions; link them to IPCR/OPCR targets. | H15: CDRRMO Admin & Training; HRMO | I15: Jan 2027 (with MOP) | J15: No cost | K15: =A_CDRRMO!P18 -> MOO Ch.2 / Annex JDs | L15: Ongoing
A16: =A_CDRRMO!A19 -> A2.5 | B16: =A_CDRRMO!C19 -> 24/7 operations capability with documented shift roster (Operations Center/Duty officers) | C16: =A_CDRRMO!E19 -> M | D16: =IF(A_CDRRMO!I19="","",A_CDRRMO!I19) -> 1 | E16: =A_CDRRMO!N19 -> High | F16: =A_CDRRMO!O19 -> Non-compliant | G16: =IF(A_CDRRMO!L19="","",A_CDRRMO!L19) -> Write the OpCen normal-operations SOP (shifts, handover, monitoring, logbook, reporting times 6AM/6PM per RDRRMC8 Res. 12-006) as EOC Manual Ch.4/Ch.5; have it approved and keep 3 months of rosters as proof of use. | H16: CDRRMO Operations & Warning | I16: Jan 2027 (with MOP) | J16: MOP engagement | K16: =A_CDRRMO!P19 -> MOO Ch.4 Operations / EOC Ch.4 | L16: Ongoing
A17: =A_CDRRMO!A20 -> A2.6 | B17: =A_CDRRMO!C20 -> Training needs analysis done and competency-based training plan for staff (ICS, BLS/SFA, WASAR, CSSR, MOSAR, EOC, PDNA, GIS) | C17: =A_CDRRMO!E20 -> GP | D17: =IF(A_CDRRMO!I20="","",A_CDRRMO!I20) -> 1 | E17: =A_CDRRMO!N20 -> Medium | F17: =A_CDRRMO!O20 -> Below GP | G17: =IF(A_CDRRMO!L20="","",A_CDRRMO!L20) -> Run a TNA for all CDRRMO/EOC staff against the competency list (ICS, BLS/SFA, WASAR, CSSR, EOC, PDNA, GIS); produce a 3-year training plan with OCD VIII courses in MOO Ch.6. | H17: CDRRMO Admin & Training | I17: Q1 2027 | J17: LDRRMF 70% (capacity building) | K17: =A_CDRRMO!P20 -> MOO Ch.6 Capacity Development | L17: Not started
A18: =A_CDRRMO!A21 -> A2.7 | B18: =A_CDRRMO!C21 -> Personnel welfare and safety: insurance, hazard pay, PPE, psychosocial support for responders | C18: =A_CDRRMO!E21 -> M | D18: =IF(A_CDRRMO!I21="","",A_CDRRMO!I21) -> 1 | E18: =A_CDRRMO!N21 -> High | F18: =A_CDRRMO!O21 -> Non-compliant | G18: =IF(A_CDRRMO!L21="","",A_CDRRMO!L21) -> Adopt a responder welfare policy: group accident insurance (staff and accredited volunteers), PPE issue list, rest cycles, MHPSS referral with CHO (RA 11036). Memo 131 also requires EOC personnel welfare. | H18: CDRRMO; HRMO; CHO | I18: FY2027 AIP | J18: LDRRMF 70% | K18: =A_CDRRMO!P21 -> MOO Ch.2 / Ch.4 | L18: Not started
A19: =A_CDRRMO!A22 -> A2.8 | B19: =A_CDRRMO!C22 -> Volunteer/auxiliary responder management system (accreditation, registry, deployment, insurance), incl. mobilization of ACDVs for anticipatory action | C19: =A_CDRRMO!E22 -> GP | D19: =IF(A_CDRRMO!I22="","",A_CDRRMO!I22) -> 3 | E19: =A_CDRRMO!N22 -> Low | F19: =A_CDRRMO!O22 -> Meets GP | G19: =IF(A_CDRRMO!L22="","",A_CDRRMO!L22) -> Formalise the ACDV registry with accreditation, insurance and deployment rules, and add AA tasks for ACDVs. | H19: CDRRMO Admin & Training | I19: Q2 2027 | J19: LDRRMF 70% | K19: =A_CDRRMO!P22 -> MOO Ch.6 | L19: Ongoing
A20: =A_CDRRMO!A23 -> A2.9 | B20: =A_CDRRMO!C23 -> Anticipatory action focal person designated in the CDRRMO, with AA training for staff, BDRRMCs, ACDVs and partner CSOs (incl. community-based early warning and early action) | C20: =A_CDRRMO!E23 -> M | D20: =IF(A_CDRRMO!I23="","",A_CDRRMO!I23) -> 0 | E20: =A_CDRRMO!N23 -> High | F20: =A_CDRRMO!O23 -> Non-compliant | G20: =IF(A_CDRRMO!L23="","",A_CDRRMO!L23) -> Designate an AA focal person by office order and enrol them, BDRRMC officers, ACDVs and partner CSOs in AA training when OCD VIII cascades the IRR. | H20: CDRRMO Head | I20: Dec 2026 | J20: No cost; training via OCD VIII | K20: =A_CDRRMO!P23 -> MOO Ch.2 / Ch.6 | L20: Not started
A21: =A_CDRRMO!A24 -> A2.10 | B21: =A_CDRRMO!C24 -> Inventory of DRRM-relevant skills across the CDRRMO, partner offices and barangays (SAR, engineering, logistics, GIS, PDNA, MHPSS) updated within the last 12 months | C21: =A_CDRRMO!E24 -> GP | D21: =IF(A_CDRRMO!I24="","",A_CDRRMO!I24) -> 1 | E21: =A_CDRRMO!N24 -> Low | F21: =A_CDRRMO!O24 -> Below GP | G21: =IF(A_CDRRMO!L24="","",A_CDRRMO!L24) -> Build a skills inventory (SAR, engineering, logistics, GIS, PDNA, MHPSS) covering CDRRMO, CDRRMC offices and BDRRMCs; update it every 12 months (UNDRR DRSC 6.1.1). | H21: CDRRMO Admin & Training | I21: Q1 2027 | J21: No cost | K21: =A_CDRRMO!P24 -> MOO Ch.6 | L21: Not started
A22: =A_CDRRMO!A26 -> A3.1 | B22: =A_CDRRMO!C26 -> Local DRRM Plan (LDRRMP) current, approved by Sanggunian, aligned with NDRRMP 2020-2030 and Sendai Framework | C22: =A_CDRRMO!E26 -> M | D22: =IF(A_CDRRMO!I26="","",A_CDRRMO!I26) -> 4 | E22: =A_CDRRMO!N26 -> Low | F22: =A_CDRRMO!O26 -> Compliant | G22: =IF(A_CDRRMO!L26="","",A_CDRRMO!L26) -> Maintain; in the next update correct the barangay count to 85 and add RA 12287 anticipatory action PPAs. | H22: CDRRMO Research & Planning | I22: Next LDRRMP review | J22: LDRRMF 70% (planning) | K22: =A_CDRRMO!P26 -> MOO Ch.3 Planning | L22: Ongoing
A23: =A_CDRRMO!A27 -> A3.2 | B23: =A_CDRRMO!C27 -> DRR-CCA mainstreamed in CDP, CLUP, ELA and LCCAP (hazard data used in land use and investment decisions) | C23: =A_CDRRMO!E27 -> M | D23: =IF(A_CDRRMO!I27="","",A_CDRRMO!I27) -> 3 | E23: =A_CDRRMO!N27 -> Low | F23: =A_CDRRMO!O27 -> Compliant | G23: =IF(A_CDRRMO!L27="","",A_CDRRMO!L27) -> Review mainstreaming in CDP, CLUP, ELA and LCCAP during the CLUP update; check that CDRA results drive land-use and AIP decisions (see C1.1-C1.4). | H23: CPDO; CDRRMO Research & Planning | I23: With CLUP update | J23: General Fund (CPDO) | K23: =A_CDRRMO!P27 -> MOO Ch.3 | L23: Ongoing
A24: =A_CDRRMO!A28 -> A3.3 | B24: =A_CDRRMO!C28 -> Hazard-specific Contingency Plans for priority hazards (flood/flash flood, landslide, earthquake/tsunami, tropical cyclone, industrial/geothermal), updated and tested | C24: =A_CDRRMO!E28 -> M | D24: =IF(A_CDRRMO!I28="","",A_CDRRMO!I28) -> 3 | E24: =A_CDRRMO!N28 -> Medium | F24: =A_CDRRMO!O28 -> Compliant | G24: =IF(A_CDRRMO!L28="","",A_CDRRMO!L28) -> Prepare CPs for the remaining priority hazards and test each by tabletop; add AA annexes (A8.8) and pre-disaster recovery annex (A9.5). | H24: CDRRMO Research & Planning; response cluster leads | I24: 2027 | J24: LDRRMF 70% | K24: =A_CDRRMO!P28 -> MOO Ch.3 / EOC Ch.3 | L24: Ongoing
A25: =A_CDRRMO!A29 -> A3.4 | B25: =A_CDRRMO!C29 -> Public Service Continuity Plan (PSCP) prepared covering CDRRMO and essential city services | C25: =A_CDRRMO!E29 -> M | D25: =IF(A_CDRRMO!I29="","",A_CDRRMO!I29) -> 2 | E25: =A_CDRRMO!N29 -> Medium | F25: =A_CDRRMO!O29 -> Non-compliant | G25: =IF(A_CDRRMO!L29="","",A_CDRRMO!L29) -> Complete the PSCP using the PSCP Guidebook: essential functions, BIA, alternate site (links to B2.7), orders of succession, vital records. Exercise it once. | H25: CDRRMO Research & Planning; all city offices | I25: Q2 2027 | J25: LDRRMF 70% | K25: =A_CDRRMO!P29 -> MOO Ch.3 / EOC Ch.7 | L25: Ongoing
